<Annotations>
	<Annotation Id="1" Name="Ivan" ReadOnly="0" NameReadOnly="0" LineColorReadOnly="0" Incremental="0" Type="4" LineColor="255" Visible="1" Selected="1" MarkupImagePath="" MacroName="">
		<Attributes/>
		<Regions>
			<RegionAttributeHeaders>
				<AttributeHeader Id="9999" Name="Region" ColumnWidth="-1"/>
				<AttributeHeader Id="9997" Name="Length" ColumnWidth="-1"/>
				<AttributeHeader Id="9996" Name="Area" ColumnWidth="-1"/>
				<AttributeHeader Id="9998" Name="Text" ColumnWidth="-1"/>
				<AttributeHeader Id="1" Name="Description" ColumnWidth="-1"/>
			</RegionAttributeHeaders>
			<Region Id="1" Type="0" Zoom="0.630000" Selected="1" ImageLocation="" ImageFocus="-1" Length="4189.4" Area="627196.5" Text="" NegativeROA="0" InputRegionId="0" Analyze="1" DisplayId="1">
				<Attributes/>
				<Vertices>
					<Vertex X="13" Y="475" Z="0"/>
					<Vertex X="13" Y="477" Z="0"/>
					<Vertex X="12" Y="478" Z="0"/>
					<Vertex X="12" Y="480" Z="0"/>
					<Vertex X="13" Y="480" Z="0"/>
					<Vertex X="13" Y="481" Z="0"/>
					<Vertex X="13" Y="483" Z="0"/>
					<Vertex X="15" Y="483" Z="0"/>
					<Vertex X="16" Y="483" Z="0"/>
					<Vertex X="16" Y="485" Z="0"/>
					<Vertex X="18" Y="485" Z="0"/>
					<Vertex X="18" Y="486" Z="0"/>
					<Vertex X="19" Y="486" Z="0"/>
					<Vertex X="21" Y="488" Z="0"/>
					<Vertex X="23" Y="488" Z="0"/>
					<Vertex X="23" Y="489" Z="0"/>
					<Vertex X="24" Y="489" Z="0"/>
					<Vertex X="24" Y="491" Z="0"/>
					<Vertex X="26" Y="491" Z="0"/>
					<Vertex X="27" Y="491" Z="0"/>
					<Vertex X="27" Y="493" Z="0"/>
					<Vertex X="29" Y="493" Z="0"/>
					<Vertex X="31" Y="493" Z="0"/>
					<Vertex X="31" Y="494" Z="0"/>
					<Vertex X="32" Y="494" Z="0"/>
					<Vertex X="32" Y="496" Z="0"/>
					<Vertex X="34" Y="496" Z="0"/>
					<Vertex X="35" Y="496" Z="0"/>
					<Vertex X="35" Y="497" Z="0"/>
					<Vertex X="37" Y="497" Z="0"/>
					<Vertex X="37" Y="499" Z="0"/>
					<Vertex X="39" Y="499" Z="0"/>
					<Vertex X="40" Y="499" Z="0"/>
					<Vertex X="40" Y="500" Z="0"/>
					<Vertex X="42" Y="500" Z="0"/>
					<Vertex X="42" Y="502" Z="0"/>
					<Vertex X="43" Y="502" Z="0"/>
					<Vertex X="45" Y="502" Z="0"/>
					<Vertex X="45" Y="504" Z="0"/>
					<Vertex X="46" Y="504" Z="0"/>
					<Vertex X="46" Y="505" Z="0"/>
					<Vertex X="48" Y="505" Z="0"/>
					<Vertex X="50" Y="505" Z="0"/>
					<Vertex X="50" Y="507" Z="0"/>
					<Vertex X="51" Y="507" Z="0"/>
					<Vertex X="51" Y="508" Z="0"/>
					<Vertex X="53" Y="508" Z="0"/>
					<Vertex X="54" Y="508" Z="0"/>
					<Vertex X="54" Y="510" Z="0"/>
					<Vertex X="54" Y="512" Z="0"/>
					<Vertex X="56" Y="512" Z="0"/>
					<Vertex X="58" Y="512" Z="0"/>
					<Vertex X="58" Y="513" Z="0"/>
					<Vertex X="59" Y="513" Z="0"/>
					<Vertex X="59" Y="515" Z="0"/>
					<Vertex X="61" Y="515" Z="0"/>
					<Vertex X="62" Y="515" Z="0"/>
					<Vertex X="62" Y="516" Z="0"/>
					<Vertex X="64" Y="516" Z="0"/>
					<Vertex X="64" Y="518" Z="0"/>
					<Vertex X="66" Y="518" Z="0"/>
					<Vertex X="66" Y="520" Z="0"/>
					<Vertex X="67" Y="520" Z="0"/>
					<Vertex X="67" Y="521" Z="0"/>
					<Vertex X="69" Y="521" Z="0"/>
					<Vertex X="70" Y="521" Z="0"/>
					<Vertex X="70" Y="523" Z="0"/>
					<Vertex X="70" Y="524" Z="0"/>
					<Vertex X="72" Y="524" Z="0"/>
					<Vertex X="73" Y="524" Z="0"/>
					<Vertex X="73" Y="526" Z="0"/>
					<Vertex X="75" Y="526" Z="0"/>
					<Vertex X="75" Y="527" Z="0"/>
					<Vertex X="77" Y="527" Z="0"/>
					<Vertex X="77" Y="529" Z="0"/>
					<Vertex X="78" Y="529" Z="0"/>
					<Vertex X="80" Y="529" Z="0"/>
					<Vertex X="80" Y="531" Z="0"/>
					<Vertex X="81" Y="531" Z="0"/>
					<Vertex X="81" Y="532" Z="0"/>
					<Vertex X="83" Y="532" Z="0"/>
					<Vertex X="83" Y="534" Z="0"/>
					<Vertex X="85" Y="534" Z="0"/>
					<Vertex X="85" Y="535" Z="0"/>
					<Vertex X="86" Y="535" Z="0"/>
					<Vertex X="88" Y="535" Z="0"/>
					<Vertex X="88" Y="537" Z="0"/>
					<Vertex X="88" Y="539" Z="0"/>
					<Vertex X="89" Y="539" Z="0"/>
					<Vertex X="91" Y="539" Z="0"/>
					<Vertex X="91" Y="540" Z="0"/>
					<Vertex X="91" Y="542" Z="0"/>
					<Vertex X="92" Y="542" Z="0"/>
					<Vertex X="94" Y="542" Z="0"/>
					<Vertex X="94" Y="543" Z="0"/>
					<Vertex X="96" Y="543" Z="0"/>
					<Vertex X="96" Y="545" Z="0"/>
					<Vertex X="97" Y="545" Z="0"/>
					<Vertex X="97" Y="546" Z="0"/>
					<Vertex X="99" Y="546" Z="0"/>
					<Vertex X="100" Y="548" Z="0"/>
					<Vertex X="102" Y="548" Z="0"/>
					<Vertex X="102" Y="550" Z="0"/>
					<Vertex X="104" Y="550" Z="0"/>
					<Vertex X="104" Y="551" Z="0"/>
					<Vertex X="105" Y="551" Z="0"/>
					<Vertex X="107" Y="551" Z="0"/>
					<Vertex X="107" Y="553" Z="0"/>
					<Vertex X="108" Y="554" Z="0"/>
					<Vertex X="110" Y="554" Z="0"/>
					<Vertex X="110" Y="556" Z="0"/>
					<Vertex X="112" Y="556" Z="0"/>
					<Vertex X="113" Y="556" Z="0"/>
					<Vertex X="113" Y="558" Z="0"/>
					<Vertex X="115" Y="558" Z="0"/>
					<Vertex X="116" Y="559" Z="0"/>
					<Vertex X="118" Y="559" Z="0"/>
					<Vertex X="118" Y="561" Z="0"/>
					<Vertex X="119" Y="561" Z="0"/>
					<Vertex X="121" Y="561" Z="0"/>
					<Vertex X="123" Y="562" Z="0"/>
					<Vertex X="123" Y="564" Z="0"/>
					<Vertex X="124" Y="564" Z="0"/>
					<Vertex X="126" Y="564" Z="0"/>
					<Vertex X="127" Y="564" Z="0"/>
					<Vertex X="127" Y="566" Z="0"/>
					<Vertex X="129" Y="566" Z="0"/>
					<Vertex X="129" Y="567" Z="0"/>
					<Vertex X="131" Y="567" Z="0"/>
					<Vertex X="132" Y="567" Z="0"/>
					<Vertex X="132" Y="569" Z="0"/>
					<Vertex X="134" Y="569" Z="0"/>
					<Vertex X="135" Y="569" Z="0"/>
					<Vertex X="135" Y="570" Z="0"/>
					<Vertex X="137" Y="570" Z="0"/>
					<Vertex X="139" Y="570" Z="0"/>
					<Vertex X="139" Y="572" Z="0"/>
					<Vertex X="140" Y="572" Z="0"/>
					<Vertex X="140" Y="573" Z="0"/>
					<Vertex X="142" Y="573" Z="0"/>
					<Vertex X="143" Y="573" Z="0"/>
					<Vertex X="143" Y="575" Z="0"/>
					<Vertex X="145" Y="575" Z="0"/>
					<Vertex X="146" Y="575" Z="0"/>
					<Vertex X="146" Y="577" Z="0"/>
					<Vertex X="148" Y="577" Z="0"/>
					<Vertex X="150" Y="577" Z="0"/>
					<Vertex X="150" Y="578" Z="0"/>
					<Vertex X="151" Y="578" Z="0"/>
					<Vertex X="153" Y="580" Z="0"/>
					<Vertex X="154" Y="580" Z="0"/>
					<Vertex X="156" Y="580" Z="0"/>
					<Vertex X="156" Y="581" Z="0"/>
					<Vertex X="158" Y="581" Z="0"/>
					<Vertex X="158" Y="583" Z="0"/>
					<Vertex X="159" Y="583" Z="0"/>
					<Vertex X="161" Y="583" Z="0"/>
					<Vertex X="162" Y="585" Z="0"/>
					<Vertex X="164" Y="585" Z="0"/>
					<Vertex X="164" Y="586" Z="0"/>
					<Vertex X="166" Y="586" Z="0"/>
					<Vertex X="167" Y="586" Z="0"/>
					<Vertex X="169" Y="586" Z="0"/>
					<Vertex X="169" Y="588" Z="0"/>
					<Vertex X="170" Y="588" Z="0"/>
					<Vertex X="170" Y="589" Z="0"/>
					<Vertex X="172" Y="589" Z="0"/>
					<Vertex X="173" Y="589" Z="0"/>
					<Vertex X="175" Y="589" Z="0"/>
					<Vertex X="175" Y="591" Z="0"/>
					<Vertex X="177" Y="591" Z="0"/>
					<Vertex X="177" Y="593" Z="0"/>
					<Vertex X="178" Y="593" Z="0"/>
					<Vertex X="180" Y="593" Z="0"/>
					<Vertex X="181" Y="593" Z="0"/>
					<Vertex X="181" Y="594" Z="0"/>
					<Vertex X="183" Y="594" Z="0"/>
					<Vertex X="185" Y="594" Z="0"/>
					<Vertex X="185" Y="596" Z="0"/>
					<Vertex X="186" Y="596" Z="0"/>
					<Vertex X="188" Y="596" Z="0"/>
					<Vertex X="189" Y="596" Z="0"/>
					<Vertex X="189" Y="597" Z="0"/>
					<Vertex X="191" Y="597" Z="0"/>
					<Vertex X="192" Y="597" Z="0"/>
					<Vertex X="192" Y="599" Z="0"/>
					<Vertex X="194" Y="599" Z="0"/>
					<Vertex X="196" Y="599" Z="0"/>
					<Vertex X="197" Y="599" Z="0"/>
					<Vertex X="197" Y="600" Z="0"/>
					<Vertex X="199" Y="600" Z="0"/>
					<Vertex X="200" Y="600" Z="0"/>
					<Vertex X="200" Y="602" Z="0"/>
					<Vertex X="202" Y="602" Z="0"/>
					<Vertex X="204" Y="602" Z="0"/>
					<Vertex X="204" Y="604" Z="0"/>
					<Vertex X="205" Y="604" Z="0"/>
					<Vertex X="207" Y="604" Z="0"/>
					<Vertex X="207" Y="605" Z="0"/>
					<Vertex X="208" Y="605" Z="0"/>
					<Vertex X="208" Y="607" Z="0"/>
					<Vertex X="210" Y="607" Z="0"/>
					<Vertex X="212" Y="607" Z="0"/>
					<Vertex X="213" Y="607" Z="0"/>
					<Vertex X="213" Y="608" Z="0"/>
					<Vertex X="215" Y="608" Z="0"/>
					<Vertex X="216" Y="608" Z="0"/>
					<Vertex X="216" Y="610" Z="0"/>
					<Vertex X="218" Y="610" Z="0"/>
					<Vertex X="219" Y="610" Z="0"/>
					<Vertex X="219" Y="612" Z="0"/>
					<Vertex X="221" Y="612" Z="0"/>
					<Vertex X="223" Y="612" Z="0"/>
					<Vertex X="224" Y="613" Z="0"/>
					<Vertex X="226" Y="613" Z="0"/>
					<Vertex X="227" Y="613" Z="0"/>
					<Vertex X="227" Y="615" Z="0"/>
					<Vertex X="229" Y="615" Z="0"/>
					<Vertex X="231" Y="615" Z="0"/>
					<Vertex X="231" Y="616" Z="0"/>
					<Vertex X="232" Y="616" Z="0"/>
					<Vertex X="234" Y="616" Z="0"/>
					<Vertex X="235" Y="616" Z="0"/>
					<Vertex X="235" Y="618" Z="0"/>
					<Vertex X="237" Y="618" Z="0"/>
					<Vertex X="239" Y="618" Z="0"/>
					<Vertex X="239" Y="620" Z="0"/>
					<Vertex X="240" Y="620" Z="0"/>
					<Vertex X="242" Y="620" Z="0"/>
					<Vertex X="243" Y="620" Z="0"/>
					<Vertex X="243" Y="621" Z="0"/>
					<Vertex X="245" Y="621" Z="0"/>
					<Vertex X="246" Y="621" Z="0"/>
					<Vertex X="246" Y="623" Z="0"/>
					<Vertex X="248" Y="623" Z="0"/>
					<Vertex X="250" Y="623" Z="0"/>
					<Vertex X="251" Y="623" Z="0"/>
					<Vertex X="251" Y="624" Z="0"/>
					<Vertex X="253" Y="624" Z="0"/>
					<Vertex X="254" Y="624" Z="0"/>
					<Vertex X="254" Y="626" Z="0"/>
					<Vertex X="256" Y="626" Z="0"/>
					<Vertex X="258" Y="626" Z="0"/>
					<Vertex X="259" Y="626" Z="0"/>
					<Vertex X="259" Y="627" Z="0"/>
					<Vertex X="261" Y="627" Z="0"/>
					<Vertex X="262" Y="627" Z="0"/>
					<Vertex X="262" Y="629" Z="0"/>
					<Vertex X="264" Y="629" Z="0"/>
					<Vertex X="266" Y="629" Z="0"/>
					<Vertex X="267" Y="629" Z="0"/>
					<Vertex X="267" Y="631" Z="0"/>
					<Vertex X="269" Y="631" Z="0"/>
					<Vertex X="270" Y="631" Z="0"/>
					<Vertex X="272" Y="632" Z="0"/>
					<Vertex X="273" Y="632" Z="0"/>
					<Vertex X="275" Y="632" Z="0"/>
					<Vertex X="277" Y="632" Z="0"/>
					<Vertex X="277" Y="634" Z="0"/>
					<Vertex X="278" Y="634" Z="0"/>
					<Vertex X="280" Y="634" Z="0"/>
					<Vertex X="280" Y="635" Z="0"/>
					<Vertex X="281" Y="635" Z="0"/>
					<Vertex X="283" Y="635" Z="0"/>
					<Vertex X="285" Y="635" Z="0"/>
					<Vertex X="285" Y="637" Z="0"/>
					<Vertex X="286" Y="637" Z="0"/>
					<Vertex X="286" Y="639" Z="0"/>
					<Vertex X="288" Y="639" Z="0"/>
					<Vertex X="289" Y="639" Z="0"/>
					<Vertex X="291" Y="639" Z="0"/>
					<Vertex X="291" Y="640" Z="0"/>
					<Vertex X="292" Y="640" Z="0"/>
					<Vertex X="294" Y="640" Z="0"/>
					<Vertex X="294" Y="642" Z="0"/>
					<Vertex X="296" Y="642" Z="0"/>
					<Vertex X="297" Y="642" Z="0"/>
					<Vertex X="297" Y="643" Z="0"/>
					<Vertex X="299" Y="643" Z="0"/>
					<Vertex X="300" Y="643" Z="0"/>
					<Vertex X="302" Y="643" Z="0"/>
					<Vertex X="302" Y="645" Z="0"/>
					<Vertex X="304" Y="645" Z="0"/>
					<Vertex X="305" Y="645" Z="0"/>
					<Vertex X="307" Y="646" Z="0"/>
					<Vertex X="308" Y="646" Z="0"/>
					<Vertex X="308" Y="648" Z="0"/>
					<Vertex X="310" Y="648" Z="0"/>
					<Vertex X="312" Y="648" Z="0"/>
					<Vertex X="312" Y="650" Z="0"/>
					<Vertex X="313" Y="650" Z="0"/>
					<Vertex X="315" Y="650" Z="0"/>
					<Vertex X="315" Y="651" Z="0"/>
					<Vertex X="316" Y="651" Z="0"/>
					<Vertex X="318" Y="651" Z="0"/>
					<Vertex X="318" Y="653" Z="0"/>
					<Vertex X="319" Y="653" Z="0"/>
					<Vertex X="321" Y="653" Z="0"/>
					<Vertex X="321" Y="654" Z="0"/>
					<Vertex X="323" Y="654" Z="0"/>
					<Vertex X="324" Y="654" Z="0"/>
					<Vertex X="324" Y="656" Z="0"/>
					<Vertex X="326" Y="656" Z="0"/>
					<Vertex X="327" Y="658" Z="0"/>
					<Vertex X="329" Y="658" Z="0"/>
					<Vertex X="331" Y="658" Z="0"/>
					<Vertex X="331" Y="659" Z="0"/>
					<Vertex X="332" Y="659" Z="0"/>
					<Vertex X="332" Y="661" Z="0"/>
					<Vertex X="334" Y="661" Z="0"/>
					<Vertex X="335" Y="661" Z="0"/>
					<Vertex X="335" Y="662" Z="0"/>
					<Vertex X="337" Y="662" Z="0"/>
					<Vertex X="339" Y="662" Z="0"/>
					<Vertex X="339" Y="664" Z="0"/>
					<Vertex X="340" Y="664" Z="0"/>
					<Vertex X="342" Y="664" Z="0"/>
					<Vertex X="342" Y="666" Z="0"/>
					<Vertex X="343" Y="666" Z="0"/>
					<Vertex X="343" Y="667" Z="0"/>
					<Vertex X="345" Y="667" Z="0"/>
					<Vertex X="346" Y="667" Z="0"/>
					<Vertex X="346" Y="669" Z="0"/>
					<Vertex X="348" Y="669" Z="0"/>
					<Vertex X="350" Y="669" Z="0"/>
					<Vertex X="350" Y="670" Z="0"/>
					<Vertex X="351" Y="670" Z="0"/>
					<Vertex X="353" Y="670" Z="0"/>
					<Vertex X="353" Y="672" Z="0"/>
					<Vertex X="354" Y="672" Z="0"/>
					<Vertex X="356" Y="672" Z="0"/>
					<Vertex X="356" Y="673" Z="0"/>
					<Vertex X="358" Y="673" Z="0"/>
					<Vertex X="359" Y="673" Z="0"/>
					<Vertex X="359" Y="675" Z="0"/>
					<Vertex X="361" Y="675" Z="0"/>
					<Vertex X="362" Y="675" Z="0"/>
					<Vertex X="362" Y="677" Z="0"/>
					<Vertex X="364" Y="677" Z="0"/>
					<Vertex X="364" Y="678" Z="0"/>
					<Vertex X="366" Y="678" Z="0"/>
					<Vertex X="367" Y="678" Z="0"/>
					<Vertex X="367" Y="680" Z="0"/>
					<Vertex X="369" Y="680" Z="0"/>
					<Vertex X="370" Y="681" Z="0"/>
					<Vertex X="372" Y="681" Z="0"/>
					<Vertex X="373" Y="681" Z="0"/>
					<Vertex X="373" Y="683" Z="0"/>
					<Vertex X="375" Y="683" Z="0"/>
					<Vertex X="375" Y="685" Z="0"/>
					<Vertex X="377" Y="685" Z="0"/>
					<Vertex X="378" Y="685" Z="0"/>
					<Vertex X="378" Y="686" Z="0"/>
					<Vertex X="380" Y="686" Z="0"/>
					<Vertex X="381" Y="686" Z="0"/>
					<Vertex X="381" Y="688" Z="0"/>
					<Vertex X="383" Y="688" Z="0"/>
					<Vertex X="385" Y="688" Z="0"/>
					<Vertex X="385" Y="689" Z="0"/>
					<Vertex X="386" Y="689" Z="0"/>
					<Vertex X="386" Y="691" Z="0"/>
					<Vertex X="388" Y="691" Z="0"/>
					<Vertex X="389" Y="691" Z="0"/>
					<Vertex X="391" Y="691" Z="0"/>
					<Vertex X="391" Y="693" Z="0"/>
					<Vertex X="392" Y="693" Z="0"/>
					<Vertex X="392" Y="694" Z="0"/>
					<Vertex X="394" Y="694" Z="0"/>
					<Vertex X="396" Y="694" Z="0"/>
					<Vertex X="396" Y="696" Z="0"/>
					<Vertex X="397" Y="696" Z="0"/>
					<Vertex X="399" Y="696" Z="0"/>
					<Vertex X="399" Y="697" Z="0"/>
					<Vertex X="400" Y="697" Z="0"/>
					<Vertex X="402" Y="697" Z="0"/>
					<Vertex X="402" Y="699" Z="0"/>
					<Vertex X="404" Y="699" Z="0"/>
					<Vertex X="405" Y="700" Z="0"/>
					<Vertex X="407" Y="700" Z="0"/>
					<Vertex X="407" Y="702" Z="0"/>
					<Vertex X="408" Y="702" Z="0"/>
					<Vertex X="410" Y="704" Z="0"/>
					<Vertex X="412" Y="704" Z="0"/>
					<Vertex X="412" Y="705" Z="0"/>
					<Vertex X="413" Y="705" Z="0"/>
					<Vertex X="415" Y="705" Z="0"/>
					<Vertex X="415" Y="707" Z="0"/>
					<Vertex X="416" Y="707" Z="0"/>
					<Vertex X="418" Y="707" Z="0"/>
					<Vertex X="418" Y="708" Z="0"/>
					<Vertex X="419" Y="708" Z="0"/>
					<Vertex X="421" Y="708" Z="0"/>
					<Vertex X="421" Y="710" Z="0"/>
					<Vertex X="423" Y="710" Z="0"/>
					<Vertex X="424" Y="710" Z="0"/>
					<Vertex X="424" Y="712" Z="0"/>
					<Vertex X="426" Y="712" Z="0"/>
					<Vertex X="426" Y="713" Z="0"/>
					<Vertex X="427" Y="713" Z="0"/>
					<Vertex X="429" Y="713" Z="0"/>
					<Vertex X="429" Y="715" Z="0"/>
					<Vertex X="431" Y="715" Z="0"/>
					<Vertex X="432" Y="715" Z="0"/>
					<Vertex X="432" Y="716" Z="0"/>
					<Vertex X="434" Y="716" Z="0"/>
					<Vertex X="435" Y="716" Z="0"/>
					<Vertex X="435" Y="718" Z="0"/>
					<Vertex X="437" Y="718" Z="0"/>
					<Vertex X="437" Y="720" Z="0"/>
					<Vertex X="439" Y="720" Z="0"/>
					<Vertex X="440" Y="720" Z="0"/>
					<Vertex X="442" Y="720" Z="0"/>
					<Vertex X="442" Y="721" Z="0"/>
					<Vertex X="443" Y="721" Z="0"/>
					<Vertex X="443" Y="723" Z="0"/>
					<Vertex X="445" Y="723" Z="0"/>
					<Vertex X="446" Y="723" Z="0"/>
					<Vertex X="446" Y="724" Z="0"/>
					<Vertex X="448" Y="724" Z="0"/>
					<Vertex X="450" Y="724" Z="0"/>
					<Vertex X="450" Y="726" Z="0"/>
					<Vertex X="451" Y="726" Z="0"/>
					<Vertex X="453" Y="726" Z="0"/>
					<Vertex X="453" Y="727" Z="0"/>
					<Vertex X="454" Y="727" Z="0"/>
					<Vertex X="454" Y="729" Z="0"/>
					<Vertex X="456" Y="729" Z="0"/>
					<Vertex X="458" Y="729" Z="0"/>
					<Vertex X="459" Y="731" Z="0"/>
					<Vertex X="461" Y="731" Z="0"/>
					<Vertex X="461" Y="732" Z="0"/>
					<Vertex X="462" Y="732" Z="0"/>
					<Vertex X="464" Y="732" Z="0"/>
					<Vertex X="464" Y="734" Z="0"/>
					<Vertex X="466" Y="734" Z="0"/>
					<Vertex X="467" Y="734" Z="0"/>
					<Vertex X="467" Y="735" Z="0"/>
					<Vertex X="469" Y="735" Z="0"/>
					<Vertex X="470" Y="735" Z="0"/>
					<Vertex X="470" Y="737" Z="0"/>
					<Vertex X="472" Y="737" Z="0"/>
					<Vertex X="473" Y="737" Z="0"/>
					<Vertex X="473" Y="739" Z="0"/>
					<Vertex X="475" Y="739" Z="0"/>
					<Vertex X="477" Y="739" Z="0"/>
					<Vertex X="477" Y="740" Z="0"/>
					<Vertex X="478" Y="740" Z="0"/>
					<Vertex X="480" Y="740" Z="0"/>
					<Vertex X="480" Y="742" Z="0"/>
					<Vertex X="481" Y="742" Z="0"/>
					<Vertex X="483" Y="742" Z="0"/>
					<Vertex X="485" Y="742" Z="0"/>
					<Vertex X="485" Y="743" Z="0"/>
					<Vertex X="486" Y="743" Z="0"/>
					<Vertex X="488" Y="743" Z="0"/>
					<Vertex X="489" Y="743" Z="0"/>
					<Vertex X="489" Y="745" Z="0"/>
					<Vertex X="491" Y="745" Z="0"/>
					<Vertex X="492" Y="746" Z="0"/>
					<Vertex X="494" Y="746" Z="0"/>
					<Vertex X="496" Y="746" Z="0"/>
					<Vertex X="496" Y="748" Z="0"/>
					<Vertex X="497" Y="748" Z="0"/>
					<Vertex X="499" Y="748" Z="0"/>
					<Vertex X="499" Y="750" Z="0"/>
					<Vertex X="500" Y="750" Z="0"/>
					<Vertex X="502" Y="750" Z="0"/>
					<Vertex X="502" Y="751" Z="0"/>
					<Vertex X="504" Y="751" Z="0"/>
					<Vertex X="505" Y="751" Z="0"/>
					<Vertex X="507" Y="751" Z="0"/>
					<Vertex X="507" Y="753" Z="0"/>
					<Vertex X="508" Y="753" Z="0"/>
					<Vertex X="510" Y="753" Z="0"/>
					<Vertex X="512" Y="754" Z="0"/>
					<Vertex X="513" Y="754" Z="0"/>
					<Vertex X="513" Y="756" Z="0"/>
					<Vertex X="515" Y="756" Z="0"/>
					<Vertex X="516" Y="756" Z="0"/>
					<Vertex X="518" Y="756" Z="0"/>
					<Vertex X="519" Y="756" Z="0"/>
					<Vertex X="519" Y="758" Z="0"/>
					<Vertex X="521" Y="758" Z="0"/>
					<Vertex X="523" Y="758" Z="0"/>
					<Vertex X="523" Y="759" Z="0"/>
					<Vertex X="524" Y="759" Z="0"/>
					<Vertex X="526" Y="759" Z="0"/>
					<Vertex X="527" Y="761" Z="0"/>
					<Vertex X="529" Y="761" Z="0"/>
					<Vertex X="531" Y="762" Z="0"/>
					<Vertex X="532" Y="762" Z="0"/>
					<Vertex X="534" Y="762" Z="0"/>
					<Vertex X="534" Y="764" Z="0"/>
					<Vertex X="535" Y="764" Z="0"/>
					<Vertex X="537" Y="764" Z="0"/>
					<Vertex X="537" Y="766" Z="0"/>
					<Vertex X="539" Y="766" Z="0"/>
					<Vertex X="540" Y="766" Z="0"/>
					<Vertex X="542" Y="766" Z="0"/>
					<Vertex X="542" Y="767" Z="0"/>
					<Vertex X="543" Y="767" Z="0"/>
					<Vertex X="545" Y="767" Z="0"/>
					<Vertex X="546" Y="767" Z="0"/>
					<Vertex X="546" Y="769" Z="0"/>
					<Vertex X="548" Y="769" Z="0"/>
					<Vertex X="550" Y="769" Z="0"/>
					<Vertex X="551" Y="770" Z="0"/>
					<Vertex X="553" Y="770" Z="0"/>
					<Vertex X="554" Y="770" Z="0"/>
					<Vertex X="554" Y="772" Z="0"/>
					<Vertex X="556" Y="772" Z="0"/>
					<Vertex X="558" Y="772" Z="0"/>
					<Vertex X="558" Y="773" Z="0"/>
					<Vertex X="559" Y="773" Z="0"/>
					<Vertex X="561" Y="773" Z="0"/>
					<Vertex X="562" Y="775" Z="0"/>
					<Vertex X="564" Y="775" Z="0"/>
					<Vertex X="566" Y="775" Z="0"/>
					<Vertex X="566" Y="777" Z="0"/>
					<Vertex X="567" Y="777" Z="0"/>
					<Vertex X="569" Y="777" Z="0"/>
					<Vertex X="570" Y="777" Z="0"/>
					<Vertex X="570" Y="778" Z="0"/>
					<Vertex X="572" Y="778" Z="0"/>
					<Vertex X="573" Y="778" Z="0"/>
					<Vertex X="575" Y="778" Z="0"/>
					<Vertex X="577" Y="778" Z="0"/>
					<Vertex X="578" Y="780" Z="0"/>
					<Vertex X="580" Y="780" Z="0"/>
					<Vertex X="581" Y="780" Z="0"/>
					<Vertex X="581" Y="781" Z="0"/>
					<Vertex X="583" Y="781" Z="0"/>
					<Vertex X="585" Y="781" Z="0"/>
					<Vertex X="586" Y="781" Z="0"/>
					<Vertex X="588" Y="781" Z="0"/>
					<Vertex X="588" Y="783" Z="0"/>
					<Vertex X="589" Y="783" Z="0"/>
					<Vertex X="591" Y="783" Z="0"/>
					<Vertex X="591" Y="785" Z="0"/>
					<Vertex X="592" Y="785" Z="0"/>
					<Vertex X="594" Y="785" Z="0"/>
					<Vertex X="596" Y="786" Z="0"/>
					<Vertex X="597" Y="786" Z="0"/>
					<Vertex X="599" Y="786" Z="0"/>
					<Vertex X="599" Y="788" Z="0"/>
					<Vertex X="600" Y="788" Z="0"/>
					<Vertex X="602" Y="788" Z="0"/>
					<Vertex X="604" Y="788" Z="0"/>
					<Vertex X="604" Y="789" Z="0"/>
					<Vertex X="605" Y="789" Z="0"/>
					<Vertex X="607" Y="789" Z="0"/>
					<Vertex X="608" Y="791" Z="0"/>
					<Vertex X="610" Y="791" Z="0"/>
					<Vertex X="612" Y="791" Z="0"/>
					<Vertex X="613" Y="791" Z="0"/>
					<Vertex X="613" Y="793" Z="0"/>
					<Vertex X="615" Y="793" Z="0"/>
					<Vertex X="616" Y="793" Z="0"/>
					<Vertex X="616" Y="794" Z="0"/>
					<Vertex X="618" Y="794" Z="0"/>
					<Vertex X="619" Y="794" Z="0"/>
					<Vertex X="621" Y="794" Z="0"/>
					<Vertex X="621" Y="796" Z="0"/>
					<Vertex X="623" Y="796" Z="0"/>
					<Vertex X="624" Y="796" Z="0"/>
					<Vertex X="624" Y="797" Z="0"/>
					<Vertex X="626" Y="797" Z="0"/>
					<Vertex X="627" Y="797" Z="0"/>
					<Vertex X="629" Y="797" Z="0"/>
					<Vertex X="629" Y="799" Z="0"/>
					<Vertex X="631" Y="799" Z="0"/>
					<Vertex X="632" Y="799" Z="0"/>
					<Vertex X="632" Y="800" Z="0"/>
					<Vertex X="634" Y="800" Z="0"/>
					<Vertex X="635" Y="800" Z="0"/>
					<Vertex X="637" Y="800" Z="0"/>
					<Vertex X="637" Y="802" Z="0"/>
					<Vertex X="639" Y="802" Z="0"/>
					<Vertex X="640" Y="802" Z="0"/>
					<Vertex X="640" Y="804" Z="0"/>
					<Vertex X="642" Y="804" Z="0"/>
					<Vertex X="643" Y="804" Z="0"/>
					<Vertex X="645" Y="804" Z="0"/>
					<Vertex X="645" Y="805" Z="0"/>
					<Vertex X="646" Y="805" Z="0"/>
					<Vertex X="646" Y="807" Z="0"/>
					<Vertex X="648" Y="807" Z="0"/>
					<Vertex X="650" Y="807" Z="0"/>
					<Vertex X="651" Y="807" Z="0"/>
					<Vertex X="653" Y="808" Z="0"/>
					<Vertex X="654" Y="808" Z="0"/>
					<Vertex X="656" Y="808" Z="0"/>
					<Vertex X="656" Y="810" Z="0"/>
					<Vertex X="658" Y="810" Z="0"/>
					<Vertex X="659" Y="810" Z="0"/>
					<Vertex X="661" Y="810" Z="0"/>
					<Vertex X="661" Y="812" Z="0"/>
					<Vertex X="662" Y="812" Z="0"/>
					<Vertex X="664" Y="812" Z="0"/>
					<Vertex X="666" Y="812" Z="0"/>
					<Vertex X="666" Y="813" Z="0"/>
					<Vertex X="667" Y="813" Z="0"/>
					<Vertex X="669" Y="813" Z="0"/>
					<Vertex X="670" Y="813" Z="0"/>
					<Vertex X="670" Y="815" Z="0"/>
					<Vertex X="672" Y="815" Z="0"/>
					<Vertex X="673" Y="815" Z="0"/>
					<Vertex X="675" Y="815" Z="0"/>
					<Vertex X="675" Y="816" Z="0"/>
					<Vertex X="677" Y="816" Z="0"/>
					<Vertex X="678" Y="816" Z="0"/>
					<Vertex X="680" Y="816" Z="0"/>
					<Vertex X="681" Y="818" Z="0"/>
					<Vertex X="683" Y="818" Z="0"/>
					<Vertex X="685" Y="818" Z="0"/>
					<Vertex X="685" Y="820" Z="0"/>
					<Vertex X="686" Y="820" Z="0"/>
					<Vertex X="688" Y="820" Z="0"/>
					<Vertex X="689" Y="820" Z="0"/>
					<Vertex X="691" Y="821" Z="0"/>
					<Vertex X="692" Y="821" Z="0"/>
					<Vertex X="694" Y="821" Z="0"/>
					<Vertex X="696" Y="821" Z="0"/>
					<Vertex X="696" Y="823" Z="0"/>
					<Vertex X="697" Y="823" Z="0"/>
					<Vertex X="699" Y="823" Z="0"/>
					<Vertex X="700" Y="824" Z="0"/>
					<Vertex X="702" Y="824" Z="0"/>
					<Vertex X="704" Y="824" Z="0"/>
					<Vertex X="705" Y="824" Z="0"/>
					<Vertex X="707" Y="826" Z="0"/>
					<Vertex X="708" Y="826" Z="0"/>
					<Vertex X="710" Y="826" Z="0"/>
					<Vertex X="710" Y="827" Z="0"/>
					<Vertex X="712" Y="827" Z="0"/>
					<Vertex X="713" Y="827" Z="0"/>
					<Vertex X="715" Y="827" Z="0"/>
					<Vertex X="716" Y="829" Z="0"/>
					<Vertex X="718" Y="829" Z="0"/>
					<Vertex X="718" Y="831" Z="0"/>
					<Vertex X="719" Y="831" Z="0"/>
					<Vertex X="721" Y="831" Z="0"/>
					<Vertex X="723" Y="831" Z="0"/>
					<Vertex X="724" Y="831" Z="0"/>
					<Vertex X="726" Y="831" Z="0"/>
					<Vertex X="727" Y="832" Z="0"/>
					<Vertex X="729" Y="832" Z="0"/>
					<Vertex X="731" Y="832" Z="0"/>
					<Vertex X="732" Y="832" Z="0"/>
					<Vertex X="734" Y="834" Z="0"/>
					<Vertex X="735" Y="834" Z="0"/>
					<Vertex X="737" Y="834" Z="0"/>
					<Vertex X="739" Y="834" Z="0"/>
					<Vertex X="739" Y="835" Z="0"/>
					<Vertex X="740" Y="835" Z="0"/>
					<Vertex X="742" Y="835" Z="0"/>
					<Vertex X="743" Y="835" Z="0"/>
					<Vertex X="745" Y="835" Z="0"/>
					<Vertex X="746" Y="837" Z="0"/>
					<Vertex X="748" Y="837" Z="0"/>
					<Vertex X="750" Y="837" Z="0"/>
					<Vertex X="751" Y="837" Z="0"/>
					<Vertex X="753" Y="839" Z="0"/>
					<Vertex X="754" Y="839" Z="0"/>
					<Vertex X="756" Y="839" Z="0"/>
					<Vertex X="758" Y="840" Z="0"/>
					<Vertex X="759" Y="840" Z="0"/>
					<Vertex X="761" Y="840" Z="0"/>
					<Vertex X="762" Y="840" Z="0"/>
					<Vertex X="764" Y="840" Z="0"/>
					<Vertex X="766" Y="842" Z="0"/>
					<Vertex X="767" Y="842" Z="0"/>
					<Vertex X="769" Y="842" Z="0"/>
					<Vertex X="769" Y="843" Z="0"/>
					<Vertex X="770" Y="843" Z="0"/>
					<Vertex X="772" Y="843" Z="0"/>
					<Vertex X="773" Y="843" Z="0"/>
					<Vertex X="775" Y="843" Z="0"/>
					<Vertex X="777" Y="843" Z="0"/>
					<Vertex X="778" Y="845" Z="0"/>
					<Vertex X="780" Y="845" Z="0"/>
					<Vertex X="781" Y="845" Z="0"/>
					<Vertex X="783" Y="846" Z="0"/>
					<Vertex X="785" Y="846" Z="0"/>
					<Vertex X="786" Y="846" Z="0"/>
					<Vertex X="788" Y="846" Z="0"/>
					<Vertex X="789" Y="848" Z="0"/>
					<Vertex X="791" Y="848" Z="0"/>
					<Vertex X="792" Y="848" Z="0"/>
					<Vertex X="792" Y="850" Z="0"/>
					<Vertex X="794" Y="850" Z="0"/>
					<Vertex X="796" Y="850" Z="0"/>
					<Vertex X="797" Y="850" Z="0"/>
					<Vertex X="799" Y="850" Z="0"/>
					<Vertex X="800" Y="850" Z="0"/>
					<Vertex X="800" Y="851" Z="0"/>
					<Vertex X="802" Y="851" Z="0"/>
					<Vertex X="804" Y="851" Z="0"/>
					<Vertex X="805" Y="851" Z="0"/>
					<Vertex X="807" Y="851" Z="0"/>
					<Vertex X="808" Y="853" Z="0"/>
					<Vertex X="810" Y="853" Z="0"/>
					<Vertex X="812" Y="853" Z="0"/>
					<Vertex X="813" Y="853" Z="0"/>
					<Vertex X="815" Y="853" Z="0"/>
					<Vertex X="816" Y="854" Z="0"/>
					<Vertex X="818" Y="854" Z="0"/>
					<Vertex X="819" Y="854" Z="0"/>
					<Vertex X="821" Y="856" Z="0"/>
					<Vertex X="823" Y="856" Z="0"/>
					<Vertex X="824" Y="856" Z="0"/>
					<Vertex X="826" Y="856" Z="0"/>
					<Vertex X="827" Y="856" Z="0"/>
					<Vertex X="827" Y="858" Z="0"/>
					<Vertex X="829" Y="858" Z="0"/>
					<Vertex X="831" Y="858" Z="0"/>
					<Vertex X="832" Y="858" Z="0"/>
					<Vertex X="834" Y="858" Z="0"/>
					<Vertex X="835" Y="859" Z="0"/>
					<Vertex X="837" Y="859" Z="0"/>
					<Vertex X="840" Y="859" Z="0"/>
					<Vertex X="842" Y="859" Z="0"/>
					<Vertex X="843" Y="859" Z="0"/>
					<Vertex X="845" Y="859" Z="0"/>
					<Vertex X="846" Y="861" Z="0"/>
					<Vertex X="848" Y="861" Z="0"/>
					<Vertex X="850" Y="861" Z="0"/>
					<Vertex X="851" Y="861" Z="0"/>
					<Vertex X="853" Y="861" Z="0"/>
					<Vertex X="853" Y="862" Z="0"/>
					<Vertex X="854" Y="862" Z="0"/>
					<Vertex X="856" Y="862" Z="0"/>
					<Vertex X="858" Y="862" Z="0"/>
					<Vertex X="859" Y="862" Z="0"/>
					<Vertex X="861" Y="862" Z="0"/>
					<Vertex X="862" Y="864" Z="0"/>
					<Vertex X="864" Y="864" Z="0"/>
					<Vertex X="866" Y="864" Z="0"/>
					<Vertex X="867" Y="864" Z="0"/>
					<Vertex X="869" Y="864" Z="0"/>
					<Vertex X="869" Y="866" Z="0"/>
					<Vertex X="870" Y="866" Z="0"/>
					<Vertex X="872" Y="866" Z="0"/>
					<Vertex X="873" Y="866" Z="0"/>
					<Vertex X="875" Y="866" Z="0"/>
					<Vertex X="877" Y="866" Z="0"/>
					<Vertex X="878" Y="866" Z="0"/>
					<Vertex X="880" Y="866" Z="0"/>
					<Vertex X="881" Y="867" Z="0"/>
					<Vertex X="883" Y="867" Z="0"/>
					<Vertex X="885" Y="867" Z="0"/>
					<Vertex X="886" Y="867" Z="0"/>
					<Vertex X="888" Y="867" Z="0"/>
					<Vertex X="889" Y="867" Z="0"/>
					<Vertex X="891" Y="867" Z="0"/>
					<Vertex X="892" Y="867" Z="0"/>
					<Vertex X="896" Y="869" Z="0"/>
					<Vertex X="897" Y="869" Z="0"/>
					<Vertex X="899" Y="869" Z="0"/>
					<Vertex X="900" Y="869" Z="0"/>
					<Vertex X="902" Y="869" Z="0"/>
					<Vertex X="904" Y="869" Z="0"/>
					<Vertex X="905" Y="869" Z="0"/>
					<Vertex X="907" Y="869" Z="0"/>
					<Vertex X="908" Y="869" Z="0"/>
					<Vertex X="908" Y="870" Z="0"/>
					<Vertex X="910" Y="870" Z="0"/>
					<Vertex X="912" Y="870" Z="0"/>
					<Vertex X="913" Y="870" Z="0"/>
					<Vertex X="915" Y="870" Z="0"/>
					<Vertex X="916" Y="870" Z="0"/>
					<Vertex X="918" Y="870" Z="0"/>
					<Vertex X="918" Y="872" Z="0"/>
					<Vertex X="921" Y="872" Z="0"/>
					<Vertex X="923" Y="872" Z="0"/>
					<Vertex X="924" Y="872" Z="0"/>
					<Vertex X="926" Y="872" Z="0"/>
					<Vertex X="927" Y="872" Z="0"/>
					<Vertex X="929" Y="872" Z="0"/>
					<Vertex X="931" Y="872" Z="0"/>
					<Vertex X="932" Y="872" Z="0"/>
					<Vertex X="934" Y="873" Z="0"/>
					<Vertex X="935" Y="873" Z="0"/>
					<Vertex X="937" Y="873" Z="0"/>
					<Vertex X="939" Y="873" Z="0"/>
					<Vertex X="940" Y="873" Z="0"/>
					<Vertex X="942" Y="873" Z="0"/>
					<Vertex X="943" Y="873" Z="0"/>
					<Vertex X="945" Y="873" Z="0"/>
					<Vertex X="946" Y="873" Z="0"/>
					<Vertex X="948" Y="875" Z="0"/>
					<Vertex X="950" Y="875" Z="0"/>
					<Vertex X="951" Y="875" Z="0"/>
					<Vertex X="953" Y="875" Z="0"/>
					<Vertex X="954" Y="875" Z="0"/>
					<Vertex X="956" Y="875" Z="0"/>
					<Vertex X="958" Y="875" Z="0"/>
					<Vertex X="959" Y="875" Z="0"/>
					<Vertex X="961" Y="875" Z="0"/>
					<Vertex X="962" Y="875" Z="0"/>
					<Vertex X="962" Y="877" Z="0"/>
					<Vertex X="964" Y="877" Z="0"/>
					<Vertex X="966" Y="877" Z="0"/>
					<Vertex X="967" Y="877" Z="0"/>
					<Vertex X="969" Y="877" Z="0"/>
					<Vertex X="970" Y="877" Z="0"/>
					<Vertex X="972" Y="877" Z="0"/>
					<Vertex X="973" Y="877" Z="0"/>
					<Vertex X="973" Y="878" Z="0"/>
					<Vertex X="977" Y="878" Z="0"/>
					<Vertex X="978" Y="878" Z="0"/>
					<Vertex X="980" Y="878" Z="0"/>
					<Vertex X="981" Y="878" Z="0"/>
					<Vertex X="983" Y="878" Z="0"/>
					<Vertex X="985" Y="878" Z="0"/>
					<Vertex X="986" Y="878" Z="0"/>
					<Vertex X="988" Y="878" Z="0"/>
					<Vertex X="989" Y="878" Z="0"/>
					<Vertex X="991" Y="878" Z="0"/>
					<Vertex X="992" Y="878" Z="0"/>
					<Vertex X="994" Y="878" Z="0"/>
					<Vertex X="996" Y="880" Z="0"/>
					<Vertex X="997" Y="880" Z="0"/>
					<Vertex X="999" Y="880" Z="0"/>
					<Vertex X="1000" Y="880" Z="0"/>
					<Vertex X="1002" Y="880" Z="0"/>
					<Vertex X="1004" Y="880" Z="0"/>
					<Vertex X="1005" Y="880" Z="0"/>
					<Vertex X="1007" Y="880" Z="0"/>
					<Vertex X="1008" Y="880" Z="0"/>
					<Vertex X="1010" Y="881" Z="0"/>
					<Vertex X="1012" Y="881" Z="0"/>
					<Vertex X="1013" Y="881" Z="0"/>
					<Vertex X="1015" Y="881" Z="0"/>
					<Vertex X="1016" Y="881" Z="0"/>
					<Vertex X="1018" Y="881" Z="0"/>
					<Vertex X="1019" Y="881" Z="0"/>
					<Vertex X="1021" Y="881" Z="0"/>
					<Vertex X="1023" Y="881" Z="0"/>
					<Vertex X="1026" Y="881" Z="0"/>
					<Vertex X="1026" Y="883" Z="0"/>
					<Vertex X="1029" Y="883" Z="0"/>
					<Vertex X="1031" Y="883" Z="0"/>
					<Vertex X="1032" Y="883" Z="0"/>
					<Vertex X="1034" Y="883" Z="0"/>
					<Vertex X="1035" Y="883" Z="0"/>
					<Vertex X="1037" Y="883" Z="0"/>
					<Vertex X="1039" Y="883" Z="0"/>
					<Vertex X="1040" Y="883" Z="0"/>
					<Vertex X="1042" Y="883" Z="0"/>
					<Vertex X="1045" Y="883" Z="0"/>
					<Vertex X="1046" Y="883" Z="0"/>
					<Vertex X="1048" Y="885" Z="0"/>
					<Vertex X="1051" Y="885" Z="0"/>
					<Vertex X="1053" Y="885" Z="0"/>
					<Vertex X="1056" Y="885" Z="0"/>
					<Vertex X="1058" Y="885" Z="0"/>
					<Vertex X="1061" Y="886" Z="0"/>
					<Vertex X="1062" Y="886" Z="0"/>
					<Vertex X="1064" Y="886" Z="0"/>
					<Vertex X="1067" Y="886" Z="0"/>
					<Vertex X="1069" Y="886" Z="0"/>
					<Vertex X="1070" Y="886" Z="0"/>
					<Vertex X="1072" Y="886" Z="0"/>
					<Vertex X="1073" Y="886" Z="0"/>
					<Vertex X="1075" Y="886" Z="0"/>
					<Vertex X="1077" Y="886" Z="0"/>
					<Vertex X="1078" Y="888" Z="0"/>
					<Vertex X="1080" Y="888" Z="0"/>
					<Vertex X="1081" Y="888" Z="0"/>
					<Vertex X="1083" Y="888" Z="0"/>
					<Vertex X="1085" Y="888" Z="0"/>
					<Vertex X="1086" Y="888" Z="0"/>
					<Vertex X="1088" Y="888" Z="0"/>
					<Vertex X="1089" Y="888" Z="0"/>
					<Vertex X="1091" Y="888" Z="0"/>
					<Vertex X="1092" Y="888" Z="0"/>
					<Vertex X="1094" Y="888" Z="0"/>
					<Vertex X="1094" Y="889" Z="0"/>
					<Vertex X="1096" Y="889" Z="0"/>
					<Vertex X="1097" Y="889" Z="0"/>
					<Vertex X="1099" Y="889" Z="0"/>
					<Vertex X="1100" Y="889" Z="0"/>
					<Vertex X="1102" Y="889" Z="0"/>
					<Vertex X="1104" Y="889" Z="0"/>
					<Vertex X="1105" Y="889" Z="0"/>
					<Vertex X="1107" Y="889" Z="0"/>
					<Vertex X="1108" Y="889" Z="0"/>
					<Vertex X="1110" Y="889" Z="0"/>
					<Vertex X="1112" Y="889" Z="0"/>
					<Vertex X="1113" Y="889" Z="0"/>
					<Vertex X="1115" Y="889" Z="0"/>
					<Vertex X="1116" Y="889" Z="0"/>
					<Vertex X="1118" Y="889" Z="0"/>
					<Vertex X="1119" Y="889" Z="0"/>
					<Vertex X="1121" Y="889" Z="0"/>
					<Vertex X="1123" Y="889" Z="0"/>
					<Vertex X="1124" Y="889" Z="0"/>
					<Vertex X="1126" Y="889" Z="0"/>
					<Vertex X="1127" Y="889" Z="0"/>
					<Vertex X="1129" Y="889" Z="0"/>
					<Vertex X="1131" Y="889" Z="0"/>
					<Vertex X="1132" Y="889" Z="0"/>
					<Vertex X="1134" Y="889" Z="0"/>
					<Vertex X="1135" Y="889" Z="0"/>
					<Vertex X="1137" Y="889" Z="0"/>
					<Vertex X="1139" Y="889" Z="0"/>
					<Vertex X="1140" Y="889" Z="0"/>
					<Vertex X="1142" Y="889" Z="0"/>
					<Vertex X="1143" Y="889" Z="0"/>
					<Vertex X="1145" Y="889" Z="0"/>
					<Vertex X="1146" Y="889" Z="0"/>
					<Vertex X="1150" Y="889" Z="0"/>
					<Vertex X="1151" Y="889" Z="0"/>
					<Vertex X="1154" Y="889" Z="0"/>
					<Vertex X="1156" Y="889" Z="0"/>
					<Vertex X="1158" Y="889" Z="0"/>
					<Vertex X="1161" Y="889" Z="0"/>
					<Vertex X="1162" Y="889" Z="0"/>
					<Vertex X="1166" Y="889" Z="0"/>
					<Vertex X="1167" Y="889" Z="0"/>
					<Vertex X="1169" Y="889" Z="0"/>
					<Vertex X="1170" Y="889" Z="0"/>
					<Vertex X="1172" Y="889" Z="0"/>
					<Vertex X="1175" Y="889" Z="0"/>
					<Vertex X="1177" Y="889" Z="0"/>
					<Vertex X="1178" Y="889" Z="0"/>
					<Vertex X="1180" Y="889" Z="0"/>
					<Vertex X="1181" Y="889" Z="0"/>
					<Vertex X="1185" Y="889" Z="0"/>
					<Vertex X="1186" Y="889" Z="0"/>
					<Vertex X="1188" Y="889" Z="0"/>
					<Vertex X="1189" Y="889" Z="0"/>
					<Vertex X="1191" Y="889" Z="0"/>
					<Vertex X="1192" Y="889" Z="0"/>
					<Vertex X="1194" Y="889" Z="0"/>
					<Vertex X="1196" Y="889" Z="0"/>
					<Vertex X="1197" Y="889" Z="0"/>
					<Vertex X="1199" Y="889" Z="0"/>
					<Vertex X="1200" Y="888" Z="0"/>
					<Vertex X="1202" Y="888" Z="0"/>
					<Vertex X="1204" Y="888" Z="0"/>
					<Vertex X="1205" Y="888" Z="0"/>
					<Vertex X="1207" Y="888" Z="0"/>
					<Vertex X="1208" Y="888" Z="0"/>
					<Vertex X="1210" Y="888" Z="0"/>
					<Vertex X="1212" Y="888" Z="0"/>
					<Vertex X="1213" Y="888" Z="0"/>
					<Vertex X="1215" Y="888" Z="0"/>
					<Vertex X="1218" Y="886" Z="0"/>
					<Vertex X="1219" Y="886" Z="0"/>
					<Vertex X="1221" Y="886" Z="0"/>
					<Vertex X="1223" Y="886" Z="0"/>
					<Vertex X="1224" Y="886" Z="0"/>
					<Vertex X="1226" Y="885" Z="0"/>
					<Vertex X="1227" Y="885" Z="0"/>
					<Vertex X="1229" Y="885" Z="0"/>
					<Vertex X="1231" Y="885" Z="0"/>
					<Vertex X="1232" Y="885" Z="0"/>
					<Vertex X="1234" Y="885" Z="0"/>
					<Vertex X="1235" Y="885" Z="0"/>
					<Vertex X="1237" Y="883" Z="0"/>
					<Vertex X="1239" Y="883" Z="0"/>
					<Vertex X="1240" Y="883" Z="0"/>
					<Vertex X="1242" Y="883" Z="0"/>
					<Vertex X="1243" Y="883" Z="0"/>
					<Vertex X="1245" Y="883" Z="0"/>
					<Vertex X="1246" Y="883" Z="0"/>
					<Vertex X="1248" Y="883" Z="0"/>
					<Vertex X="1250" Y="883" Z="0"/>
					<Vertex X="1250" Y="881" Z="0"/>
					<Vertex X="1251" Y="881" Z="0"/>
					<Vertex X="1253" Y="881" Z="0"/>
					<Vertex X="1254" Y="881" Z="0"/>
					<Vertex X="1256" Y="881" Z="0"/>
					<Vertex X="1258" Y="881" Z="0"/>
					<Vertex X="1259" Y="880" Z="0"/>
					<Vertex X="1261" Y="880" Z="0"/>
					<Vertex X="1262" Y="880" Z="0"/>
					<Vertex X="1264" Y="880" Z="0"/>
					<Vertex X="1266" Y="880" Z="0"/>
					<Vertex X="1267" Y="880" Z="0"/>
					<Vertex X="1269" Y="878" Z="0"/>
					<Vertex X="1270" Y="878" Z="0"/>
					<Vertex X="1272" Y="878" Z="0"/>
					<Vertex X="1273" Y="878" Z="0"/>
					<Vertex X="1275" Y="877" Z="0"/>
					<Vertex X="1277" Y="877" Z="0"/>
					<Vertex X="1278" Y="877" Z="0"/>
					<Vertex X="1280" Y="877" Z="0"/>
					<Vertex X="1281" Y="877" Z="0"/>
					<Vertex X="1283" Y="877" Z="0"/>
					<Vertex X="1285" Y="877" Z="0"/>
					<Vertex X="1286" Y="877" Z="0"/>
					<Vertex X="1288" Y="875" Z="0"/>
					<Vertex X="1289" Y="875" Z="0"/>
					<Vertex X="1291" Y="875" Z="0"/>
					<Vertex X="1292" Y="875" Z="0"/>
					<Vertex X="1294" Y="873" Z="0"/>
					<Vertex X="1296" Y="873" Z="0"/>
					<Vertex X="1297" Y="873" Z="0"/>
					<Vertex X="1299" Y="873" Z="0"/>
					<Vertex X="1302" Y="873" Z="0"/>
					<Vertex X="1304" Y="872" Z="0"/>
					<Vertex X="1305" Y="872" Z="0"/>
					<Vertex X="1307" Y="872" Z="0"/>
					<Vertex X="1308" Y="872" Z="0"/>
					<Vertex X="1310" Y="870" Z="0"/>
					<Vertex X="1312" Y="870" Z="0"/>
					<Vertex X="1313" Y="870" Z="0"/>
					<Vertex X="1315" Y="870" Z="0"/>
					<Vertex X="1316" Y="870" Z="0"/>
					<Vertex X="1318" Y="870" Z="0"/>
					<Vertex X="1319" Y="869" Z="0"/>
					<Vertex X="1321" Y="869" Z="0"/>
					<Vertex X="1323" Y="869" Z="0"/>
					<Vertex X="1324" Y="869" Z="0"/>
					<Vertex X="1326" Y="867" Z="0"/>
					<Vertex X="1327" Y="867" Z="0"/>
					<Vertex X="1331" Y="867" Z="0"/>
					<Vertex X="1332" Y="867" Z="0"/>
					<Vertex X="1334" Y="866" Z="0"/>
					<Vertex X="1335" Y="866" Z="0"/>
					<Vertex X="1337" Y="864" Z="0"/>
					<Vertex X="1340" Y="864" Z="0"/>
					<Vertex X="1342" Y="864" Z="0"/>
					<Vertex X="1343" Y="864" Z="0"/>
					<Vertex X="1345" Y="864" Z="0"/>
					<Vertex X="1346" Y="862" Z="0"/>
					<Vertex X="1348" Y="862" Z="0"/>
					<Vertex X="1350" Y="862" Z="0"/>
					<Vertex X="1351" Y="861" Z="0"/>
					<Vertex X="1353" Y="861" Z="0"/>
					<Vertex X="1354" Y="861" Z="0"/>
					<Vertex X="1356" Y="861" Z="0"/>
					<Vertex X="1358" Y="859" Z="0"/>
					<Vertex X="1359" Y="859" Z="0"/>
					<Vertex X="1361" Y="859" Z="0"/>
					<Vertex X="1362" Y="858" Z="0"/>
					<Vertex X="1364" Y="858" Z="0"/>
					<Vertex X="1366" Y="858" Z="0"/>
					<Vertex X="1367" Y="858" Z="0"/>
					<Vertex X="1367" Y="856" Z="0"/>
					<Vertex X="1370" Y="856" Z="0"/>
					<Vertex X="1372" Y="856" Z="0"/>
					<Vertex X="1373" Y="854" Z="0"/>
					<Vertex X="1375" Y="854" Z="0"/>
					<Vertex X="1377" Y="854" Z="0"/>
					<Vertex X="1378" Y="853" Z="0"/>
					<Vertex X="1380" Y="853" Z="0"/>
					<Vertex X="1383" Y="851" Z="0"/>
					<Vertex X="1385" Y="851" Z="0"/>
					<Vertex X="1386" Y="851" Z="0"/>
					<Vertex X="1388" Y="850" Z="0"/>
					<Vertex X="1389" Y="850" Z="0"/>
					<Vertex X="1391" Y="850" Z="0"/>
					<Vertex X="1392" Y="848" Z="0"/>
					<Vertex X="1394" Y="848" Z="0"/>
					<Vertex X="1396" Y="848" Z="0"/>
					<Vertex X="1397" Y="846" Z="0"/>
					<Vertex X="1399" Y="846" Z="0"/>
					<Vertex X="1399" Y="845" Z="0"/>
					<Vertex X="1400" Y="845" Z="0"/>
					<Vertex X="1402" Y="845" Z="0"/>
					<Vertex X="1404" Y="845" Z="0"/>
					<Vertex X="1405" Y="843" Z="0"/>
					<Vertex X="1407" Y="843" Z="0"/>
					<Vertex X="1408" Y="842" Z="0"/>
					<Vertex X="1410" Y="842" Z="0"/>
					<Vertex X="1412" Y="842" Z="0"/>
					<Vertex X="1412" Y="840" Z="0"/>
					<Vertex X="1413" Y="840" Z="0"/>
					<Vertex X="1415" Y="839" Z="0"/>
					<Vertex X="1416" Y="839" Z="0"/>
					<Vertex X="1418" Y="839" Z="0"/>
					<Vertex X="1418" Y="837" Z="0"/>
					<Vertex X="1419" Y="837" Z="0"/>
					<Vertex X="1421" Y="835" Z="0"/>
					<Vertex X="1423" Y="835" Z="0"/>
					<Vertex X="1423" Y="834" Z="0"/>
					<Vertex X="1424" Y="834" Z="0"/>
					<Vertex X="1426" Y="832" Z="0"/>
					<Vertex X="1427" Y="832" Z="0"/>
					<Vertex X="1427" Y="831" Z="0"/>
					<Vertex X="1429" Y="829" Z="0"/>
					<Vertex X="1431" Y="829" Z="0"/>
					<Vertex X="1432" Y="829" Z="0"/>
					<Vertex X="1432" Y="827" Z="0"/>
					<Vertex X="1434" Y="826" Z="0"/>
					<Vertex X="1435" Y="826" Z="0"/>
					<Vertex X="1437" Y="824" Z="0"/>
					<Vertex X="1439" Y="824" Z="0"/>
					<Vertex X="1439" Y="823" Z="0"/>
					<Vertex X="1440" Y="823" Z="0"/>
					<Vertex X="1442" Y="823" Z="0"/>
					<Vertex X="1442" Y="821" Z="0"/>
					<Vertex X="1443" Y="820" Z="0"/>
					<Vertex X="1445" Y="820" Z="0"/>
					<Vertex X="1446" Y="818" Z="0"/>
					<Vertex X="1448" Y="818" Z="0"/>
					<Vertex X="1450" Y="816" Z="0"/>
					<Vertex X="1451" Y="816" Z="0"/>
					<Vertex X="1451" Y="815" Z="0"/>
					<Vertex X="1453" Y="815" Z="0"/>
					<Vertex X="1454" Y="813" Z="0"/>
					<Vertex X="1456" Y="813" Z="0"/>
					<Vertex X="1456" Y="812" Z="0"/>
					<Vertex X="1458" Y="812" Z="0"/>
					<Vertex X="1458" Y="810" Z="0"/>
					<Vertex X="1459" Y="810" Z="0"/>
					<Vertex X="1461" Y="808" Z="0"/>
					<Vertex X="1462" Y="808" Z="0"/>
					<Vertex X="1462" Y="807" Z="0"/>
					<Vertex X="1464" Y="805" Z="0"/>
					<Vertex X="1466" Y="805" Z="0"/>
					<Vertex X="1466" Y="804" Z="0"/>
					<Vertex X="1467" Y="804" Z="0"/>
					<Vertex X="1467" Y="802" Z="0"/>
					<Vertex X="1469" Y="802" Z="0"/>
					<Vertex X="1469" Y="800" Z="0"/>
					<Vertex X="1470" Y="800" Z="0"/>
					<Vertex X="1470" Y="799" Z="0"/>
					<Vertex X="1472" Y="799" Z="0"/>
					<Vertex X="1472" Y="797" Z="0"/>
					<Vertex X="1473" Y="796" Z="0"/>
					<Vertex X="1473" Y="794" Z="0"/>
					<Vertex X="1475" Y="794" Z="0"/>
					<Vertex X="1475" Y="793" Z="0"/>
					<Vertex X="1477" Y="793" Z="0"/>
					<Vertex X="1477" Y="791" Z="0"/>
					<Vertex X="1477" Y="789" Z="0"/>
					<Vertex X="1478" Y="789" Z="0"/>
					<Vertex X="1478" Y="788" Z="0"/>
					<Vertex X="1480" Y="788" Z="0"/>
					<Vertex X="1486" Y="793" Z="0"/>
					<Vertex X="1486" Y="791" Z="0"/>
					<Vertex X="1488" Y="791" Z="0"/>
					<Vertex X="1488" Y="789" Z="0"/>
					<Vertex X="1488" Y="788" Z="0"/>
					<Vertex X="1488" Y="786" Z="0"/>
					<Vertex X="1489" Y="786" Z="0"/>
					<Vertex X="1489" Y="785" Z="0"/>
					<Vertex X="1491" Y="783" Z="0"/>
					<Vertex X="1491" Y="781" Z="0"/>
					<Vertex X="1491" Y="780" Z="0"/>
					<Vertex X="1491" Y="778" Z="0"/>
					<Vertex X="1492" Y="778" Z="0"/>
					<Vertex X="1492" Y="777" Z="0"/>
					<Vertex X="1492" Y="775" Z="0"/>
					<Vertex X="1494" Y="775" Z="0"/>
					<Vertex X="1494" Y="773" Z="0"/>
					<Vertex X="1494" Y="772" Z="0"/>
					<Vertex X="1494" Y="770" Z="0"/>
					<Vertex X="1494" Y="769" Z="0"/>
					<Vertex X="1496" Y="767" Z="0"/>
					<Vertex X="1496" Y="766" Z="0"/>
					<Vertex X="1496" Y="764" Z="0"/>
					<Vertex X="1496" Y="762" Z="0"/>
					<Vertex X="1496" Y="761" Z="0"/>
					<Vertex X="1496" Y="759" Z="0"/>
					<Vertex X="1496" Y="758" Z="0"/>
					<Vertex X="1496" Y="756" Z="0"/>
					<Vertex X="1496" Y="754" Z="0"/>
					<Vertex X="1496" Y="753" Z="0"/>
					<Vertex X="1496" Y="751" Z="0"/>
					<Vertex X="1496" Y="750" Z="0"/>
					<Vertex X="1496" Y="748" Z="0"/>
					<Vertex X="1496" Y="746" Z="0"/>
					<Vertex X="1496" Y="745" Z="0"/>
					<Vertex X="1496" Y="743" Z="0"/>
					<Vertex X="1494" Y="742" Z="0"/>
					<Vertex X="1494" Y="740" Z="0"/>
					<Vertex X="1494" Y="739" Z="0"/>
					<Vertex X="1494" Y="737" Z="0"/>
					<Vertex X="1494" Y="735" Z="0"/>
					<Vertex X="1494" Y="734" Z="0"/>
					<Vertex X="1494" Y="732" Z="0"/>
					<Vertex X="1494" Y="731" Z="0"/>
					<Vertex X="1494" Y="729" Z="0"/>
					<Vertex X="1492" Y="726" Z="0"/>
					<Vertex X="1492" Y="724" Z="0"/>
					<Vertex X="1492" Y="723" Z="0"/>
					<Vertex X="1492" Y="721" Z="0"/>
					<Vertex X="1492" Y="720" Z="0"/>
					<Vertex X="1491" Y="718" Z="0"/>
					<Vertex X="1491" Y="716" Z="0"/>
					<Vertex X="1491" Y="715" Z="0"/>
					<Vertex X="1489" Y="713" Z="0"/>
					<Vertex X="1489" Y="712" Z="0"/>
					<Vertex X="1489" Y="710" Z="0"/>
					<Vertex X="1489" Y="708" Z="0"/>
					<Vertex X="1489" Y="707" Z="0"/>
					<Vertex X="1488" Y="707" Z="0"/>
					<Vertex X="1488" Y="705" Z="0"/>
					<Vertex X="1488" Y="704" Z="0"/>
					<Vertex X="1486" Y="702" Z="0"/>
					<Vertex X="1486" Y="700" Z="0"/>
					<Vertex X="1486" Y="699" Z="0"/>
					<Vertex X="1486" Y="697" Z="0"/>
					<Vertex X="1485" Y="697" Z="0"/>
					<Vertex X="1485" Y="696" Z="0"/>
					<Vertex X="1485" Y="694" Z="0"/>
					<Vertex X="1485" Y="693" Z="0"/>
					<Vertex X="1483" Y="691" Z="0"/>
					<Vertex X="1483" Y="689" Z="0"/>
					<Vertex X="1483" Y="686" Z="0"/>
					<Vertex X="1483" Y="683" Z="0"/>
					<Vertex X="1483" Y="680" Z="0"/>
					<Vertex X="1483" Y="678" Z="0"/>
					<Vertex X="1483" Y="677" Z="0"/>
					<Vertex X="1483" Y="675" Z="0"/>
					<Vertex X="1483" Y="673" Z="0"/>
					<Vertex X="1483" Y="670" Z="0"/>
					<Vertex X="1483" Y="667" Z="0"/>
					<Vertex X="1483" Y="664" Z="0"/>
					<Vertex X="1483" Y="662" Z="0"/>
					<Vertex X="1483" Y="661" Z="0"/>
					<Vertex X="1485" Y="658" Z="0"/>
					<Vertex X="1485" Y="656" Z="0"/>
					<Vertex X="1485" Y="654" Z="0"/>
					<Vertex X="1485" Y="651" Z="0"/>
					<Vertex X="1485" Y="648" Z="0"/>
					<Vertex X="1485" Y="645" Z="0"/>
					<Vertex X="1485" Y="642" Z="0"/>
					<Vertex X="1485" Y="640" Z="0"/>
					<Vertex X="1485" Y="637" Z="0"/>
					<Vertex X="1485" Y="634" Z="0"/>
					<Vertex X="1486" Y="632" Z="0"/>
					<Vertex X="1486" Y="629" Z="0"/>
					<Vertex X="1486" Y="626" Z="0"/>
					<Vertex X="1486" Y="623" Z="0"/>
					<Vertex X="1486" Y="618" Z="0"/>
					<Vertex X="1488" Y="615" Z="0"/>
					<Vertex X="1488" Y="610" Z="0"/>
					<Vertex X="1488" Y="607" Z="0"/>
					<Vertex X="1488" Y="604" Z="0"/>
					<Vertex X="1488" Y="602" Z="0"/>
					<Vertex X="1488" Y="599" Z="0"/>
					<Vertex X="1488" Y="597" Z="0"/>
					<Vertex X="1488" Y="596" Z="0"/>
					<Vertex X="1489" Y="593" Z="0"/>
					<Vertex X="1489" Y="589" Z="0"/>
					<Vertex X="1489" Y="586" Z="0"/>
					<Vertex X="1491" Y="585" Z="0"/>
					<Vertex X="1491" Y="583" Z="0"/>
					<Vertex X="1491" Y="580" Z="0"/>
					<Vertex X="1491" Y="577" Z="0"/>
					<Vertex X="1491" Y="573" Z="0"/>
					<Vertex X="1491" Y="572" Z="0"/>
					<Vertex X="1491" Y="570" Z="0"/>
					<Vertex X="1492" Y="566" Z="0"/>
					<Vertex X="1492" Y="564" Z="0"/>
					<Vertex X="1492" Y="561" Z="0"/>
					<Vertex X="1492" Y="558" Z="0"/>
					<Vertex X="1492" Y="556" Z="0"/>
					<Vertex X="1492" Y="554" Z="0"/>
					<Vertex X="1492" Y="553" Z="0"/>
					<Vertex X="1492" Y="550" Z="0"/>
					<Vertex X="1492" Y="546" Z="0"/>
					<Vertex X="1492" Y="545" Z="0"/>
					<Vertex X="1492" Y="543" Z="0"/>
					<Vertex X="1492" Y="542" Z="0"/>
					<Vertex X="1492" Y="540" Z="0"/>
					<Vertex X="1492" Y="537" Z="0"/>
					<Vertex X="1492" Y="535" Z="0"/>
					<Vertex X="1492" Y="534" Z="0"/>
					<Vertex X="1492" Y="531" Z="0"/>
					<Vertex X="1492" Y="529" Z="0"/>
					<Vertex X="1492" Y="527" Z="0"/>
					<Vertex X="1492" Y="526" Z="0"/>
					<Vertex X="1492" Y="524" Z="0"/>
					<Vertex X="1492" Y="521" Z="0"/>
					<Vertex X="1492" Y="518" Z="0"/>
					<Vertex X="1492" Y="516" Z="0"/>
					<Vertex X="1492" Y="515" Z="0"/>
					<Vertex X="1492" Y="512" Z="0"/>
					<Vertex X="1492" Y="508" Z="0"/>
					<Vertex X="1492" Y="507" Z="0"/>
					<Vertex X="1492" Y="505" Z="0"/>
					<Vertex X="1491" Y="502" Z="0"/>
					<Vertex X="1491" Y="499" Z="0"/>
					<Vertex X="1491" Y="496" Z="0"/>
					<Vertex X="1491" Y="493" Z="0"/>
					<Vertex X="1491" Y="491" Z="0"/>
					<Vertex X="1491" Y="489" Z="0"/>
					<Vertex X="1491" Y="486" Z="0"/>
					<Vertex X="1489" Y="485" Z="0"/>
					<Vertex X="1489" Y="483" Z="0"/>
					<Vertex X="1489" Y="480" Z="0"/>
					<Vertex X="1489" Y="478" Z="0"/>
					<Vertex X="1489" Y="475" Z="0"/>
					<Vertex X="1488" Y="472" Z="0"/>
					<Vertex X="1488" Y="470" Z="0"/>
					<Vertex X="1488" Y="467" Z="0"/>
					<Vertex X="1488" Y="464" Z="0"/>
					<Vertex X="1486" Y="461" Z="0"/>
					<Vertex X="1486" Y="458" Z="0"/>
					<Vertex X="1486" Y="456" Z="0"/>
					<Vertex X="1485" Y="453" Z="0"/>
					<Vertex X="1485" Y="450" Z="0"/>
					<Vertex X="1483" Y="446" Z="0"/>
					<Vertex X="1483" Y="442" Z="0"/>
					<Vertex X="1483" Y="440" Z="0"/>
					<Vertex X="1481" Y="439" Z="0"/>
					<Vertex X="1480" Y="435" Z="0"/>
					<Vertex X="1480" Y="431" Z="0"/>
					<Vertex X="1478" Y="429" Z="0"/>
					<Vertex X="1477" Y="427" Z="0"/>
					<Vertex X="1475" Y="424" Z="0"/>
					<Vertex X="1473" Y="421" Z="0"/>
					<Vertex X="1473" Y="420" Z="0"/>
					<Vertex X="1472" Y="418" Z="0"/>
					<Vertex X="1470" Y="416" Z="0"/>
					<Vertex X="1470" Y="415" Z="0"/>
					<Vertex X="1470" Y="413" Z="0"/>
					<Vertex X="1469" Y="412" Z="0"/>
					<Vertex X="1469" Y="408" Z="0"/>
					<Vertex X="1467" Y="408" Z="0"/>
					<Vertex X="1467" Y="407" Z="0"/>
					<Vertex X="1466" Y="405" Z="0"/>
					<Vertex X="1464" Y="404" Z="0"/>
					<Vertex X="1464" Y="402" Z="0"/>
					<Vertex X="1464" Y="400" Z="0"/>
					<Vertex X="1462" Y="399" Z="0"/>
					<Vertex X="1461" Y="397" Z="0"/>
					<Vertex X="1459" Y="394" Z="0"/>
					<Vertex X="1459" Y="393" Z="0"/>
					<Vertex X="1458" Y="391" Z="0"/>
					<Vertex X="1456" Y="388" Z="0"/>
					<Vertex X="1454" Y="386" Z="0"/>
					<Vertex X="1453" Y="385" Z="0"/>
					<Vertex X="1453" Y="383" Z="0"/>
					<Vertex X="1451" Y="381" Z="0"/>
					<Vertex X="1450" Y="378" Z="0"/>
					<Vertex X="1448" Y="377" Z="0"/>
					<Vertex X="1446" Y="375" Z="0"/>
					<Vertex X="1445" Y="375" Z="0"/>
					<Vertex X="1445" Y="373" Z="0"/>
					<Vertex X="1443" Y="373" Z="0"/>
					<Vertex X="1442" Y="373" Z="0"/>
					<Vertex X="1440" Y="373" Z="0"/>
					<Vertex X="1439" Y="373" Z="0"/>
					<Vertex X="1437" Y="373" Z="0"/>
					<Vertex X="1434" Y="373" Z="0"/>
					<Vertex X="1429" Y="373" Z="0"/>
					<Vertex X="1426" Y="373" Z="0"/>
					<Vertex X="1424" Y="375" Z="0"/>
					<Vertex X="1421" Y="375" Z="0"/>
					<Vertex X="1419" Y="377" Z="0"/>
					<Vertex X="1418" Y="377" Z="0"/>
					<Vertex X="1413" Y="378" Z="0"/>
					<Vertex X="1408" Y="380" Z="0"/>
					<Vertex X="1402" Y="383" Z="0"/>
					<Vertex X="1399" Y="385" Z="0"/>
					<Vertex X="1394" Y="386" Z="0"/>
					<Vertex X="1389" Y="388" Z="0"/>
					<Vertex X="1386" Y="391" Z="0"/>
					<Vertex X="1383" Y="393" Z="0"/>
					<Vertex X="1380" Y="393" Z="0"/>
					<Vertex X="1380" Y="394" Z="0"/>
					<Vertex X="1378" Y="394" Z="0"/>
					<Vertex X="1377" Y="396" Z="0"/>
					<Vertex X="1373" Y="396" Z="0"/>
					<Vertex X="1372" Y="397" Z="0"/>
					<Vertex X="1369" Y="399" Z="0"/>
					<Vertex X="1366" Y="402" Z="0"/>
					<Vertex X="1361" Y="404" Z="0"/>
					<Vertex X="1358" Y="405" Z="0"/>
					<Vertex X="1353" Y="407" Z="0"/>
					<Vertex X="1350" Y="408" Z="0"/>
					<Vertex X="1346" Y="410" Z="0"/>
					<Vertex X="1343" Y="410" Z="0"/>
					<Vertex X="1340" Y="412" Z="0"/>
					<Vertex X="1339" Y="413" Z="0"/>
					<Vertex X="1337" Y="413" Z="0"/>
					<Vertex X="1334" Y="413" Z="0"/>
					<Vertex X="1329" Y="415" Z="0"/>
					<Vertex X="1323" Y="416" Z="0"/>
					<Vertex X="1318" Y="418" Z="0"/>
					<Vertex X="1313" Y="420" Z="0"/>
					<Vertex X="1305" Y="421" Z="0"/>
					<Vertex X="1297" Y="423" Z="0"/>
					<Vertex X="1294" Y="424" Z="0"/>
					<Vertex X="1292" Y="424" Z="0"/>
					<Vertex X="1291" Y="424" Z="0"/>
					<Vertex X="1288" Y="426" Z="0"/>
					<Vertex X="1280" Y="427" Z="0"/>
					<Vertex X="1275" Y="429" Z="0"/>
					<Vertex X="1269" Y="429" Z="0"/>
					<Vertex X="1264" Y="431" Z="0"/>
					<Vertex X="1259" Y="431" Z="0"/>
					<Vertex X="1253" Y="432" Z="0"/>
					<Vertex X="1243" Y="434" Z="0"/>
					<Vertex X="1239" Y="435" Z="0"/>
					<Vertex X="1234" Y="435" Z="0"/>
					<Vertex X="1232" Y="435" Z="0"/>
					<Vertex X="1231" Y="435" Z="0"/>
					<Vertex X="1226" Y="435" Z="0"/>
					<Vertex X="1218" Y="437" Z="0"/>
					<Vertex X="1207" Y="437" Z="0"/>
					<Vertex X="1200" Y="437" Z="0"/>
					<Vertex X="1196" Y="437" Z="0"/>
					<Vertex X="1192" Y="437" Z="0"/>
					<Vertex X="1189" Y="437" Z="0"/>
					<Vertex X="1185" Y="435" Z="0"/>
					<Vertex X="1180" Y="435" Z="0"/>
					<Vertex X="1172" Y="435" Z="0"/>
					<Vertex X="1166" Y="434" Z="0"/>
					<Vertex X="1159" Y="434" Z="0"/>
					<Vertex X="1154" Y="434" Z="0"/>
					<Vertex X="1150" Y="434" Z="0"/>
					<Vertex X="1143" Y="432" Z="0"/>
					<Vertex X="1139" Y="432" Z="0"/>
					<Vertex X="1132" Y="431" Z="0"/>
					<Vertex X="1126" Y="431" Z="0"/>
					<Vertex X="1119" Y="431" Z="0"/>
					<Vertex X="1115" Y="429" Z="0"/>
					<Vertex X="1110" Y="429" Z="0"/>
					<Vertex X="1107" Y="427" Z="0"/>
					<Vertex X="1100" Y="427" Z="0"/>
					<Vertex X="1094" Y="426" Z="0"/>
					<Vertex X="1085" Y="424" Z="0"/>
					<Vertex X="1078" Y="423" Z="0"/>
					<Vertex X="1075" Y="423" Z="0"/>
					<Vertex X="1072" Y="423" Z="0"/>
					<Vertex X="1067" Y="421" Z="0"/>
					<Vertex X="1061" Y="420" Z="0"/>
					<Vertex X="1051" Y="420" Z="0"/>
					<Vertex X="1043" Y="420" Z="0"/>
					<Vertex X="1037" Y="418" Z="0"/>
					<Vertex X="1032" Y="418" Z="0"/>
					<Vertex X="1031" Y="416" Z="0"/>
					<Vertex X="1029" Y="416" Z="0"/>
					<Vertex X="1023" Y="415" Z="0"/>
					<Vertex X="1015" Y="415" Z="0"/>
					<Vertex X="1007" Y="413" Z="0"/>
					<Vertex X="1000" Y="413" Z="0"/>
					<Vertex X="997" Y="413" Z="0"/>
					<Vertex X="994" Y="412" Z="0"/>
					<Vertex X="989" Y="412" Z="0"/>
					<Vertex X="981" Y="410" Z="0"/>
					<Vertex X="973" Y="408" Z="0"/>
					<Vertex X="970" Y="408" Z="0"/>
					<Vertex X="966" Y="407" Z="0"/>
					<Vertex X="961" Y="407" Z="0"/>
					<Vertex X="956" Y="405" Z="0"/>
					<Vertex X="950" Y="404" Z="0"/>
					<Vertex X="945" Y="404" Z="0"/>
					<Vertex X="942" Y="404" Z="0"/>
					<Vertex X="939" Y="404" Z="0"/>
					<Vertex X="937" Y="402" Z="0"/>
					<Vertex X="934" Y="402" Z="0"/>
					<Vertex X="931" Y="400" Z="0"/>
					<Vertex X="927" Y="400" Z="0"/>
					<Vertex X="923" Y="400" Z="0"/>
					<Vertex X="918" Y="400" Z="0"/>
					<Vertex X="913" Y="400" Z="0"/>
					<Vertex X="912" Y="400" Z="0"/>
					<Vertex X="908" Y="400" Z="0"/>
					<Vertex X="905" Y="400" Z="0"/>
					<Vertex X="902" Y="400" Z="0"/>
					<Vertex X="899" Y="400" Z="0"/>
					<Vertex X="897" Y="400" Z="0"/>
					<Vertex X="894" Y="400" Z="0"/>
					<Vertex X="892" Y="400" Z="0"/>
					<Vertex X="891" Y="400" Z="0"/>
					<Vertex X="889" Y="400" Z="0"/>
					<Vertex X="888" Y="400" Z="0"/>
					<Vertex X="883" Y="402" Z="0"/>
					<Vertex X="880" Y="402" Z="0"/>
					<Vertex X="875" Y="402" Z="0"/>
					<Vertex X="872" Y="402" Z="0"/>
					<Vertex X="869" Y="402" Z="0"/>
					<Vertex X="866" Y="402" Z="0"/>
					<Vertex X="861" Y="402" Z="0"/>
					<Vertex X="856" Y="402" Z="0"/>
					<Vertex X="853" Y="402" Z="0"/>
					<Vertex X="850" Y="402" Z="0"/>
					<Vertex X="846" Y="402" Z="0"/>
					<Vertex X="842" Y="402" Z="0"/>
					<Vertex X="835" Y="400" Z="0"/>
					<Vertex X="831" Y="400" Z="0"/>
					<Vertex X="827" Y="400" Z="0"/>
					<Vertex X="824" Y="400" Z="0"/>
					<Vertex X="819" Y="400" Z="0"/>
					<Vertex X="815" Y="399" Z="0"/>
					<Vertex X="808" Y="397" Z="0"/>
					<Vertex X="802" Y="396" Z="0"/>
					<Vertex X="797" Y="394" Z="0"/>
					<Vertex X="794" Y="394" Z="0"/>
					<Vertex X="789" Y="393" Z="0"/>
					<Vertex X="785" Y="391" Z="0"/>
					<Vertex X="781" Y="391" Z="0"/>
					<Vertex X="777" Y="391" Z="0"/>
					<Vertex X="772" Y="388" Z="0"/>
					<Vertex X="766" Y="388" Z="0"/>
					<Vertex X="761" Y="386" Z="0"/>
					<Vertex X="756" Y="385" Z="0"/>
					<Vertex X="751" Y="385" Z="0"/>
					<Vertex X="748" Y="383" Z="0"/>
					<Vertex X="743" Y="381" Z="0"/>
					<Vertex X="740" Y="381" Z="0"/>
					<Vertex X="737" Y="381" Z="0"/>
					<Vertex X="734" Y="380" Z="0"/>
					<Vertex X="729" Y="378" Z="0"/>
					<Vertex X="721" Y="378" Z="0"/>
					<Vertex X="716" Y="377" Z="0"/>
					<Vertex X="713" Y="377" Z="0"/>
					<Vertex X="710" Y="377" Z="0"/>
					<Vertex X="707" Y="375" Z="0"/>
					<Vertex X="704" Y="375" Z="0"/>
					<Vertex X="699" Y="375" Z="0"/>
					<Vertex X="696" Y="373" Z="0"/>
					<Vertex X="692" Y="373" Z="0"/>
					<Vertex X="689" Y="373" Z="0"/>
					<Vertex X="688" Y="373" Z="0"/>
					<Vertex X="685" Y="373" Z="0"/>
					<Vertex X="681" Y="373" Z="0"/>
					<Vertex X="678" Y="372" Z="0"/>
					<Vertex X="673" Y="372" Z="0"/>
					<Vertex X="670" Y="372" Z="0"/>
					<Vertex X="669" Y="372" Z="0"/>
					<Vertex X="666" Y="372" Z="0"/>
					<Vertex X="662" Y="372" Z="0"/>
					<Vertex X="659" Y="372" Z="0"/>
					<Vertex X="656" Y="372" Z="0"/>
					<Vertex X="654" Y="372" Z="0"/>
					<Vertex X="653" Y="372" Z="0"/>
					<Vertex X="651" Y="372" Z="0"/>
					<Vertex X="650" Y="372" Z="0"/>
					<Vertex X="646" Y="372" Z="0"/>
					<Vertex X="645" Y="372" Z="0"/>
					<Vertex X="642" Y="372" Z="0"/>
					<Vertex X="639" Y="372" Z="0"/>
					<Vertex X="634" Y="372" Z="0"/>
					<Vertex X="631" Y="372" Z="0"/>
					<Vertex X="627" Y="372" Z="0"/>
					<Vertex X="624" Y="372" Z="0"/>
					<Vertex X="621" Y="372" Z="0"/>
					<Vertex X="619" Y="372" Z="0"/>
					<Vertex X="616" Y="372" Z="0"/>
					<Vertex X="613" Y="370" Z="0"/>
					<Vertex X="608" Y="369" Z="0"/>
					<Vertex X="604" Y="367" Z="0"/>
					<Vertex X="599" Y="366" Z="0"/>
					<Vertex X="594" Y="366" Z="0"/>
					<Vertex X="589" Y="364" Z="0"/>
					<Vertex X="586" Y="362" Z="0"/>
					<Vertex X="585" Y="362" Z="0"/>
					<Vertex X="581" Y="361" Z="0"/>
					<Vertex X="578" Y="361" Z="0"/>
					<Vertex X="575" Y="359" Z="0"/>
					<Vertex X="570" Y="358" Z="0"/>
					<Vertex X="567" Y="356" Z="0"/>
					<Vertex X="564" Y="354" Z="0"/>
					<Vertex X="559" Y="353" Z="0"/>
					<Vertex X="556" Y="351" Z="0"/>
					<Vertex X="551" Y="350" Z="0"/>
					<Vertex X="548" Y="348" Z="0"/>
					<Vertex X="543" Y="346" Z="0"/>
					<Vertex X="539" Y="345" Z="0"/>
					<Vertex X="534" Y="343" Z="0"/>
					<Vertex X="529" Y="340" Z="0"/>
					<Vertex X="524" Y="339" Z="0"/>
					<Vertex X="519" Y="337" Z="0"/>
					<Vertex X="516" Y="335" Z="0"/>
					<Vertex X="512" Y="334" Z="0"/>
					<Vertex X="507" Y="332" Z="0"/>
					<Vertex X="502" Y="329" Z="0"/>
					<Vertex X="499" Y="327" Z="0"/>
					<Vertex X="494" Y="326" Z="0"/>
					<Vertex X="491" Y="326" Z="0"/>
					<Vertex X="488" Y="324" Z="0"/>
					<Vertex X="485" Y="323" Z="0"/>
					<Vertex X="483" Y="323" Z="0"/>
					<Vertex X="480" Y="321" Z="0"/>
					<Vertex X="477" Y="320" Z="0"/>
					<Vertex X="473" Y="320" Z="0"/>
					<Vertex X="470" Y="318" Z="0"/>
					<Vertex X="467" Y="318" Z="0"/>
					<Vertex X="464" Y="316" Z="0"/>
					<Vertex X="461" Y="316" Z="0"/>
					<Vertex X="456" Y="315" Z="0"/>
					<Vertex X="451" Y="315" Z="0"/>
					<Vertex X="450" Y="313" Z="0"/>
					<Vertex X="446" Y="313" Z="0"/>
					<Vertex X="443" Y="313" Z="0"/>
					<Vertex X="440" Y="313" Z="0"/>
					<Vertex X="437" Y="312" Z="0"/>
					<Vertex X="434" Y="312" Z="0"/>
					<Vertex X="429" Y="312" Z="0"/>
					<Vertex X="426" Y="312" Z="0"/>
					<Vertex X="423" Y="310" Z="0"/>
					<Vertex X="419" Y="310" Z="0"/>
					<Vertex X="415" Y="310" Z="0"/>
					<Vertex X="410" Y="310" Z="0"/>
					<Vertex X="405" Y="310" Z="0"/>
					<Vertex X="399" Y="310" Z="0"/>
					<Vertex X="394" Y="308" Z="0"/>
					<Vertex X="389" Y="308" Z="0"/>
					<Vertex X="385" Y="308" Z="0"/>
					<Vertex X="381" Y="308" Z="0"/>
					<Vertex X="375" Y="307" Z="0"/>
					<Vertex X="370" Y="307" Z="0"/>
					<Vertex X="367" Y="307" Z="0"/>
					<Vertex X="362" Y="307" Z="0"/>
					<Vertex X="359" Y="307" Z="0"/>
					<Vertex X="354" Y="307" Z="0"/>
					<Vertex X="350" Y="305" Z="0"/>
					<Vertex X="346" Y="304" Z="0"/>
					<Vertex X="342" Y="304" Z="0"/>
					<Vertex X="339" Y="302" Z="0"/>
					<Vertex X="335" Y="300" Z="0"/>
					<Vertex X="332" Y="300" Z="0"/>
					<Vertex X="329" Y="299" Z="0"/>
					<Vertex X="326" Y="297" Z="0"/>
					<Vertex X="321" Y="296" Z="0"/>
					<Vertex X="316" Y="294" Z="0"/>
					<Vertex X="312" Y="291" Z="0"/>
					<Vertex X="308" Y="289" Z="0"/>
					<Vertex X="304" Y="288" Z="0"/>
					<Vertex X="299" Y="286" Z="0"/>
					<Vertex X="296" Y="285" Z="0"/>
					<Vertex X="291" Y="281" Z="0"/>
					<Vertex X="288" Y="280" Z="0"/>
					<Vertex X="285" Y="278" Z="0"/>
					<Vertex X="283" Y="277" Z="0"/>
					<Vertex X="280" Y="275" Z="0"/>
					<Vertex X="278" Y="272" Z="0"/>
					<Vertex X="275" Y="270" Z="0"/>
					<Vertex X="272" Y="269" Z="0"/>
					<Vertex X="269" Y="266" Z="0"/>
					<Vertex X="266" Y="264" Z="0"/>
					<Vertex X="262" Y="261" Z="0"/>
					<Vertex X="261" Y="261" Z="0"/>
					<Vertex X="259" Y="258" Z="0"/>
					<Vertex X="256" Y="258" Z="0"/>
					<Vertex X="254" Y="256" Z="0"/>
					<Vertex X="254" Y="254" Z="0"/>
					<Vertex X="253" Y="254" Z="0"/>
					<Vertex X="251" Y="253" Z="0"/>
					<Vertex X="250" Y="251" Z="0"/>
					<Vertex X="248" Y="251" Z="0"/>
					<Vertex X="246" Y="250" Z="0"/>
					<Vertex X="243" Y="248" Z="0"/>
					<Vertex X="242" Y="248" Z="0"/>
					<Vertex X="239" Y="246" Z="0"/>
					<Vertex X="237" Y="245" Z="0"/>
					<Vertex X="234" Y="242" Z="0"/>
					<Vertex X="229" Y="239" Z="0"/>
					<Vertex X="224" Y="235" Z="0"/>
					<Vertex X="221" Y="234" Z="0"/>
					<Vertex X="219" Y="231" Z="0"/>
					<Vertex X="216" Y="229" Z="0"/>
					<Vertex X="213" Y="226" Z="0"/>
					<Vertex X="208" Y="223" Z="0"/>
					<Vertex X="204" Y="220" Z="0"/>
					<Vertex X="199" Y="215" Z="0"/>
					<Vertex X="194" Y="212" Z="0"/>
					<Vertex X="191" Y="208" Z="0"/>
					<Vertex X="186" Y="204" Z="0"/>
					<Vertex X="183" Y="200" Z="0"/>
					<Vertex X="178" Y="197" Z="0"/>
					<Vertex X="175" Y="194" Z="0"/>
					<Vertex X="170" Y="193" Z="0"/>
					<Vertex X="166" Y="188" Z="0"/>
					<Vertex X="161" Y="183" Z="0"/>
					<Vertex X="156" Y="180" Z="0"/>
					<Vertex X="151" Y="177" Z="0"/>
					<Vertex X="145" Y="172" Z="0"/>
					<Vertex X="140" Y="169" Z="0"/>
					<Vertex X="135" Y="166" Z="0"/>
					<Vertex X="129" Y="162" Z="0"/>
					<Vertex X="121" Y="158" Z="0"/>
					<Vertex X="115" Y="154" Z="0"/>
					<Vertex X="108" Y="153" Z="0"/>
					<Vertex X="104" Y="153" Z="0"/>
					<Vertex X="100" Y="153" Z="0"/>
					<Vertex X="94" Y="153" Z="0"/>
					<Vertex X="88" Y="153" Z="0"/>
					<Vertex X="83" Y="153" Z="0"/>
					<Vertex X="80" Y="153" Z="0"/>
					<Vertex X="77" Y="153" Z="0"/>
					<Vertex X="70" Y="154" Z="0"/>
					<Vertex X="66" Y="156" Z="0"/>
					<Vertex X="61" Y="158" Z="0"/>
					<Vertex X="56" Y="159" Z="0"/>
					<Vertex X="53" Y="161" Z="0"/>
					<Vertex X="50" Y="162" Z="0"/>
					<Vertex X="48" Y="166" Z="0"/>
					<Vertex X="45" Y="167" Z="0"/>
					<Vertex X="43" Y="169" Z="0"/>
					<Vertex X="42" Y="172" Z="0"/>
					<Vertex X="39" Y="173" Z="0"/>
					<Vertex X="37" Y="175" Z="0"/>
					<Vertex X="35" Y="178" Z="0"/>
					<Vertex X="34" Y="180" Z="0"/>
					<Vertex X="32" Y="183" Z="0"/>
					<Vertex X="31" Y="185" Z="0"/>
					<Vertex X="29" Y="188" Z="0"/>
					<Vertex X="29" Y="191" Z="0"/>
					<Vertex X="27" Y="194" Z="0"/>
					<Vertex X="26" Y="197" Z="0"/>
					<Vertex X="26" Y="199" Z="0"/>
					<Vertex X="26" Y="202" Z="0"/>
					<Vertex X="24" Y="205" Z="0"/>
					<Vertex X="24" Y="208" Z="0"/>
					<Vertex X="23" Y="212" Z="0"/>
					<Vertex X="23" Y="215" Z="0"/>
					<Vertex X="21" Y="221" Z="0"/>
					<Vertex X="19" Y="224" Z="0"/>
					<Vertex X="19" Y="229" Z="0"/>
					<Vertex X="19" Y="232" Z="0"/>
					<Vertex X="18" Y="237" Z="0"/>
					<Vertex X="18" Y="242" Z="0"/>
					<Vertex X="18" Y="246" Z="0"/>
					<Vertex X="18" Y="251" Z="0"/>
					<Vertex X="18" Y="256" Z="0"/>
					<Vertex X="18" Y="261" Z="0"/>
					<Vertex X="18" Y="264" Z="0"/>
					<Vertex X="18" Y="269" Z="0"/>
					<Vertex X="18" Y="275" Z="0"/>
					<Vertex X="18" Y="280" Z="0"/>
					<Vertex X="18" Y="286" Z="0"/>
					<Vertex X="18" Y="293" Z="0"/>
					<Vertex X="19" Y="299" Z="0"/>
					<Vertex X="19" Y="305" Z="0"/>
					<Vertex X="21" Y="312" Z="0"/>
					<Vertex X="21" Y="318" Z="0"/>
					<Vertex X="21" Y="323" Z="0"/>
					<Vertex X="21" Y="327" Z="0"/>
					<Vertex X="21" Y="332" Z="0"/>
					<Vertex X="21" Y="337" Z="0"/>
					<Vertex X="21" Y="343" Z="0"/>
					<Vertex X="21" Y="350" Z="0"/>
					<Vertex X="21" Y="356" Z="0"/>
					<Vertex X="21" Y="361" Z="0"/>
					<Vertex X="21" Y="367" Z="0"/>
					<Vertex X="21" Y="373" Z="0"/>
					<Vertex X="21" Y="380" Z="0"/>
					<Vertex X="21" Y="388" Z="0"/>
					<Vertex X="21" Y="394" Z="0"/>
					<Vertex X="21" Y="402" Z="0"/>
					<Vertex X="21" Y="410" Z="0"/>
					<Vertex X="19" Y="418" Z="0"/>
					<Vertex X="19" Y="427" Z="0"/>
					<Vertex X="16" Y="439" Z="0"/>
					<Vertex X="15" Y="451" Z="0"/>
					<Vertex X="13" Y="462" Z="0"/>
					<Vertex X="13" Y="470" Z="0"/>
					<Vertex X="13" Y="475" Z="0"/>
				</Vertices>
			</Region>
		</Regions>
		<Plots/>
	</Annotation>
</Annotations>
