<Annotations>
	<Annotation Id="1" Name="Ivan" ReadOnly="0" NameReadOnly="0" LineColorReadOnly="0" Incremental="0" Type="4" LineColor="255" Visible="1" Selected="1" MarkupImagePath="" MacroName="">
		<Attributes/>
		<Regions>
			<RegionAttributeHeaders>
				<AttributeHeader Id="9999" Name="Region" ColumnWidth="-1"/>
				<AttributeHeader Id="9997" Name="Length" ColumnWidth="-1"/>
				<AttributeHeader Id="9996" Name="Area" ColumnWidth="-1"/>
				<AttributeHeader Id="9998" Name="Text" ColumnWidth="-1"/>
				<AttributeHeader Id="1" Name="Description" ColumnWidth="-1"/>
			</RegionAttributeHeaders>
			<Region Id="1" Type="0" Zoom="0.221208" Selected="1" ImageLocation="" ImageFocus="-1" Length="7683.8" Area="1445905.5" Text="" NegativeROA="0" InputRegionId="0" Analyze="1" DisplayId="1">
				<Attributes/>
				<Vertices>
					<Vertex X="908" Y="773" Z="0"/>
					<Vertex X="908" Y="778" Z="0"/>
					<Vertex X="908" Y="782" Z="0"/>
					<Vertex X="913" Y="782" Z="0"/>
					<Vertex X="913" Y="787" Z="0"/>
					<Vertex X="913" Y="791" Z="0"/>
					<Vertex X="917" Y="791" Z="0"/>
					<Vertex X="917" Y="796" Z="0"/>
					<Vertex X="922" Y="800" Z="0"/>
					<Vertex X="922" Y="805" Z="0"/>
					<Vertex X="926" Y="805" Z="0"/>
					<Vertex X="926" Y="809" Z="0"/>
					<Vertex X="926" Y="814" Z="0"/>
					<Vertex X="931" Y="814" Z="0"/>
					<Vertex X="931" Y="818" Z="0"/>
					<Vertex X="935" Y="818" Z="0"/>
					<Vertex X="935" Y="823" Z="0"/>
					<Vertex X="935" Y="827" Z="0"/>
					<Vertex X="940" Y="827" Z="0"/>
					<Vertex X="940" Y="832" Z="0"/>
					<Vertex X="940" Y="836" Z="0"/>
					<Vertex X="945" Y="836" Z="0"/>
					<Vertex X="945" Y="841" Z="0"/>
					<Vertex X="945" Y="845" Z="0"/>
					<Vertex X="949" Y="845" Z="0"/>
					<Vertex X="949" Y="850" Z="0"/>
					<Vertex X="949" Y="854" Z="0"/>
					<Vertex X="954" Y="854" Z="0"/>
					<Vertex X="954" Y="859" Z="0"/>
					<Vertex X="954" Y="863" Z="0"/>
					<Vertex X="958" Y="868" Z="0"/>
					<Vertex X="958" Y="872" Z="0"/>
					<Vertex X="963" Y="872" Z="0"/>
					<Vertex X="963" Y="877" Z="0"/>
					<Vertex X="963" Y="882" Z="0"/>
					<Vertex X="967" Y="882" Z="0"/>
					<Vertex X="967" Y="886" Z="0"/>
					<Vertex X="967" Y="891" Z="0"/>
					<Vertex X="972" Y="891" Z="0"/>
					<Vertex X="972" Y="895" Z="0"/>
					<Vertex X="972" Y="900" Z="0"/>
					<Vertex X="976" Y="900" Z="0"/>
					<Vertex X="976" Y="904" Z="0"/>
					<Vertex X="981" Y="909" Z="0"/>
					<Vertex X="981" Y="913" Z="0"/>
					<Vertex X="981" Y="918" Z="0"/>
					<Vertex X="985" Y="918" Z="0"/>
					<Vertex X="985" Y="922" Z="0"/>
					<Vertex X="985" Y="927" Z="0"/>
					<Vertex X="990" Y="927" Z="0"/>
					<Vertex X="990" Y="931" Z="0"/>
					<Vertex X="990" Y="936" Z="0"/>
					<Vertex X="994" Y="936" Z="0"/>
					<Vertex X="994" Y="940" Z="0"/>
					<Vertex X="994" Y="945" Z="0"/>
					<Vertex X="999" Y="945" Z="0"/>
					<Vertex X="999" Y="949" Z="0"/>
					<Vertex X="999" Y="954" Z="0"/>
					<Vertex X="1003" Y="954" Z="0"/>
					<Vertex X="1003" Y="958" Z="0"/>
					<Vertex X="1003" Y="963" Z="0"/>
					<Vertex X="1003" Y="967" Z="0"/>
					<Vertex X="1003" Y="972" Z="0"/>
					<Vertex X="1008" Y="972" Z="0"/>
					<Vertex X="1008" Y="976" Z="0"/>
					<Vertex X="1008" Y="981" Z="0"/>
					<Vertex X="1012" Y="981" Z="0"/>
					<Vertex X="1012" Y="985" Z="0"/>
					<Vertex X="1012" Y="990" Z="0"/>
					<Vertex X="1012" Y="995" Z="0"/>
					<Vertex X="1017" Y="995" Z="0"/>
					<Vertex X="1017" Y="999" Z="0"/>
					<Vertex X="1017" Y="1004" Z="0"/>
					<Vertex X="1021" Y="1004" Z="0"/>
					<Vertex X="1021" Y="1008" Z="0"/>
					<Vertex X="1021" Y="1013" Z="0"/>
					<Vertex X="1021" Y="1017" Z="0"/>
					<Vertex X="1026" Y="1017" Z="0"/>
					<Vertex X="1026" Y="1022" Z="0"/>
					<Vertex X="1026" Y="1026" Z="0"/>
					<Vertex X="1026" Y="1031" Z="0"/>
					<Vertex X="1030" Y="1031" Z="0"/>
					<Vertex X="1030" Y="1035" Z="0"/>
					<Vertex X="1030" Y="1040" Z="0"/>
					<Vertex X="1030" Y="1044" Z="0"/>
					<Vertex X="1035" Y="1044" Z="0"/>
					<Vertex X="1035" Y="1049" Z="0"/>
					<Vertex X="1035" Y="1053" Z="0"/>
					<Vertex X="1039" Y="1058" Z="0"/>
					<Vertex X="1039" Y="1062" Z="0"/>
					<Vertex X="1039" Y="1067" Z="0"/>
					<Vertex X="1039" Y="1071" Z="0"/>
					<Vertex X="1044" Y="1071" Z="0"/>
					<Vertex X="1044" Y="1076" Z="0"/>
					<Vertex X="1044" Y="1080" Z="0"/>
					<Vertex X="1048" Y="1080" Z="0"/>
					<Vertex X="1048" Y="1085" Z="0"/>
					<Vertex X="1048" Y="1089" Z="0"/>
					<Vertex X="1048" Y="1094" Z="0"/>
					<Vertex X="1053" Y="1094" Z="0"/>
					<Vertex X="1053" Y="1099" Z="0"/>
					<Vertex X="1053" Y="1103" Z="0"/>
					<Vertex X="1058" Y="1103" Z="0"/>
					<Vertex X="1058" Y="1108" Z="0"/>
					<Vertex X="1058" Y="1112" Z="0"/>
					<Vertex X="1058" Y="1117" Z="0"/>
					<Vertex X="1062" Y="1117" Z="0"/>
					<Vertex X="1062" Y="1121" Z="0"/>
					<Vertex X="1062" Y="1126" Z="0"/>
					<Vertex X="1067" Y="1130" Z="0"/>
					<Vertex X="1067" Y="1135" Z="0"/>
					<Vertex X="1067" Y="1139" Z="0"/>
					<Vertex X="1067" Y="1144" Z="0"/>
					<Vertex X="1071" Y="1144" Z="0"/>
					<Vertex X="1071" Y="1148" Z="0"/>
					<Vertex X="1071" Y="1153" Z="0"/>
					<Vertex X="1076" Y="1153" Z="0"/>
					<Vertex X="1076" Y="1157" Z="0"/>
					<Vertex X="1076" Y="1162" Z="0"/>
					<Vertex X="1076" Y="1166" Z="0"/>
					<Vertex X="1080" Y="1166" Z="0"/>
					<Vertex X="1080" Y="1171" Z="0"/>
					<Vertex X="1080" Y="1175" Z="0"/>
					<Vertex X="1080" Y="1180" Z="0"/>
					<Vertex X="1085" Y="1180" Z="0"/>
					<Vertex X="1085" Y="1184" Z="0"/>
					<Vertex X="1085" Y="1189" Z="0"/>
					<Vertex X="1085" Y="1193" Z="0"/>
					<Vertex X="1089" Y="1193" Z="0"/>
					<Vertex X="1089" Y="1198" Z="0"/>
					<Vertex X="1089" Y="1202" Z="0"/>
					<Vertex X="1094" Y="1207" Z="0"/>
					<Vertex X="1094" Y="1212" Z="0"/>
					<Vertex X="1094" Y="1216" Z="0"/>
					<Vertex X="1098" Y="1221" Z="0"/>
					<Vertex X="1098" Y="1225" Z="0"/>
					<Vertex X="1103" Y="1225" Z="0"/>
					<Vertex X="1103" Y="1230" Z="0"/>
					<Vertex X="1103" Y="1234" Z="0"/>
					<Vertex X="1103" Y="1239" Z="0"/>
					<Vertex X="1103" Y="1243" Z="0"/>
					<Vertex X="1107" Y="1243" Z="0"/>
					<Vertex X="1107" Y="1248" Z="0"/>
					<Vertex X="1107" Y="1252" Z="0"/>
					<Vertex X="1112" Y="1252" Z="0"/>
					<Vertex X="1112" Y="1257" Z="0"/>
					<Vertex X="1112" Y="1261" Z="0"/>
					<Vertex X="1116" Y="1261" Z="0"/>
					<Vertex X="1116" Y="1266" Z="0"/>
					<Vertex X="1121" Y="1270" Z="0"/>
					<Vertex X="1121" Y="1275" Z="0"/>
					<Vertex X="1121" Y="1279" Z="0"/>
					<Vertex X="1125" Y="1279" Z="0"/>
					<Vertex X="1125" Y="1284" Z="0"/>
					<Vertex X="1130" Y="1288" Z="0"/>
					<Vertex X="1130" Y="1293" Z="0"/>
					<Vertex X="1130" Y="1297" Z="0"/>
					<Vertex X="1134" Y="1297" Z="0"/>
					<Vertex X="1134" Y="1302" Z="0"/>
					<Vertex X="1139" Y="1302" Z="0"/>
					<Vertex X="1139" Y="1306" Z="0"/>
					<Vertex X="1139" Y="1311" Z="0"/>
					<Vertex X="1139" Y="1316" Z="0"/>
					<Vertex X="1143" Y="1316" Z="0"/>
					<Vertex X="1143" Y="1320" Z="0"/>
					<Vertex X="1148" Y="1320" Z="0"/>
					<Vertex X="1148" Y="1325" Z="0"/>
					<Vertex X="1148" Y="1329" Z="0"/>
					<Vertex X="1152" Y="1329" Z="0"/>
					<Vertex X="1152" Y="1334" Z="0"/>
					<Vertex X="1157" Y="1334" Z="0"/>
					<Vertex X="1157" Y="1338" Z="0"/>
					<Vertex X="1157" Y="1343" Z="0"/>
					<Vertex X="1157" Y="1347" Z="0"/>
					<Vertex X="1162" Y="1347" Z="0"/>
					<Vertex X="1162" Y="1352" Z="0"/>
					<Vertex X="1166" Y="1352" Z="0"/>
					<Vertex X="1166" Y="1356" Z="0"/>
					<Vertex X="1166" Y="1361" Z="0"/>
					<Vertex X="1166" Y="1365" Z="0"/>
					<Vertex X="1171" Y="1365" Z="0"/>
					<Vertex X="1171" Y="1370" Z="0"/>
					<Vertex X="1175" Y="1370" Z="0"/>
					<Vertex X="1175" Y="1374" Z="0"/>
					<Vertex X="1175" Y="1379" Z="0"/>
					<Vertex X="1180" Y="1379" Z="0"/>
					<Vertex X="1180" Y="1383" Z="0"/>
					<Vertex X="1184" Y="1388" Z="0"/>
					<Vertex X="1184" Y="1392" Z="0"/>
					<Vertex X="1189" Y="1392" Z="0"/>
					<Vertex X="1189" Y="1397" Z="0"/>
					<Vertex X="1189" Y="1401" Z="0"/>
					<Vertex X="1193" Y="1406" Z="0"/>
					<Vertex X="1193" Y="1410" Z="0"/>
					<Vertex X="1198" Y="1410" Z="0"/>
					<Vertex X="1198" Y="1415" Z="0"/>
					<Vertex X="1198" Y="1419" Z="0"/>
					<Vertex X="1202" Y="1419" Z="0"/>
					<Vertex X="1202" Y="1424" Z="0"/>
					<Vertex X="1202" Y="1429" Z="0"/>
					<Vertex X="1207" Y="1429" Z="0"/>
					<Vertex X="1207" Y="1433" Z="0"/>
					<Vertex X="1207" Y="1438" Z="0"/>
					<Vertex X="1211" Y="1442" Z="0"/>
					<Vertex X="1211" Y="1447" Z="0"/>
					<Vertex X="1216" Y="1447" Z="0"/>
					<Vertex X="1216" Y="1451" Z="0"/>
					<Vertex X="1216" Y="1456" Z="0"/>
					<Vertex X="1220" Y="1456" Z="0"/>
					<Vertex X="1220" Y="1460" Z="0"/>
					<Vertex X="1225" Y="1465" Z="0"/>
					<Vertex X="1225" Y="1469" Z="0"/>
					<Vertex X="1229" Y="1469" Z="0"/>
					<Vertex X="1229" Y="1474" Z="0"/>
					<Vertex X="1234" Y="1474" Z="0"/>
					<Vertex X="1234" Y="1478" Z="0"/>
					<Vertex X="1234" Y="1483" Z="0"/>
					<Vertex X="1238" Y="1483" Z="0"/>
					<Vertex X="1238" Y="1487" Z="0"/>
					<Vertex X="1243" Y="1487" Z="0"/>
					<Vertex X="1243" Y="1492" Z="0"/>
					<Vertex X="1243" Y="1496" Z="0"/>
					<Vertex X="1247" Y="1496" Z="0"/>
					<Vertex X="1247" Y="1501" Z="0"/>
					<Vertex X="1252" Y="1501" Z="0"/>
					<Vertex X="1252" Y="1505" Z="0"/>
					<Vertex X="1252" Y="1510" Z="0"/>
					<Vertex X="1256" Y="1510" Z="0"/>
					<Vertex X="1256" Y="1514" Z="0"/>
					<Vertex X="1261" Y="1514" Z="0"/>
					<Vertex X="1261" Y="1519" Z="0"/>
					<Vertex X="1265" Y="1519" Z="0"/>
					<Vertex X="1265" Y="1523" Z="0"/>
					<Vertex X="1270" Y="1523" Z="0"/>
					<Vertex X="1270" Y="1528" Z="0"/>
					<Vertex X="1270" Y="1532" Z="0"/>
					<Vertex X="1275" Y="1532" Z="0"/>
					<Vertex X="1275" Y="1537" Z="0"/>
					<Vertex X="1279" Y="1537" Z="0"/>
					<Vertex X="1279" Y="1542" Z="0"/>
					<Vertex X="1279" Y="1546" Z="0"/>
					<Vertex X="1284" Y="1546" Z="0"/>
					<Vertex X="1288" Y="1551" Z="0"/>
					<Vertex X="1288" Y="1555" Z="0"/>
					<Vertex X="1293" Y="1555" Z="0"/>
					<Vertex X="1293" Y="1560" Z="0"/>
					<Vertex X="1297" Y="1564" Z="0"/>
					<Vertex X="1297" Y="1569" Z="0"/>
					<Vertex X="1302" Y="1569" Z="0"/>
					<Vertex X="1302" Y="1573" Z="0"/>
					<Vertex X="1306" Y="1573" Z="0"/>
					<Vertex X="1306" Y="1578" Z="0"/>
					<Vertex X="1306" Y="1582" Z="0"/>
					<Vertex X="1311" Y="1582" Z="0"/>
					<Vertex X="1311" Y="1587" Z="0"/>
					<Vertex X="1315" Y="1587" Z="0"/>
					<Vertex X="1315" Y="1591" Z="0"/>
					<Vertex X="1320" Y="1591" Z="0"/>
					<Vertex X="1320" Y="1596" Z="0"/>
					<Vertex X="1324" Y="1596" Z="0"/>
					<Vertex X="1324" Y="1600" Z="0"/>
					<Vertex X="1329" Y="1600" Z="0"/>
					<Vertex X="1329" Y="1605" Z="0"/>
					<Vertex X="1333" Y="1605" Z="0"/>
					<Vertex X="1333" Y="1609" Z="0"/>
					<Vertex X="1333" Y="1614" Z="0"/>
					<Vertex X="1338" Y="1614" Z="0"/>
					<Vertex X="1342" Y="1614" Z="0"/>
					<Vertex X="1342" Y="1618" Z="0"/>
					<Vertex X="1342" Y="1623" Z="0"/>
					<Vertex X="1347" Y="1623" Z="0"/>
					<Vertex X="1351" Y="1623" Z="0"/>
					<Vertex X="1351" Y="1627" Z="0"/>
					<Vertex X="1351" Y="1632" Z="0"/>
					<Vertex X="1356" Y="1632" Z="0"/>
					<Vertex X="1360" Y="1632" Z="0"/>
					<Vertex X="1360" Y="1636" Z="0"/>
					<Vertex X="1360" Y="1641" Z="0"/>
					<Vertex X="1365" Y="1641" Z="0"/>
					<Vertex X="1369" Y="1641" Z="0"/>
					<Vertex X="1369" Y="1646" Z="0"/>
					<Vertex X="1369" Y="1650" Z="0"/>
					<Vertex X="1374" Y="1650" Z="0"/>
					<Vertex X="1379" Y="1650" Z="0"/>
					<Vertex X="1379" Y="1655" Z="0"/>
					<Vertex X="1383" Y="1659" Z="0"/>
					<Vertex X="1388" Y="1659" Z="0"/>
					<Vertex X="1388" Y="1664" Z="0"/>
					<Vertex X="1392" Y="1664" Z="0"/>
					<Vertex X="1392" Y="1668" Z="0"/>
					<Vertex X="1397" Y="1668" Z="0"/>
					<Vertex X="1401" Y="1673" Z="0"/>
					<Vertex X="1401" Y="1677" Z="0"/>
					<Vertex X="1406" Y="1677" Z="0"/>
					<Vertex X="1410" Y="1677" Z="0"/>
					<Vertex X="1410" Y="1682" Z="0"/>
					<Vertex X="1415" Y="1682" Z="0"/>
					<Vertex X="1415" Y="1686" Z="0"/>
					<Vertex X="1419" Y="1686" Z="0"/>
					<Vertex X="1424" Y="1686" Z="0"/>
					<Vertex X="1424" Y="1691" Z="0"/>
					<Vertex X="1428" Y="1691" Z="0"/>
					<Vertex X="1428" Y="1695" Z="0"/>
					<Vertex X="1433" Y="1695" Z="0"/>
					<Vertex X="1437" Y="1695" Z="0"/>
					<Vertex X="1437" Y="1700" Z="0"/>
					<Vertex X="1442" Y="1700" Z="0"/>
					<Vertex X="1442" Y="1704" Z="0"/>
					<Vertex X="1446" Y="1704" Z="0"/>
					<Vertex X="1451" Y="1704" Z="0"/>
					<Vertex X="1455" Y="1709" Z="0"/>
					<Vertex X="1460" Y="1713" Z="0"/>
					<Vertex X="1464" Y="1713" Z="0"/>
					<Vertex X="1469" Y="1718" Z="0"/>
					<Vertex X="1473" Y="1718" Z="0"/>
					<Vertex X="1473" Y="1722" Z="0"/>
					<Vertex X="1478" Y="1722" Z="0"/>
					<Vertex X="1482" Y="1722" Z="0"/>
					<Vertex X="1482" Y="1727" Z="0"/>
					<Vertex X="1487" Y="1727" Z="0"/>
					<Vertex X="1492" Y="1727" Z="0"/>
					<Vertex X="1492" Y="1731" Z="0"/>
					<Vertex X="1496" Y="1731" Z="0"/>
					<Vertex X="1501" Y="1731" Z="0"/>
					<Vertex X="1505" Y="1736" Z="0"/>
					<Vertex X="1510" Y="1736" Z="0"/>
					<Vertex X="1510" Y="1740" Z="0"/>
					<Vertex X="1514" Y="1740" Z="0"/>
					<Vertex X="1519" Y="1740" Z="0"/>
					<Vertex X="1523" Y="1740" Z="0"/>
					<Vertex X="1528" Y="1740" Z="0"/>
					<Vertex X="1528" Y="1745" Z="0"/>
					<Vertex X="1532" Y="1745" Z="0"/>
					<Vertex X="1537" Y="1745" Z="0"/>
					<Vertex X="1541" Y="1745" Z="0"/>
					<Vertex X="1541" Y="1749" Z="0"/>
					<Vertex X="1546" Y="1749" Z="0"/>
					<Vertex X="1550" Y="1749" Z="0"/>
					<Vertex X="1555" Y="1749" Z="0"/>
					<Vertex X="1559" Y="1749" Z="0"/>
					<Vertex X="1559" Y="1754" Z="0"/>
					<Vertex X="1564" Y="1754" Z="0"/>
					<Vertex X="1568" Y="1754" Z="0"/>
					<Vertex X="1573" Y="1754" Z="0"/>
					<Vertex X="1573" Y="1759" Z="0"/>
					<Vertex X="1577" Y="1759" Z="0"/>
					<Vertex X="1582" Y="1759" Z="0"/>
					<Vertex X="1586" Y="1759" Z="0"/>
					<Vertex X="1591" Y="1759" Z="0"/>
					<Vertex X="1591" Y="1763" Z="0"/>
					<Vertex X="1595" Y="1763" Z="0"/>
					<Vertex X="1600" Y="1763" Z="0"/>
					<Vertex X="1605" Y="1763" Z="0"/>
					<Vertex X="1605" Y="1768" Z="0"/>
					<Vertex X="1609" Y="1768" Z="0"/>
					<Vertex X="1614" Y="1768" Z="0"/>
					<Vertex X="1618" Y="1768" Z="0"/>
					<Vertex X="1623" Y="1768" Z="0"/>
					<Vertex X="1623" Y="1772" Z="0"/>
					<Vertex X="1627" Y="1772" Z="0"/>
					<Vertex X="1632" Y="1772" Z="0"/>
					<Vertex X="1636" Y="1772" Z="0"/>
					<Vertex X="1636" Y="1777" Z="0"/>
					<Vertex X="1641" Y="1777" Z="0"/>
					<Vertex X="1645" Y="1777" Z="0"/>
					<Vertex X="1650" Y="1777" Z="0"/>
					<Vertex X="1654" Y="1777" Z="0"/>
					<Vertex X="1659" Y="1777" Z="0"/>
					<Vertex X="1659" Y="1781" Z="0"/>
					<Vertex X="1663" Y="1781" Z="0"/>
					<Vertex X="1668" Y="1781" Z="0"/>
					<Vertex X="1672" Y="1781" Z="0"/>
					<Vertex X="1677" Y="1781" Z="0"/>
					<Vertex X="1681" Y="1781" Z="0"/>
					<Vertex X="1686" Y="1781" Z="0"/>
					<Vertex X="1686" Y="1786" Z="0"/>
					<Vertex X="1690" Y="1786" Z="0"/>
					<Vertex X="1695" Y="1786" Z="0"/>
					<Vertex X="1699" Y="1786" Z="0"/>
					<Vertex X="1704" Y="1786" Z="0"/>
					<Vertex X="1709" Y="1786" Z="0"/>
					<Vertex X="1713" Y="1786" Z="0"/>
					<Vertex X="1718" Y="1786" Z="0"/>
					<Vertex X="1722" Y="1786" Z="0"/>
					<Vertex X="1722" Y="1790" Z="0"/>
					<Vertex X="1727" Y="1790" Z="0"/>
					<Vertex X="1731" Y="1790" Z="0"/>
					<Vertex X="1736" Y="1790" Z="0"/>
					<Vertex X="1740" Y="1790" Z="0"/>
					<Vertex X="1745" Y="1790" Z="0"/>
					<Vertex X="1749" Y="1790" Z="0"/>
					<Vertex X="1754" Y="1790" Z="0"/>
					<Vertex X="1758" Y="1790" Z="0"/>
					<Vertex X="1758" Y="1795" Z="0"/>
					<Vertex X="1763" Y="1795" Z="0"/>
					<Vertex X="1767" Y="1795" Z="0"/>
					<Vertex X="1772" Y="1795" Z="0"/>
					<Vertex X="1776" Y="1795" Z="0"/>
					<Vertex X="1781" Y="1795" Z="0"/>
					<Vertex X="1785" Y="1795" Z="0"/>
					<Vertex X="1790" Y="1795" Z="0"/>
					<Vertex X="1794" Y="1795" Z="0"/>
					<Vertex X="1799" Y="1795" Z="0"/>
					<Vertex X="1803" Y="1795" Z="0"/>
					<Vertex X="1808" Y="1795" Z="0"/>
					<Vertex X="1812" Y="1795" Z="0"/>
					<Vertex X="1817" Y="1795" Z="0"/>
					<Vertex X="1822" Y="1795" Z="0"/>
					<Vertex X="1826" Y="1795" Z="0"/>
					<Vertex X="1831" Y="1795" Z="0"/>
					<Vertex X="1835" Y="1795" Z="0"/>
					<Vertex X="1840" Y="1795" Z="0"/>
					<Vertex X="1844" Y="1795" Z="0"/>
					<Vertex X="1849" Y="1795" Z="0"/>
					<Vertex X="1853" Y="1795" Z="0"/>
					<Vertex X="1858" Y="1795" Z="0"/>
					<Vertex X="1862" Y="1795" Z="0"/>
					<Vertex X="1867" Y="1795" Z="0"/>
					<Vertex X="1871" Y="1795" Z="0"/>
					<Vertex X="1876" Y="1795" Z="0"/>
					<Vertex X="1880" Y="1795" Z="0"/>
					<Vertex X="1885" Y="1795" Z="0"/>
					<Vertex X="1889" Y="1795" Z="0"/>
					<Vertex X="1894" Y="1795" Z="0"/>
					<Vertex X="1898" Y="1795" Z="0"/>
					<Vertex X="1903" Y="1795" Z="0"/>
					<Vertex X="1907" Y="1795" Z="0"/>
					<Vertex X="1912" Y="1795" Z="0"/>
					<Vertex X="1916" Y="1795" Z="0"/>
					<Vertex X="1921" Y="1795" Z="0"/>
					<Vertex X="1925" Y="1795" Z="0"/>
					<Vertex X="1930" Y="1795" Z="0"/>
					<Vertex X="1935" Y="1795" Z="0"/>
					<Vertex X="1939" Y="1795" Z="0"/>
					<Vertex X="1944" Y="1795" Z="0"/>
					<Vertex X="1948" Y="1795" Z="0"/>
					<Vertex X="1953" Y="1795" Z="0"/>
					<Vertex X="1957" Y="1795" Z="0"/>
					<Vertex X="1962" Y="1795" Z="0"/>
					<Vertex X="1966" Y="1795" Z="0"/>
					<Vertex X="1971" Y="1795" Z="0"/>
					<Vertex X="1975" Y="1795" Z="0"/>
					<Vertex X="1975" Y="1790" Z="0"/>
					<Vertex X="1980" Y="1790" Z="0"/>
					<Vertex X="1984" Y="1790" Z="0"/>
					<Vertex X="1989" Y="1790" Z="0"/>
					<Vertex X="1993" Y="1790" Z="0"/>
					<Vertex X="1998" Y="1790" Z="0"/>
					<Vertex X="2002" Y="1790" Z="0"/>
					<Vertex X="2007" Y="1790" Z="0"/>
					<Vertex X="2011" Y="1790" Z="0"/>
					<Vertex X="2011" Y="1786" Z="0"/>
					<Vertex X="2016" Y="1786" Z="0"/>
					<Vertex X="2020" Y="1786" Z="0"/>
					<Vertex X="2025" Y="1786" Z="0"/>
					<Vertex X="2029" Y="1786" Z="0"/>
					<Vertex X="2034" Y="1786" Z="0"/>
					<Vertex X="2039" Y="1786" Z="0"/>
					<Vertex X="2039" Y="1781" Z="0"/>
					<Vertex X="2043" Y="1781" Z="0"/>
					<Vertex X="2048" Y="1781" Z="0"/>
					<Vertex X="2052" Y="1781" Z="0"/>
					<Vertex X="2057" Y="1781" Z="0"/>
					<Vertex X="2061" Y="1781" Z="0"/>
					<Vertex X="2066" Y="1781" Z="0"/>
					<Vertex X="2066" Y="1777" Z="0"/>
					<Vertex X="2070" Y="1777" Z="0"/>
					<Vertex X="2075" Y="1777" Z="0"/>
					<Vertex X="2079" Y="1777" Z="0"/>
					<Vertex X="2084" Y="1777" Z="0"/>
					<Vertex X="2088" Y="1777" Z="0"/>
					<Vertex X="2093" Y="1777" Z="0"/>
					<Vertex X="2097" Y="1777" Z="0"/>
					<Vertex X="2102" Y="1777" Z="0"/>
					<Vertex X="2102" Y="1772" Z="0"/>
					<Vertex X="2106" Y="1772" Z="0"/>
					<Vertex X="2111" Y="1772" Z="0"/>
					<Vertex X="2115" Y="1772" Z="0"/>
					<Vertex X="2120" Y="1772" Z="0"/>
					<Vertex X="2124" Y="1772" Z="0"/>
					<Vertex X="2129" Y="1772" Z="0"/>
					<Vertex X="2133" Y="1772" Z="0"/>
					<Vertex X="2138" Y="1772" Z="0"/>
					<Vertex X="2142" Y="1772" Z="0"/>
					<Vertex X="2147" Y="1772" Z="0"/>
					<Vertex X="2152" Y="1772" Z="0"/>
					<Vertex X="2156" Y="1772" Z="0"/>
					<Vertex X="2161" Y="1772" Z="0"/>
					<Vertex X="2165" Y="1772" Z="0"/>
					<Vertex X="2170" Y="1772" Z="0"/>
					<Vertex X="2174" Y="1772" Z="0"/>
					<Vertex X="2179" Y="1772" Z="0"/>
					<Vertex X="2183" Y="1772" Z="0"/>
					<Vertex X="2188" Y="1772" Z="0"/>
					<Vertex X="2192" Y="1772" Z="0"/>
					<Vertex X="2197" Y="1772" Z="0"/>
					<Vertex X="2201" Y="1772" Z="0"/>
					<Vertex X="2206" Y="1772" Z="0"/>
					<Vertex X="2210" Y="1772" Z="0"/>
					<Vertex X="2215" Y="1772" Z="0"/>
					<Vertex X="2219" Y="1772" Z="0"/>
					<Vertex X="2224" Y="1772" Z="0"/>
					<Vertex X="2228" Y="1772" Z="0"/>
					<Vertex X="2233" Y="1772" Z="0"/>
					<Vertex X="2237" Y="1772" Z="0"/>
					<Vertex X="2242" Y="1772" Z="0"/>
					<Vertex X="2246" Y="1772" Z="0"/>
					<Vertex X="2251" Y="1772" Z="0"/>
					<Vertex X="2256" Y="1772" Z="0"/>
					<Vertex X="2260" Y="1772" Z="0"/>
					<Vertex X="2265" Y="1772" Z="0"/>
					<Vertex X="2269" Y="1772" Z="0"/>
					<Vertex X="2274" Y="1772" Z="0"/>
					<Vertex X="2274" Y="1777" Z="0"/>
					<Vertex X="2278" Y="1777" Z="0"/>
					<Vertex X="2283" Y="1777" Z="0"/>
					<Vertex X="2287" Y="1777" Z="0"/>
					<Vertex X="2292" Y="1777" Z="0"/>
					<Vertex X="2296" Y="1777" Z="0"/>
					<Vertex X="2301" Y="1777" Z="0"/>
					<Vertex X="2305" Y="1777" Z="0"/>
					<Vertex X="2310" Y="1777" Z="0"/>
					<Vertex X="2310" Y="1781" Z="0"/>
					<Vertex X="2314" Y="1781" Z="0"/>
					<Vertex X="2319" Y="1781" Z="0"/>
					<Vertex X="2323" Y="1781" Z="0"/>
					<Vertex X="2328" Y="1781" Z="0"/>
					<Vertex X="2332" Y="1781" Z="0"/>
					<Vertex X="2337" Y="1781" Z="0"/>
					<Vertex X="2341" Y="1781" Z="0"/>
					<Vertex X="2346" Y="1781" Z="0"/>
					<Vertex X="2350" Y="1781" Z="0"/>
					<Vertex X="2350" Y="1786" Z="0"/>
					<Vertex X="2355" Y="1786" Z="0"/>
					<Vertex X="2359" Y="1786" Z="0"/>
					<Vertex X="2364" Y="1786" Z="0"/>
					<Vertex X="2369" Y="1786" Z="0"/>
					<Vertex X="2373" Y="1786" Z="0"/>
					<Vertex X="2378" Y="1786" Z="0"/>
					<Vertex X="2382" Y="1786" Z="0"/>
					<Vertex X="2387" Y="1786" Z="0"/>
					<Vertex X="2391" Y="1786" Z="0"/>
					<Vertex X="2396" Y="1786" Z="0"/>
					<Vertex X="2400" Y="1786" Z="0"/>
					<Vertex X="2405" Y="1786" Z="0"/>
					<Vertex X="2409" Y="1786" Z="0"/>
					<Vertex X="2414" Y="1786" Z="0"/>
					<Vertex X="2418" Y="1786" Z="0"/>
					<Vertex X="2423" Y="1786" Z="0"/>
					<Vertex X="2427" Y="1786" Z="0"/>
					<Vertex X="2432" Y="1786" Z="0"/>
					<Vertex X="2436" Y="1786" Z="0"/>
					<Vertex X="2441" Y="1786" Z="0"/>
					<Vertex X="2445" Y="1786" Z="0"/>
					<Vertex X="2450" Y="1786" Z="0"/>
					<Vertex X="2454" Y="1786" Z="0"/>
					<Vertex X="2459" Y="1786" Z="0"/>
					<Vertex X="2463" Y="1786" Z="0"/>
					<Vertex X="2468" Y="1786" Z="0"/>
					<Vertex X="2472" Y="1786" Z="0"/>
					<Vertex X="2477" Y="1786" Z="0"/>
					<Vertex X="2482" Y="1786" Z="0"/>
					<Vertex X="2486" Y="1786" Z="0"/>
					<Vertex X="2491" Y="1786" Z="0"/>
					<Vertex X="2495" Y="1786" Z="0"/>
					<Vertex X="2500" Y="1786" Z="0"/>
					<Vertex X="2504" Y="1786" Z="0"/>
					<Vertex X="2509" Y="1786" Z="0"/>
					<Vertex X="2513" Y="1786" Z="0"/>
					<Vertex X="2518" Y="1786" Z="0"/>
					<Vertex X="2522" Y="1786" Z="0"/>
					<Vertex X="2527" Y="1786" Z="0"/>
					<Vertex X="2531" Y="1786" Z="0"/>
					<Vertex X="2536" Y="1786" Z="0"/>
					<Vertex X="2540" Y="1786" Z="0"/>
					<Vertex X="2545" Y="1786" Z="0"/>
					<Vertex X="2549" Y="1786" Z="0"/>
					<Vertex X="2554" Y="1786" Z="0"/>
					<Vertex X="2558" Y="1786" Z="0"/>
					<Vertex X="2563" Y="1786" Z="0"/>
					<Vertex X="2567" Y="1786" Z="0"/>
					<Vertex X="2572" Y="1786" Z="0"/>
					<Vertex X="2576" Y="1786" Z="0"/>
					<Vertex X="2581" Y="1786" Z="0"/>
					<Vertex X="2586" Y="1786" Z="0"/>
					<Vertex X="2590" Y="1786" Z="0"/>
					<Vertex X="2595" Y="1786" Z="0"/>
					<Vertex X="2599" Y="1786" Z="0"/>
					<Vertex X="2604" Y="1786" Z="0"/>
					<Vertex X="2608" Y="1786" Z="0"/>
					<Vertex X="2608" Y="1781" Z="0"/>
					<Vertex X="2613" Y="1781" Z="0"/>
					<Vertex X="2617" Y="1781" Z="0"/>
					<Vertex X="2622" Y="1781" Z="0"/>
					<Vertex X="2626" Y="1781" Z="0"/>
					<Vertex X="2631" Y="1781" Z="0"/>
					<Vertex X="2635" Y="1781" Z="0"/>
					<Vertex X="2640" Y="1781" Z="0"/>
					<Vertex X="2640" Y="1777" Z="0"/>
					<Vertex X="2644" Y="1777" Z="0"/>
					<Vertex X="2649" Y="1777" Z="0"/>
					<Vertex X="2653" Y="1777" Z="0"/>
					<Vertex X="2653" Y="1772" Z="0"/>
					<Vertex X="2658" Y="1772" Z="0"/>
					<Vertex X="2662" Y="1772" Z="0"/>
					<Vertex X="2667" Y="1772" Z="0"/>
					<Vertex X="2671" Y="1772" Z="0"/>
					<Vertex X="2676" Y="1772" Z="0"/>
					<Vertex X="2676" Y="1768" Z="0"/>
					<Vertex X="2680" Y="1768" Z="0"/>
					<Vertex X="2685" Y="1768" Z="0"/>
					<Vertex X="2689" Y="1768" Z="0"/>
					<Vertex X="2694" Y="1768" Z="0"/>
					<Vertex X="2694" Y="1763" Z="0"/>
					<Vertex X="2699" Y="1763" Z="0"/>
					<Vertex X="2703" Y="1763" Z="0"/>
					<Vertex X="2708" Y="1763" Z="0"/>
					<Vertex X="2712" Y="1763" Z="0"/>
					<Vertex X="2712" Y="1759" Z="0"/>
					<Vertex X="2717" Y="1759" Z="0"/>
					<Vertex X="2721" Y="1759" Z="0"/>
					<Vertex X="2726" Y="1759" Z="0"/>
					<Vertex X="2730" Y="1759" Z="0"/>
					<Vertex X="2730" Y="1754" Z="0"/>
					<Vertex X="2735" Y="1754" Z="0"/>
					<Vertex X="2739" Y="1754" Z="0"/>
					<Vertex X="2744" Y="1754" Z="0"/>
					<Vertex X="2744" Y="1749" Z="0"/>
					<Vertex X="2748" Y="1749" Z="0"/>
					<Vertex X="2753" Y="1749" Z="0"/>
					<Vertex X="2757" Y="1749" Z="0"/>
					<Vertex X="2757" Y="1745" Z="0"/>
					<Vertex X="2762" Y="1745" Z="0"/>
					<Vertex X="2766" Y="1745" Z="0"/>
					<Vertex X="2766" Y="1740" Z="0"/>
					<Vertex X="2771" Y="1740" Z="0"/>
					<Vertex X="2775" Y="1740" Z="0"/>
					<Vertex X="2775" Y="1736" Z="0"/>
					<Vertex X="2780" Y="1736" Z="0"/>
					<Vertex X="2784" Y="1736" Z="0"/>
					<Vertex X="2789" Y="1736" Z="0"/>
					<Vertex X="2789" Y="1731" Z="0"/>
					<Vertex X="2793" Y="1731" Z="0"/>
					<Vertex X="2793" Y="1727" Z="0"/>
					<Vertex X="2798" Y="1727" Z="0"/>
					<Vertex X="2803" Y="1727" Z="0"/>
					<Vertex X="2803" Y="1722" Z="0"/>
					<Vertex X="2807" Y="1722" Z="0"/>
					<Vertex X="2807" Y="1718" Z="0"/>
					<Vertex X="2812" Y="1718" Z="0"/>
					<Vertex X="2816" Y="1718" Z="0"/>
					<Vertex X="2821" Y="1713" Z="0"/>
					<Vertex X="2825" Y="1713" Z="0"/>
					<Vertex X="2825" Y="1709" Z="0"/>
					<Vertex X="2830" Y="1709" Z="0"/>
					<Vertex X="2834" Y="1709" Z="0"/>
					<Vertex X="2834" Y="1704" Z="0"/>
					<Vertex X="2839" Y="1704" Z="0"/>
					<Vertex X="2843" Y="1704" Z="0"/>
					<Vertex X="2843" Y="1700" Z="0"/>
					<Vertex X="2848" Y="1700" Z="0"/>
					<Vertex X="2852" Y="1700" Z="0"/>
					<Vertex X="2852" Y="1695" Z="0"/>
					<Vertex X="2857" Y="1695" Z="0"/>
					<Vertex X="2861" Y="1695" Z="0"/>
					<Vertex X="2861" Y="1691" Z="0"/>
					<Vertex X="2866" Y="1691" Z="0"/>
					<Vertex X="2870" Y="1691" Z="0"/>
					<Vertex X="2870" Y="1686" Z="0"/>
					<Vertex X="2875" Y="1686" Z="0"/>
					<Vertex X="2879" Y="1686" Z="0"/>
					<Vertex X="2879" Y="1682" Z="0"/>
					<Vertex X="2884" Y="1682" Z="0"/>
					<Vertex X="2888" Y="1682" Z="0"/>
					<Vertex X="2888" Y="1677" Z="0"/>
					<Vertex X="2893" Y="1677" Z="0"/>
					<Vertex X="2897" Y="1677" Z="0"/>
					<Vertex X="2897" Y="1673" Z="0"/>
					<Vertex X="2902" Y="1673" Z="0"/>
					<Vertex X="2906" Y="1673" Z="0"/>
					<Vertex X="2911" Y="1668" Z="0"/>
					<Vertex X="2916" Y="1668" Z="0"/>
					<Vertex X="2916" Y="1664" Z="0"/>
					<Vertex X="2920" Y="1664" Z="0"/>
					<Vertex X="2925" Y="1664" Z="0"/>
					<Vertex X="2929" Y="1664" Z="0"/>
					<Vertex X="2929" Y="1659" Z="0"/>
					<Vertex X="2934" Y="1659" Z="0"/>
					<Vertex X="2938" Y="1659" Z="0"/>
					<Vertex X="2938" Y="1655" Z="0"/>
					<Vertex X="2943" Y="1655" Z="0"/>
					<Vertex X="2947" Y="1655" Z="0"/>
					<Vertex X="2947" Y="1650" Z="0"/>
					<Vertex X="2952" Y="1650" Z="0"/>
					<Vertex X="2956" Y="1650" Z="0"/>
					<Vertex X="2956" Y="1646" Z="0"/>
					<Vertex X="2961" Y="1646" Z="0"/>
					<Vertex X="2965" Y="1646" Z="0"/>
					<Vertex X="2965" Y="1641" Z="0"/>
					<Vertex X="2970" Y="1641" Z="0"/>
					<Vertex X="2970" Y="1636" Z="0"/>
					<Vertex X="2974" Y="1636" Z="0"/>
					<Vertex X="2979" Y="1636" Z="0"/>
					<Vertex X="2983" Y="1636" Z="0"/>
					<Vertex X="2983" Y="1632" Z="0"/>
					<Vertex X="2988" Y="1632" Z="0"/>
					<Vertex X="2988" Y="1627" Z="0"/>
					<Vertex X="2992" Y="1627" Z="0"/>
					<Vertex X="2997" Y="1627" Z="0"/>
					<Vertex X="2997" Y="1623" Z="0"/>
					<Vertex X="3001" Y="1623" Z="0"/>
					<Vertex X="3001" Y="1618" Z="0"/>
					<Vertex X="3006" Y="1618" Z="0"/>
					<Vertex X="3010" Y="1618" Z="0"/>
					<Vertex X="3010" Y="1614" Z="0"/>
					<Vertex X="3015" Y="1614" Z="0"/>
					<Vertex X="3019" Y="1614" Z="0"/>
					<Vertex X="3019" Y="1609" Z="0"/>
					<Vertex X="3024" Y="1609" Z="0"/>
					<Vertex X="3024" Y="1605" Z="0"/>
					<Vertex X="3029" Y="1605" Z="0"/>
					<Vertex X="3029" Y="1600" Z="0"/>
					<Vertex X="3033" Y="1600" Z="0"/>
					<Vertex X="3038" Y="1600" Z="0"/>
					<Vertex X="3038" Y="1596" Z="0"/>
					<Vertex X="3042" Y="1596" Z="0"/>
					<Vertex X="3042" Y="1591" Z="0"/>
					<Vertex X="3047" Y="1591" Z="0"/>
					<Vertex X="3047" Y="1587" Z="0"/>
					<Vertex X="3051" Y="1587" Z="0"/>
					<Vertex X="3056" Y="1587" Z="0"/>
					<Vertex X="3056" Y="1582" Z="0"/>
					<Vertex X="3060" Y="1582" Z="0"/>
					<Vertex X="3060" Y="1578" Z="0"/>
					<Vertex X="3065" Y="1578" Z="0"/>
					<Vertex X="3065" Y="1573" Z="0"/>
					<Vertex X="3069" Y="1573" Z="0"/>
					<Vertex X="3069" Y="1569" Z="0"/>
					<Vertex X="3074" Y="1569" Z="0"/>
					<Vertex X="3074" Y="1564" Z="0"/>
					<Vertex X="3078" Y="1564" Z="0"/>
					<Vertex X="3078" Y="1560" Z="0"/>
					<Vertex X="3083" Y="1560" Z="0"/>
					<Vertex X="3083" Y="1555" Z="0"/>
					<Vertex X="3087" Y="1555" Z="0"/>
					<Vertex X="3087" Y="1551" Z="0"/>
					<Vertex X="3092" Y="1551" Z="0"/>
					<Vertex X="3092" Y="1546" Z="0"/>
					<Vertex X="3096" Y="1546" Z="0"/>
					<Vertex X="3096" Y="1542" Z="0"/>
					<Vertex X="3101" Y="1542" Z="0"/>
					<Vertex X="3101" Y="1537" Z="0"/>
					<Vertex X="3105" Y="1537" Z="0"/>
					<Vertex X="3105" Y="1532" Z="0"/>
					<Vertex X="3110" Y="1532" Z="0"/>
					<Vertex X="3110" Y="1528" Z="0"/>
					<Vertex X="3110" Y="1523" Z="0"/>
					<Vertex X="3114" Y="1523" Z="0"/>
					<Vertex X="3119" Y="1519" Z="0"/>
					<Vertex X="3119" Y="1514" Z="0"/>
					<Vertex X="3123" Y="1514" Z="0"/>
					<Vertex X="3123" Y="1510" Z="0"/>
					<Vertex X="3128" Y="1510" Z="0"/>
					<Vertex X="3128" Y="1505" Z="0"/>
					<Vertex X="3133" Y="1505" Z="0"/>
					<Vertex X="3133" Y="1501" Z="0"/>
					<Vertex X="3137" Y="1501" Z="0"/>
					<Vertex X="3137" Y="1496" Z="0"/>
					<Vertex X="3137" Y="1492" Z="0"/>
					<Vertex X="3142" Y="1492" Z="0"/>
					<Vertex X="3142" Y="1487" Z="0"/>
					<Vertex X="3146" Y="1487" Z="0"/>
					<Vertex X="3146" Y="1483" Z="0"/>
					<Vertex X="3151" Y="1483" Z="0"/>
					<Vertex X="3151" Y="1478" Z="0"/>
					<Vertex X="3155" Y="1478" Z="0"/>
					<Vertex X="3155" Y="1474" Z="0"/>
					<Vertex X="3155" Y="1469" Z="0"/>
					<Vertex X="3160" Y="1469" Z="0"/>
					<Vertex X="3164" Y="1469" Z="0"/>
					<Vertex X="3164" Y="1465" Z="0"/>
					<Vertex X="3169" Y="1465" Z="0"/>
					<Vertex X="3169" Y="1460" Z="0"/>
					<Vertex X="3173" Y="1460" Z="0"/>
					<Vertex X="3173" Y="1456" Z="0"/>
					<Vertex X="3173" Y="1451" Z="0"/>
					<Vertex X="3178" Y="1447" Z="0"/>
					<Vertex X="3178" Y="1442" Z="0"/>
					<Vertex X="3182" Y="1442" Z="0"/>
					<Vertex X="3182" Y="1438" Z="0"/>
					<Vertex X="3187" Y="1438" Z="0"/>
					<Vertex X="3187" Y="1433" Z="0"/>
					<Vertex X="3187" Y="1429" Z="0"/>
					<Vertex X="3191" Y="1429" Z="0"/>
					<Vertex X="3191" Y="1424" Z="0"/>
					<Vertex X="3191" Y="1419" Z="0"/>
					<Vertex X="3196" Y="1419" Z="0"/>
					<Vertex X="3196" Y="1415" Z="0"/>
					<Vertex X="3200" Y="1415" Z="0"/>
					<Vertex X="3200" Y="1410" Z="0"/>
					<Vertex X="3200" Y="1406" Z="0"/>
					<Vertex X="3205" Y="1406" Z="0"/>
					<Vertex X="3205" Y="1401" Z="0"/>
					<Vertex X="3205" Y="1397" Z="0"/>
					<Vertex X="3209" Y="1397" Z="0"/>
					<Vertex X="3209" Y="1392" Z="0"/>
					<Vertex X="3214" Y="1392" Z="0"/>
					<Vertex X="3214" Y="1388" Z="0"/>
					<Vertex X="3214" Y="1383" Z="0"/>
					<Vertex X="3218" Y="1383" Z="0"/>
					<Vertex X="3218" Y="1379" Z="0"/>
					<Vertex X="3223" Y="1379" Z="0"/>
					<Vertex X="3223" Y="1374" Z="0"/>
					<Vertex X="3223" Y="1370" Z="0"/>
					<Vertex X="3227" Y="1370" Z="0"/>
					<Vertex X="3227" Y="1365" Z="0"/>
					<Vertex X="3232" Y="1365" Z="0"/>
					<Vertex X="3232" Y="1361" Z="0"/>
					<Vertex X="3232" Y="1356" Z="0"/>
					<Vertex X="3236" Y="1356" Z="0"/>
					<Vertex X="3236" Y="1352" Z="0"/>
					<Vertex X="3241" Y="1352" Z="0"/>
					<Vertex X="3241" Y="1347" Z="0"/>
					<Vertex X="3246" Y="1347" Z="0"/>
					<Vertex X="3246" Y="1343" Z="0"/>
					<Vertex X="3246" Y="1338" Z="0"/>
					<Vertex X="3250" Y="1338" Z="0"/>
					<Vertex X="3250" Y="1334" Z="0"/>
					<Vertex X="3255" Y="1334" Z="0"/>
					<Vertex X="3255" Y="1329" Z="0"/>
					<Vertex X="3255" Y="1325" Z="0"/>
					<Vertex X="3259" Y="1325" Z="0"/>
					<Vertex X="3259" Y="1320" Z="0"/>
					<Vertex X="3264" Y="1320" Z="0"/>
					<Vertex X="3264" Y="1316" Z="0"/>
					<Vertex X="3264" Y="1311" Z="0"/>
					<Vertex X="3268" Y="1311" Z="0"/>
					<Vertex X="3268" Y="1306" Z="0"/>
					<Vertex X="3273" Y="1302" Z="0"/>
					<Vertex X="3277" Y="1302" Z="0"/>
					<Vertex X="3277" Y="1297" Z="0"/>
					<Vertex X="3277" Y="1293" Z="0"/>
					<Vertex X="3282" Y="1293" Z="0"/>
					<Vertex X="3282" Y="1288" Z="0"/>
					<Vertex X="3282" Y="1284" Z="0"/>
					<Vertex X="3286" Y="1284" Z="0"/>
					<Vertex X="3286" Y="1279" Z="0"/>
					<Vertex X="3291" Y="1279" Z="0"/>
					<Vertex X="3291" Y="1275" Z="0"/>
					<Vertex X="3295" Y="1275" Z="0"/>
					<Vertex X="3295" Y="1270" Z="0"/>
					<Vertex X="3295" Y="1266" Z="0"/>
					<Vertex X="3300" Y="1266" Z="0"/>
					<Vertex X="3300" Y="1261" Z="0"/>
					<Vertex X="3304" Y="1257" Z="0"/>
					<Vertex X="3304" Y="1252" Z="0"/>
					<Vertex X="3304" Y="1248" Z="0"/>
					<Vertex X="3309" Y="1248" Z="0"/>
					<Vertex X="3313" Y="1243" Z="0"/>
					<Vertex X="3313" Y="1239" Z="0"/>
					<Vertex X="3313" Y="1234" Z="0"/>
					<Vertex X="3318" Y="1234" Z="0"/>
					<Vertex X="3318" Y="1230" Z="0"/>
					<Vertex X="3322" Y="1230" Z="0"/>
					<Vertex X="3322" Y="1225" Z="0"/>
					<Vertex X="3322" Y="1221" Z="0"/>
					<Vertex X="3327" Y="1221" Z="0"/>
					<Vertex X="3327" Y="1216" Z="0"/>
					<Vertex X="3327" Y="1212" Z="0"/>
					<Vertex X="3331" Y="1212" Z="0"/>
					<Vertex X="3331" Y="1207" Z="0"/>
					<Vertex X="3331" Y="1202" Z="0"/>
					<Vertex X="3336" Y="1202" Z="0"/>
					<Vertex X="3336" Y="1198" Z="0"/>
					<Vertex X="3340" Y="1198" Z="0"/>
					<Vertex X="3340" Y="1193" Z="0"/>
					<Vertex X="3340" Y="1189" Z="0"/>
					<Vertex X="3340" Y="1184" Z="0"/>
					<Vertex X="3345" Y="1184" Z="0"/>
					<Vertex X="3345" Y="1180" Z="0"/>
					<Vertex X="3349" Y="1180" Z="0"/>
					<Vertex X="3349" Y="1175" Z="0"/>
					<Vertex X="3349" Y="1171" Z="0"/>
					<Vertex X="3349" Y="1166" Z="0"/>
					<Vertex X="3354" Y="1166" Z="0"/>
					<Vertex X="3354" Y="1162" Z="0"/>
					<Vertex X="3359" Y="1162" Z="0"/>
					<Vertex X="3359" Y="1157" Z="0"/>
					<Vertex X="3359" Y="1153" Z="0"/>
					<Vertex X="3359" Y="1148" Z="0"/>
					<Vertex X="3363" Y="1148" Z="0"/>
					<Vertex X="3363" Y="1144" Z="0"/>
					<Vertex X="3368" Y="1144" Z="0"/>
					<Vertex X="3368" Y="1139" Z="0"/>
					<Vertex X="3368" Y="1135" Z="0"/>
					<Vertex X="3372" Y="1135" Z="0"/>
					<Vertex X="3372" Y="1130" Z="0"/>
					<Vertex X="3372" Y="1126" Z="0"/>
					<Vertex X="3377" Y="1126" Z="0"/>
					<Vertex X="3377" Y="1121" Z="0"/>
					<Vertex X="3377" Y="1117" Z="0"/>
					<Vertex X="3381" Y="1117" Z="0"/>
					<Vertex X="3381" Y="1112" Z="0"/>
					<Vertex X="3386" Y="1112" Z="0"/>
					<Vertex X="3386" Y="1108" Z="0"/>
					<Vertex X="3386" Y="1103" Z="0"/>
					<Vertex X="3390" Y="1103" Z="0"/>
					<Vertex X="3390" Y="1099" Z="0"/>
					<Vertex X="3395" Y="1099" Z="0"/>
					<Vertex X="3395" Y="1094" Z="0"/>
					<Vertex X="3395" Y="1089" Z="0"/>
					<Vertex X="3399" Y="1089" Z="0"/>
					<Vertex X="3399" Y="1085" Z="0"/>
					<Vertex X="3399" Y="1080" Z="0"/>
					<Vertex X="3404" Y="1080" Z="0"/>
					<Vertex X="3404" Y="1076" Z="0"/>
					<Vertex X="3404" Y="1071" Z="0"/>
					<Vertex X="3408" Y="1071" Z="0"/>
					<Vertex X="3408" Y="1067" Z="0"/>
					<Vertex X="3408" Y="1062" Z="0"/>
					<Vertex X="3413" Y="1062" Z="0"/>
					<Vertex X="3413" Y="1058" Z="0"/>
					<Vertex X="3413" Y="1053" Z="0"/>
					<Vertex X="3417" Y="1053" Z="0"/>
					<Vertex X="3417" Y="1049" Z="0"/>
					<Vertex X="3417" Y="1044" Z="0"/>
					<Vertex X="3422" Y="1044" Z="0"/>
					<Vertex X="3422" Y="1040" Z="0"/>
					<Vertex X="3426" Y="1040" Z="0"/>
					<Vertex X="3426" Y="1035" Z="0"/>
					<Vertex X="3426" Y="1031" Z="0"/>
					<Vertex X="3431" Y="1031" Z="0"/>
					<Vertex X="3431" Y="1026" Z="0"/>
					<Vertex X="3435" Y="1026" Z="0"/>
					<Vertex X="3435" Y="1022" Z="0"/>
					<Vertex X="3435" Y="1017" Z="0"/>
					<Vertex X="3440" Y="1017" Z="0"/>
					<Vertex X="3440" Y="1013" Z="0"/>
					<Vertex X="3440" Y="1008" Z="0"/>
					<Vertex X="3444" Y="1008" Z="0"/>
					<Vertex X="3444" Y="1004" Z="0"/>
					<Vertex X="3444" Y="999" Z="0"/>
					<Vertex X="3449" Y="995" Z="0"/>
					<Vertex X="3449" Y="990" Z="0"/>
					<Vertex X="3453" Y="990" Z="0"/>
					<Vertex X="3453" Y="985" Z="0"/>
					<Vertex X="3453" Y="981" Z="0"/>
					<Vertex X="3453" Y="976" Z="0"/>
					<Vertex X="3453" Y="972" Z="0"/>
					<Vertex X="3453" Y="967" Z="0"/>
					<Vertex X="3453" Y="963" Z="0"/>
					<Vertex X="3453" Y="958" Z="0"/>
					<Vertex X="3453" Y="954" Z="0"/>
					<Vertex X="3453" Y="949" Z="0"/>
					<Vertex X="3453" Y="945" Z="0"/>
					<Vertex X="3449" Y="945" Z="0"/>
					<Vertex X="3449" Y="940" Z="0"/>
					<Vertex X="3444" Y="940" Z="0"/>
					<Vertex X="3440" Y="940" Z="0"/>
					<Vertex X="3435" Y="940" Z="0"/>
					<Vertex X="3431" Y="940" Z="0"/>
					<Vertex X="3431" Y="936" Z="0"/>
					<Vertex X="3426" Y="936" Z="0"/>
					<Vertex X="3422" Y="936" Z="0"/>
					<Vertex X="3417" Y="936" Z="0"/>
					<Vertex X="3413" Y="936" Z="0"/>
					<Vertex X="3408" Y="936" Z="0"/>
					<Vertex X="3404" Y="936" Z="0"/>
					<Vertex X="3399" Y="936" Z="0"/>
					<Vertex X="3395" Y="936" Z="0"/>
					<Vertex X="3390" Y="936" Z="0"/>
					<Vertex X="3386" Y="936" Z="0"/>
					<Vertex X="3381" Y="936" Z="0"/>
					<Vertex X="3377" Y="936" Z="0"/>
					<Vertex X="3372" Y="936" Z="0"/>
					<Vertex X="3368" Y="936" Z="0"/>
					<Vertex X="3363" Y="936" Z="0"/>
					<Vertex X="3359" Y="936" Z="0"/>
					<Vertex X="3354" Y="936" Z="0"/>
					<Vertex X="3354" Y="940" Z="0"/>
					<Vertex X="3349" Y="940" Z="0"/>
					<Vertex X="3345" Y="940" Z="0"/>
					<Vertex X="3340" Y="940" Z="0"/>
					<Vertex X="3340" Y="945" Z="0"/>
					<Vertex X="3336" Y="945" Z="0"/>
					<Vertex X="3331" Y="945" Z="0"/>
					<Vertex X="3327" Y="945" Z="0"/>
					<Vertex X="3322" Y="945" Z="0"/>
					<Vertex X="3318" Y="945" Z="0"/>
					<Vertex X="3318" Y="949" Z="0"/>
					<Vertex X="3313" Y="949" Z="0"/>
					<Vertex X="3309" Y="949" Z="0"/>
					<Vertex X="3309" Y="954" Z="0"/>
					<Vertex X="3304" Y="954" Z="0"/>
					<Vertex X="3300" Y="954" Z="0"/>
					<Vertex X="3295" Y="954" Z="0"/>
					<Vertex X="3295" Y="958" Z="0"/>
					<Vertex X="3291" Y="958" Z="0"/>
					<Vertex X="3291" Y="963" Z="0"/>
					<Vertex X="3286" Y="963" Z="0"/>
					<Vertex X="3282" Y="963" Z="0"/>
					<Vertex X="3277" Y="963" Z="0"/>
					<Vertex X="3277" Y="967" Z="0"/>
					<Vertex X="3273" Y="967" Z="0"/>
					<Vertex X="3273" Y="972" Z="0"/>
					<Vertex X="3268" Y="972" Z="0"/>
					<Vertex X="3264" Y="972" Z="0"/>
					<Vertex X="3259" Y="972" Z="0"/>
					<Vertex X="3259" Y="976" Z="0"/>
					<Vertex X="3255" Y="976" Z="0"/>
					<Vertex X="3250" Y="976" Z="0"/>
					<Vertex X="3250" Y="981" Z="0"/>
					<Vertex X="3246" Y="981" Z="0"/>
					<Vertex X="3241" Y="981" Z="0"/>
					<Vertex X="3236" Y="981" Z="0"/>
					<Vertex X="3236" Y="985" Z="0"/>
					<Vertex X="3232" Y="985" Z="0"/>
					<Vertex X="3227" Y="985" Z="0"/>
					<Vertex X="3227" Y="990" Z="0"/>
					<Vertex X="3223" Y="990" Z="0"/>
					<Vertex X="3218" Y="990" Z="0"/>
					<Vertex X="3214" Y="990" Z="0"/>
					<Vertex X="3209" Y="990" Z="0"/>
					<Vertex X="3209" Y="995" Z="0"/>
					<Vertex X="3205" Y="995" Z="0"/>
					<Vertex X="3200" Y="995" Z="0"/>
					<Vertex X="3196" Y="995" Z="0"/>
					<Vertex X="3191" Y="995" Z="0"/>
					<Vertex X="3191" Y="999" Z="0"/>
					<Vertex X="3187" Y="999" Z="0"/>
					<Vertex X="3182" Y="999" Z="0"/>
					<Vertex X="3182" Y="1004" Z="0"/>
					<Vertex X="3178" Y="1004" Z="0"/>
					<Vertex X="3173" Y="1004" Z="0"/>
					<Vertex X="3169" Y="1004" Z="0"/>
					<Vertex X="3164" Y="1004" Z="0"/>
					<Vertex X="3164" Y="1008" Z="0"/>
					<Vertex X="3160" Y="1008" Z="0"/>
					<Vertex X="3155" Y="1008" Z="0"/>
					<Vertex X="3151" Y="1008" Z="0"/>
					<Vertex X="3151" Y="1013" Z="0"/>
					<Vertex X="3146" Y="1013" Z="0"/>
					<Vertex X="3142" Y="1013" Z="0"/>
					<Vertex X="3137" Y="1013" Z="0"/>
					<Vertex X="3137" Y="1017" Z="0"/>
					<Vertex X="3133" Y="1017" Z="0"/>
					<Vertex X="3128" Y="1017" Z="0"/>
					<Vertex X="3123" Y="1017" Z="0"/>
					<Vertex X="3123" Y="1022" Z="0"/>
					<Vertex X="3119" Y="1022" Z="0"/>
					<Vertex X="3114" Y="1022" Z="0"/>
					<Vertex X="3110" Y="1022" Z="0"/>
					<Vertex X="3105" Y="1022" Z="0"/>
					<Vertex X="3105" Y="1026" Z="0"/>
					<Vertex X="3101" Y="1026" Z="0"/>
					<Vertex X="3096" Y="1026" Z="0"/>
					<Vertex X="3096" Y="1031" Z="0"/>
					<Vertex X="3092" Y="1031" Z="0"/>
					<Vertex X="3087" Y="1031" Z="0"/>
					<Vertex X="3083" Y="1031" Z="0"/>
					<Vertex X="3078" Y="1031" Z="0"/>
					<Vertex X="3074" Y="1031" Z="0"/>
					<Vertex X="3069" Y="1031" Z="0"/>
					<Vertex X="3069" Y="1035" Z="0"/>
					<Vertex X="3065" Y="1035" Z="0"/>
					<Vertex X="3060" Y="1035" Z="0"/>
					<Vertex X="3056" Y="1035" Z="0"/>
					<Vertex X="3051" Y="1035" Z="0"/>
					<Vertex X="3047" Y="1040" Z="0"/>
					<Vertex X="3042" Y="1040" Z="0"/>
					<Vertex X="3038" Y="1040" Z="0"/>
					<Vertex X="3033" Y="1040" Z="0"/>
					<Vertex X="3029" Y="1040" Z="0"/>
					<Vertex X="3024" Y="1040" Z="0"/>
					<Vertex X="3024" Y="1044" Z="0"/>
					<Vertex X="3019" Y="1044" Z="0"/>
					<Vertex X="3015" Y="1044" Z="0"/>
					<Vertex X="3010" Y="1044" Z="0"/>
					<Vertex X="3006" Y="1044" Z="0"/>
					<Vertex X="3006" Y="1049" Z="0"/>
					<Vertex X="3001" Y="1049" Z="0"/>
					<Vertex X="2997" Y="1049" Z="0"/>
					<Vertex X="2992" Y="1049" Z="0"/>
					<Vertex X="2988" Y="1049" Z="0"/>
					<Vertex X="2983" Y="1053" Z="0"/>
					<Vertex X="2979" Y="1053" Z="0"/>
					<Vertex X="2979" Y="1058" Z="0"/>
					<Vertex X="2974" Y="1058" Z="0"/>
					<Vertex X="2970" Y="1058" Z="0"/>
					<Vertex X="2965" Y="1058" Z="0"/>
					<Vertex X="2961" Y="1058" Z="0"/>
					<Vertex X="2956" Y="1058" Z="0"/>
					<Vertex X="2956" Y="1062" Z="0"/>
					<Vertex X="2952" Y="1062" Z="0"/>
					<Vertex X="2947" Y="1062" Z="0"/>
					<Vertex X="2947" Y="1067" Z="0"/>
					<Vertex X="2943" Y="1067" Z="0"/>
					<Vertex X="2938" Y="1067" Z="0"/>
					<Vertex X="2934" Y="1067" Z="0"/>
					<Vertex X="2929" Y="1067" Z="0"/>
					<Vertex X="2929" Y="1071" Z="0"/>
					<Vertex X="2925" Y="1071" Z="0"/>
					<Vertex X="2920" Y="1071" Z="0"/>
					<Vertex X="2920" Y="1076" Z="0"/>
					<Vertex X="2916" Y="1076" Z="0"/>
					<Vertex X="2911" Y="1076" Z="0"/>
					<Vertex X="2906" Y="1076" Z="0"/>
					<Vertex X="2902" Y="1076" Z="0"/>
					<Vertex X="2902" Y="1080" Z="0"/>
					<Vertex X="2897" Y="1080" Z="0"/>
					<Vertex X="2893" Y="1080" Z="0"/>
					<Vertex X="2893" Y="1085" Z="0"/>
					<Vertex X="2888" Y="1085" Z="0"/>
					<Vertex X="2884" Y="1085" Z="0"/>
					<Vertex X="2879" Y="1085" Z="0"/>
					<Vertex X="2875" Y="1089" Z="0"/>
					<Vertex X="2870" Y="1089" Z="0"/>
					<Vertex X="2866" Y="1094" Z="0"/>
					<Vertex X="2861" Y="1094" Z="0"/>
					<Vertex X="2857" Y="1094" Z="0"/>
					<Vertex X="2852" Y="1099" Z="0"/>
					<Vertex X="2848" Y="1099" Z="0"/>
					<Vertex X="2843" Y="1099" Z="0"/>
					<Vertex X="2843" Y="1103" Z="0"/>
					<Vertex X="2839" Y="1103" Z="0"/>
					<Vertex X="2834" Y="1103" Z="0"/>
					<Vertex X="2830" Y="1103" Z="0"/>
					<Vertex X="2825" Y="1103" Z="0"/>
					<Vertex X="2825" Y="1108" Z="0"/>
					<Vertex X="2821" Y="1108" Z="0"/>
					<Vertex X="2816" Y="1108" Z="0"/>
					<Vertex X="2812" Y="1112" Z="0"/>
					<Vertex X="2807" Y="1112" Z="0"/>
					<Vertex X="2803" Y="1112" Z="0"/>
					<Vertex X="2803" Y="1117" Z="0"/>
					<Vertex X="2798" Y="1117" Z="0"/>
					<Vertex X="2793" Y="1117" Z="0"/>
					<Vertex X="2789" Y="1121" Z="0"/>
					<Vertex X="2784" Y="1121" Z="0"/>
					<Vertex X="2780" Y="1121" Z="0"/>
					<Vertex X="2775" Y="1121" Z="0"/>
					<Vertex X="2771" Y="1126" Z="0"/>
					<Vertex X="2766" Y="1126" Z="0"/>
					<Vertex X="2762" Y="1126" Z="0"/>
					<Vertex X="2762" Y="1130" Z="0"/>
					<Vertex X="2757" Y="1130" Z="0"/>
					<Vertex X="2753" Y="1130" Z="0"/>
					<Vertex X="2748" Y="1130" Z="0"/>
					<Vertex X="2744" Y="1130" Z="0"/>
					<Vertex X="2739" Y="1130" Z="0"/>
					<Vertex X="2739" Y="1135" Z="0"/>
					<Vertex X="2735" Y="1135" Z="0"/>
					<Vertex X="2730" Y="1135" Z="0"/>
					<Vertex X="2726" Y="1135" Z="0"/>
					<Vertex X="2726" Y="1139" Z="0"/>
					<Vertex X="2721" Y="1139" Z="0"/>
					<Vertex X="2717" Y="1139" Z="0"/>
					<Vertex X="2708" Y="1139" Z="0"/>
					<Vertex X="2703" Y="1139" Z="0"/>
					<Vertex X="2699" Y="1144" Z="0"/>
					<Vertex X="2694" Y="1144" Z="0"/>
					<Vertex X="2689" Y="1144" Z="0"/>
					<Vertex X="2685" Y="1144" Z="0"/>
					<Vertex X="2680" Y="1148" Z="0"/>
					<Vertex X="2676" Y="1148" Z="0"/>
					<Vertex X="2671" Y="1148" Z="0"/>
					<Vertex X="2667" Y="1148" Z="0"/>
					<Vertex X="2662" Y="1148" Z="0"/>
					<Vertex X="2658" Y="1153" Z="0"/>
					<Vertex X="2653" Y="1153" Z="0"/>
					<Vertex X="2649" Y="1153" Z="0"/>
					<Vertex X="2644" Y="1157" Z="0"/>
					<Vertex X="2640" Y="1157" Z="0"/>
					<Vertex X="2635" Y="1157" Z="0"/>
					<Vertex X="2631" Y="1157" Z="0"/>
					<Vertex X="2626" Y="1157" Z="0"/>
					<Vertex X="2622" Y="1162" Z="0"/>
					<Vertex X="2617" Y="1162" Z="0"/>
					<Vertex X="2613" Y="1162" Z="0"/>
					<Vertex X="2613" Y="1166" Z="0"/>
					<Vertex X="2608" Y="1166" Z="0"/>
					<Vertex X="2604" Y="1166" Z="0"/>
					<Vertex X="2599" Y="1166" Z="0"/>
					<Vertex X="2595" Y="1166" Z="0"/>
					<Vertex X="2590" Y="1166" Z="0"/>
					<Vertex X="2590" Y="1171" Z="0"/>
					<Vertex X="2586" Y="1171" Z="0"/>
					<Vertex X="2581" Y="1171" Z="0"/>
					<Vertex X="2576" Y="1175" Z="0"/>
					<Vertex X="2572" Y="1175" Z="0"/>
					<Vertex X="2567" Y="1175" Z="0"/>
					<Vertex X="2563" Y="1175" Z="0"/>
					<Vertex X="2563" Y="1180" Z="0"/>
					<Vertex X="2558" Y="1180" Z="0"/>
					<Vertex X="2554" Y="1180" Z="0"/>
					<Vertex X="2549" Y="1180" Z="0"/>
					<Vertex X="2545" Y="1184" Z="0"/>
					<Vertex X="2540" Y="1184" Z="0"/>
					<Vertex X="2536" Y="1184" Z="0"/>
					<Vertex X="2531" Y="1184" Z="0"/>
					<Vertex X="2531" Y="1189" Z="0"/>
					<Vertex X="2527" Y="1189" Z="0"/>
					<Vertex X="2522" Y="1189" Z="0"/>
					<Vertex X="2522" Y="1193" Z="0"/>
					<Vertex X="2513" Y="1193" Z="0"/>
					<Vertex X="2509" Y="1193" Z="0"/>
					<Vertex X="2504" Y="1193" Z="0"/>
					<Vertex X="2500" Y="1198" Z="0"/>
					<Vertex X="2495" Y="1198" Z="0"/>
					<Vertex X="2491" Y="1198" Z="0"/>
					<Vertex X="2486" Y="1198" Z="0"/>
					<Vertex X="2482" Y="1202" Z="0"/>
					<Vertex X="2477" Y="1202" Z="0"/>
					<Vertex X="2468" Y="1207" Z="0"/>
					<Vertex X="2463" Y="1207" Z="0"/>
					<Vertex X="2459" Y="1207" Z="0"/>
					<Vertex X="2450" Y="1207" Z="0"/>
					<Vertex X="2445" Y="1212" Z="0"/>
					<Vertex X="2441" Y="1212" Z="0"/>
					<Vertex X="2436" Y="1212" Z="0"/>
					<Vertex X="2432" Y="1216" Z="0"/>
					<Vertex X="2423" Y="1216" Z="0"/>
					<Vertex X="2418" Y="1216" Z="0"/>
					<Vertex X="2414" Y="1221" Z="0"/>
					<Vertex X="2405" Y="1221" Z="0"/>
					<Vertex X="2400" Y="1221" Z="0"/>
					<Vertex X="2391" Y="1225" Z="0"/>
					<Vertex X="2387" Y="1225" Z="0"/>
					<Vertex X="2382" Y="1225" Z="0"/>
					<Vertex X="2373" Y="1225" Z="0"/>
					<Vertex X="2369" Y="1230" Z="0"/>
					<Vertex X="2364" Y="1230" Z="0"/>
					<Vertex X="2359" Y="1230" Z="0"/>
					<Vertex X="2355" Y="1234" Z="0"/>
					<Vertex X="2350" Y="1234" Z="0"/>
					<Vertex X="2346" Y="1234" Z="0"/>
					<Vertex X="2341" Y="1234" Z="0"/>
					<Vertex X="2337" Y="1234" Z="0"/>
					<Vertex X="2332" Y="1234" Z="0"/>
					<Vertex X="2332" Y="1239" Z="0"/>
					<Vertex X="2328" Y="1239" Z="0"/>
					<Vertex X="2323" Y="1239" Z="0"/>
					<Vertex X="2319" Y="1239" Z="0"/>
					<Vertex X="2314" Y="1243" Z="0"/>
					<Vertex X="2310" Y="1243" Z="0"/>
					<Vertex X="2305" Y="1243" Z="0"/>
					<Vertex X="2301" Y="1243" Z="0"/>
					<Vertex X="2296" Y="1243" Z="0"/>
					<Vertex X="2296" Y="1248" Z="0"/>
					<Vertex X="2292" Y="1248" Z="0"/>
					<Vertex X="2287" Y="1248" Z="0"/>
					<Vertex X="2283" Y="1248" Z="0"/>
					<Vertex X="2278" Y="1248" Z="0"/>
					<Vertex X="2274" Y="1248" Z="0"/>
					<Vertex X="2274" Y="1252" Z="0"/>
					<Vertex X="2269" Y="1252" Z="0"/>
					<Vertex X="2265" Y="1252" Z="0"/>
					<Vertex X="2260" Y="1252" Z="0"/>
					<Vertex X="2256" Y="1252" Z="0"/>
					<Vertex X="2246" Y="1252" Z="0"/>
					<Vertex X="2242" Y="1252" Z="0"/>
					<Vertex X="2237" Y="1252" Z="0"/>
					<Vertex X="2233" Y="1257" Z="0"/>
					<Vertex X="2228" Y="1257" Z="0"/>
					<Vertex X="2219" Y="1257" Z="0"/>
					<Vertex X="2215" Y="1257" Z="0"/>
					<Vertex X="2210" Y="1257" Z="0"/>
					<Vertex X="2210" Y="1261" Z="0"/>
					<Vertex X="2206" Y="1261" Z="0"/>
					<Vertex X="2201" Y="1261" Z="0"/>
					<Vertex X="2197" Y="1261" Z="0"/>
					<Vertex X="2192" Y="1261" Z="0"/>
					<Vertex X="2188" Y="1261" Z="0"/>
					<Vertex X="2183" Y="1261" Z="0"/>
					<Vertex X="2179" Y="1261" Z="0"/>
					<Vertex X="2174" Y="1261" Z="0"/>
					<Vertex X="2170" Y="1261" Z="0"/>
					<Vertex X="2161" Y="1261" Z="0"/>
					<Vertex X="2156" Y="1261" Z="0"/>
					<Vertex X="2152" Y="1261" Z="0"/>
					<Vertex X="2142" Y="1261" Z="0"/>
					<Vertex X="2133" Y="1261" Z="0"/>
					<Vertex X="2129" Y="1261" Z="0"/>
					<Vertex X="2120" Y="1261" Z="0"/>
					<Vertex X="2111" Y="1261" Z="0"/>
					<Vertex X="2102" Y="1261" Z="0"/>
					<Vertex X="2097" Y="1261" Z="0"/>
					<Vertex X="2088" Y="1261" Z="0"/>
					<Vertex X="2079" Y="1261" Z="0"/>
					<Vertex X="2075" Y="1257" Z="0"/>
					<Vertex X="2070" Y="1257" Z="0"/>
					<Vertex X="2061" Y="1257" Z="0"/>
					<Vertex X="2057" Y="1257" Z="0"/>
					<Vertex X="2052" Y="1252" Z="0"/>
					<Vertex X="2043" Y="1252" Z="0"/>
					<Vertex X="2039" Y="1252" Z="0"/>
					<Vertex X="2034" Y="1252" Z="0"/>
					<Vertex X="2029" Y="1248" Z="0"/>
					<Vertex X="2025" Y="1248" Z="0"/>
					<Vertex X="2020" Y="1248" Z="0"/>
					<Vertex X="2016" Y="1248" Z="0"/>
					<Vertex X="2011" Y="1248" Z="0"/>
					<Vertex X="2007" Y="1243" Z="0"/>
					<Vertex X="2002" Y="1243" Z="0"/>
					<Vertex X="1998" Y="1243" Z="0"/>
					<Vertex X="1998" Y="1239" Z="0"/>
					<Vertex X="1993" Y="1239" Z="0"/>
					<Vertex X="1989" Y="1239" Z="0"/>
					<Vertex X="1984" Y="1234" Z="0"/>
					<Vertex X="1975" Y="1234" Z="0"/>
					<Vertex X="1966" Y="1230" Z="0"/>
					<Vertex X="1962" Y="1230" Z="0"/>
					<Vertex X="1957" Y="1225" Z="0"/>
					<Vertex X="1948" Y="1221" Z="0"/>
					<Vertex X="1944" Y="1221" Z="0"/>
					<Vertex X="1939" Y="1221" Z="0"/>
					<Vertex X="1935" Y="1216" Z="0"/>
					<Vertex X="1930" Y="1216" Z="0"/>
					<Vertex X="1930" Y="1212" Z="0"/>
					<Vertex X="1925" Y="1212" Z="0"/>
					<Vertex X="1921" Y="1212" Z="0"/>
					<Vertex X="1916" Y="1212" Z="0"/>
					<Vertex X="1916" Y="1207" Z="0"/>
					<Vertex X="1912" Y="1207" Z="0"/>
					<Vertex X="1907" Y="1202" Z="0"/>
					<Vertex X="1903" Y="1202" Z="0"/>
					<Vertex X="1898" Y="1202" Z="0"/>
					<Vertex X="1894" Y="1198" Z="0"/>
					<Vertex X="1889" Y="1198" Z="0"/>
					<Vertex X="1885" Y="1193" Z="0"/>
					<Vertex X="1885" Y="1189" Z="0"/>
					<Vertex X="1880" Y="1189" Z="0"/>
					<Vertex X="1876" Y="1189" Z="0"/>
					<Vertex X="1876" Y="1184" Z="0"/>
					<Vertex X="1871" Y="1184" Z="0"/>
					<Vertex X="1867" Y="1180" Z="0"/>
					<Vertex X="1862" Y="1180" Z="0"/>
					<Vertex X="1858" Y="1180" Z="0"/>
					<Vertex X="1858" Y="1175" Z="0"/>
					<Vertex X="1853" Y="1175" Z="0"/>
					<Vertex X="1849" Y="1175" Z="0"/>
					<Vertex X="1849" Y="1171" Z="0"/>
					<Vertex X="1844" Y="1171" Z="0"/>
					<Vertex X="1840" Y="1171" Z="0"/>
					<Vertex X="1840" Y="1166" Z="0"/>
					<Vertex X="1835" Y="1162" Z="0"/>
					<Vertex X="1831" Y="1162" Z="0"/>
					<Vertex X="1826" Y="1162" Z="0"/>
					<Vertex X="1826" Y="1157" Z="0"/>
					<Vertex X="1822" Y="1157" Z="0"/>
					<Vertex X="1822" Y="1153" Z="0"/>
					<Vertex X="1817" Y="1153" Z="0"/>
					<Vertex X="1812" Y="1153" Z="0"/>
					<Vertex X="1812" Y="1148" Z="0"/>
					<Vertex X="1808" Y="1148" Z="0"/>
					<Vertex X="1803" Y="1148" Z="0"/>
					<Vertex X="1803" Y="1144" Z="0"/>
					<Vertex X="1799" Y="1144" Z="0"/>
					<Vertex X="1794" Y="1144" Z="0"/>
					<Vertex X="1794" Y="1139" Z="0"/>
					<Vertex X="1790" Y="1135" Z="0"/>
					<Vertex X="1785" Y="1130" Z="0"/>
					<Vertex X="1781" Y="1130" Z="0"/>
					<Vertex X="1781" Y="1126" Z="0"/>
					<Vertex X="1772" Y="1126" Z="0"/>
					<Vertex X="1772" Y="1121" Z="0"/>
					<Vertex X="1767" Y="1117" Z="0"/>
					<Vertex X="1763" Y="1117" Z="0"/>
					<Vertex X="1758" Y="1112" Z="0"/>
					<Vertex X="1754" Y="1108" Z="0"/>
					<Vertex X="1754" Y="1103" Z="0"/>
					<Vertex X="1749" Y="1103" Z="0"/>
					<Vertex X="1745" Y="1099" Z="0"/>
					<Vertex X="1740" Y="1099" Z="0"/>
					<Vertex X="1740" Y="1094" Z="0"/>
					<Vertex X="1736" Y="1089" Z="0"/>
					<Vertex X="1731" Y="1089" Z="0"/>
					<Vertex X="1731" Y="1085" Z="0"/>
					<Vertex X="1727" Y="1085" Z="0"/>
					<Vertex X="1727" Y="1080" Z="0"/>
					<Vertex X="1722" Y="1080" Z="0"/>
					<Vertex X="1718" Y="1080" Z="0"/>
					<Vertex X="1718" Y="1076" Z="0"/>
					<Vertex X="1713" Y="1076" Z="0"/>
					<Vertex X="1713" Y="1071" Z="0"/>
					<Vertex X="1709" Y="1071" Z="0"/>
					<Vertex X="1709" Y="1067" Z="0"/>
					<Vertex X="1704" Y="1067" Z="0"/>
					<Vertex X="1699" Y="1062" Z="0"/>
					<Vertex X="1695" Y="1062" Z="0"/>
					<Vertex X="1695" Y="1058" Z="0"/>
					<Vertex X="1690" Y="1053" Z="0"/>
					<Vertex X="1686" Y="1053" Z="0"/>
					<Vertex X="1686" Y="1049" Z="0"/>
					<Vertex X="1681" Y="1049" Z="0"/>
					<Vertex X="1677" Y="1044" Z="0"/>
					<Vertex X="1672" Y="1040" Z="0"/>
					<Vertex X="1668" Y="1035" Z="0"/>
					<Vertex X="1663" Y="1035" Z="0"/>
					<Vertex X="1659" Y="1031" Z="0"/>
					<Vertex X="1654" Y="1026" Z="0"/>
					<Vertex X="1650" Y="1026" Z="0"/>
					<Vertex X="1645" Y="1026" Z="0"/>
					<Vertex X="1645" Y="1022" Z="0"/>
					<Vertex X="1641" Y="1022" Z="0"/>
					<Vertex X="1636" Y="1017" Z="0"/>
					<Vertex X="1632" Y="1017" Z="0"/>
					<Vertex X="1632" Y="1013" Z="0"/>
					<Vertex X="1627" Y="1013" Z="0"/>
					<Vertex X="1627" Y="1008" Z="0"/>
					<Vertex X="1623" Y="1008" Z="0"/>
					<Vertex X="1618" Y="1008" Z="0"/>
					<Vertex X="1618" Y="1004" Z="0"/>
					<Vertex X="1614" Y="1004" Z="0"/>
					<Vertex X="1614" Y="999" Z="0"/>
					<Vertex X="1609" Y="999" Z="0"/>
					<Vertex X="1605" Y="999" Z="0"/>
					<Vertex X="1600" Y="995" Z="0"/>
					<Vertex X="1595" Y="995" Z="0"/>
					<Vertex X="1595" Y="990" Z="0"/>
					<Vertex X="1591" Y="990" Z="0"/>
					<Vertex X="1591" Y="985" Z="0"/>
					<Vertex X="1586" Y="985" Z="0"/>
					<Vertex X="1582" Y="985" Z="0"/>
					<Vertex X="1582" Y="981" Z="0"/>
					<Vertex X="1577" Y="981" Z="0"/>
					<Vertex X="1573" Y="976" Z="0"/>
					<Vertex X="1568" Y="976" Z="0"/>
					<Vertex X="1568" Y="972" Z="0"/>
					<Vertex X="1564" Y="972" Z="0"/>
					<Vertex X="1564" Y="967" Z="0"/>
					<Vertex X="1559" Y="967" Z="0"/>
					<Vertex X="1559" Y="963" Z="0"/>
					<Vertex X="1555" Y="963" Z="0"/>
					<Vertex X="1550" Y="963" Z="0"/>
					<Vertex X="1550" Y="958" Z="0"/>
					<Vertex X="1546" Y="958" Z="0"/>
					<Vertex X="1541" Y="954" Z="0"/>
					<Vertex X="1537" Y="949" Z="0"/>
					<Vertex X="1532" Y="949" Z="0"/>
					<Vertex X="1532" Y="945" Z="0"/>
					<Vertex X="1532" Y="940" Z="0"/>
					<Vertex X="1528" Y="940" Z="0"/>
					<Vertex X="1523" Y="940" Z="0"/>
					<Vertex X="1523" Y="936" Z="0"/>
					<Vertex X="1519" Y="931" Z="0"/>
					<Vertex X="1514" Y="931" Z="0"/>
					<Vertex X="1514" Y="927" Z="0"/>
					<Vertex X="1510" Y="927" Z="0"/>
					<Vertex X="1510" Y="922" Z="0"/>
					<Vertex X="1505" Y="922" Z="0"/>
					<Vertex X="1505" Y="918" Z="0"/>
					<Vertex X="1501" Y="918" Z="0"/>
					<Vertex X="1496" Y="913" Z="0"/>
					<Vertex X="1496" Y="909" Z="0"/>
					<Vertex X="1492" Y="909" Z="0"/>
					<Vertex X="1492" Y="904" Z="0"/>
					<Vertex X="1487" Y="904" Z="0"/>
					<Vertex X="1487" Y="900" Z="0"/>
					<Vertex X="1487" Y="895" Z="0"/>
					<Vertex X="1482" Y="895" Z="0"/>
					<Vertex X="1482" Y="891" Z="0"/>
					<Vertex X="1478" Y="891" Z="0"/>
					<Vertex X="1478" Y="886" Z="0"/>
					<Vertex X="1473" Y="882" Z="0"/>
					<Vertex X="1469" Y="877" Z="0"/>
					<Vertex X="1469" Y="872" Z="0"/>
					<Vertex X="1464" Y="868" Z="0"/>
					<Vertex X="1460" Y="868" Z="0"/>
					<Vertex X="1460" Y="863" Z="0"/>
					<Vertex X="1455" Y="859" Z="0"/>
					<Vertex X="1451" Y="854" Z="0"/>
					<Vertex X="1451" Y="850" Z="0"/>
					<Vertex X="1446" Y="845" Z="0"/>
					<Vertex X="1442" Y="841" Z="0"/>
					<Vertex X="1437" Y="841" Z="0"/>
					<Vertex X="1437" Y="836" Z="0"/>
					<Vertex X="1437" Y="832" Z="0"/>
					<Vertex X="1433" Y="832" Z="0"/>
					<Vertex X="1433" Y="827" Z="0"/>
					<Vertex X="1428" Y="827" Z="0"/>
					<Vertex X="1424" Y="823" Z="0"/>
					<Vertex X="1424" Y="818" Z="0"/>
					<Vertex X="1419" Y="818" Z="0"/>
					<Vertex X="1419" Y="814" Z="0"/>
					<Vertex X="1415" Y="814" Z="0"/>
					<Vertex X="1410" Y="814" Z="0"/>
					<Vertex X="1410" Y="809" Z="0"/>
					<Vertex X="1406" Y="805" Z="0"/>
					<Vertex X="1401" Y="805" Z="0"/>
					<Vertex X="1401" Y="800" Z="0"/>
					<Vertex X="1397" Y="800" Z="0"/>
					<Vertex X="1397" Y="796" Z="0"/>
					<Vertex X="1392" Y="796" Z="0"/>
					<Vertex X="1388" Y="796" Z="0"/>
					<Vertex X="1388" Y="791" Z="0"/>
					<Vertex X="1383" Y="791" Z="0"/>
					<Vertex X="1379" Y="787" Z="0"/>
					<Vertex X="1374" Y="787" Z="0"/>
					<Vertex X="1374" Y="782" Z="0"/>
					<Vertex X="1369" Y="782" Z="0"/>
					<Vertex X="1369" Y="778" Z="0"/>
					<Vertex X="1365" Y="773" Z="0"/>
					<Vertex X="1360" Y="773" Z="0"/>
					<Vertex X="1356" Y="773" Z="0"/>
					<Vertex X="1356" Y="769" Z="0"/>
					<Vertex X="1356" Y="764" Z="0"/>
					<Vertex X="1351" Y="764" Z="0"/>
					<Vertex X="1347" Y="764" Z="0"/>
					<Vertex X="1347" Y="759" Z="0"/>
					<Vertex X="1342" Y="759" Z="0"/>
					<Vertex X="1342" Y="755" Z="0"/>
					<Vertex X="1338" Y="755" Z="0"/>
					<Vertex X="1333" Y="755" Z="0"/>
					<Vertex X="1333" Y="750" Z="0"/>
					<Vertex X="1329" Y="750" Z="0"/>
					<Vertex X="1329" Y="746" Z="0"/>
					<Vertex X="1324" Y="746" Z="0"/>
					<Vertex X="1324" Y="741" Z="0"/>
					<Vertex X="1320" Y="741" Z="0"/>
					<Vertex X="1320" Y="737" Z="0"/>
					<Vertex X="1315" Y="737" Z="0"/>
					<Vertex X="1311" Y="737" Z="0"/>
					<Vertex X="1306" Y="732" Z="0"/>
					<Vertex X="1302" Y="732" Z="0"/>
					<Vertex X="1302" Y="728" Z="0"/>
					<Vertex X="1297" Y="728" Z="0"/>
					<Vertex X="1293" Y="723" Z="0"/>
					<Vertex X="1288" Y="723" Z="0"/>
					<Vertex X="1288" Y="719" Z="0"/>
					<Vertex X="1284" Y="719" Z="0"/>
					<Vertex X="1279" Y="719" Z="0"/>
					<Vertex X="1279" Y="714" Z="0"/>
					<Vertex X="1275" Y="714" Z="0"/>
					<Vertex X="1275" Y="710" Z="0"/>
					<Vertex X="1270" Y="710" Z="0"/>
					<Vertex X="1265" Y="705" Z="0"/>
					<Vertex X="1256" Y="705" Z="0"/>
					<Vertex X="1256" Y="701" Z="0"/>
					<Vertex X="1252" Y="701" Z="0"/>
					<Vertex X="1247" Y="701" Z="0"/>
					<Vertex X="1243" Y="701" Z="0"/>
					<Vertex X="1243" Y="696" Z="0"/>
					<Vertex X="1238" Y="696" Z="0"/>
					<Vertex X="1238" Y="692" Z="0"/>
					<Vertex X="1234" Y="692" Z="0"/>
					<Vertex X="1229" Y="692" Z="0"/>
					<Vertex X="1225" Y="692" Z="0"/>
					<Vertex X="1220" Y="692" Z="0"/>
					<Vertex X="1216" Y="687" Z="0"/>
					<Vertex X="1211" Y="687" Z="0"/>
					<Vertex X="1207" Y="687" Z="0"/>
					<Vertex X="1202" Y="683" Z="0"/>
					<Vertex X="1193" Y="683" Z="0"/>
					<Vertex X="1189" Y="683" Z="0"/>
					<Vertex X="1184" Y="683" Z="0"/>
					<Vertex X="1180" Y="683" Z="0"/>
					<Vertex X="1175" Y="683" Z="0"/>
					<Vertex X="1171" Y="683" Z="0"/>
					<Vertex X="1166" Y="683" Z="0"/>
					<Vertex X="1162" Y="683" Z="0"/>
					<Vertex X="1157" Y="683" Z="0"/>
					<Vertex X="1152" Y="683" Z="0"/>
					<Vertex X="1148" Y="683" Z="0"/>
					<Vertex X="1143" Y="683" Z="0"/>
					<Vertex X="1139" Y="683" Z="0"/>
					<Vertex X="1134" Y="683" Z="0"/>
					<Vertex X="1130" Y="683" Z="0"/>
					<Vertex X="1125" Y="683" Z="0"/>
					<Vertex X="1121" Y="683" Z="0"/>
					<Vertex X="1116" Y="683" Z="0"/>
					<Vertex X="1112" Y="683" Z="0"/>
					<Vertex X="1107" Y="683" Z="0"/>
					<Vertex X="1103" Y="683" Z="0"/>
					<Vertex X="1098" Y="683" Z="0"/>
					<Vertex X="1094" Y="687" Z="0"/>
					<Vertex X="1089" Y="687" Z="0"/>
					<Vertex X="1085" Y="687" Z="0"/>
					<Vertex X="1080" Y="687" Z="0"/>
					<Vertex X="1076" Y="687" Z="0"/>
					<Vertex X="1071" Y="687" Z="0"/>
					<Vertex X="1071" Y="692" Z="0"/>
					<Vertex X="1067" Y="692" Z="0"/>
					<Vertex X="1062" Y="692" Z="0"/>
					<Vertex X="1058" Y="692" Z="0"/>
					<Vertex X="1053" Y="696" Z="0"/>
					<Vertex X="1048" Y="696" Z="0"/>
					<Vertex X="1044" Y="696" Z="0"/>
					<Vertex X="1044" Y="701" Z="0"/>
					<Vertex X="1039" Y="701" Z="0"/>
					<Vertex X="1035" Y="701" Z="0"/>
					<Vertex X="1035" Y="705" Z="0"/>
					<Vertex X="1030" Y="705" Z="0"/>
					<Vertex X="1026" Y="705" Z="0"/>
					<Vertex X="1021" Y="705" Z="0"/>
					<Vertex X="1017" Y="705" Z="0"/>
					<Vertex X="1012" Y="710" Z="0"/>
					<Vertex X="1008" Y="710" Z="0"/>
					<Vertex X="1003" Y="710" Z="0"/>
					<Vertex X="999" Y="714" Z="0"/>
					<Vertex X="994" Y="714" Z="0"/>
					<Vertex X="990" Y="714" Z="0"/>
					<Vertex X="985" Y="714" Z="0"/>
					<Vertex X="985" Y="719" Z="0"/>
					<Vertex X="981" Y="719" Z="0"/>
					<Vertex X="976" Y="719" Z="0"/>
					<Vertex X="976" Y="723" Z="0"/>
					<Vertex X="972" Y="723" Z="0"/>
					<Vertex X="967" Y="723" Z="0"/>
					<Vertex X="967" Y="728" Z="0"/>
					<Vertex X="963" Y="728" Z="0"/>
					<Vertex X="963" Y="732" Z="0"/>
					<Vertex X="958" Y="732" Z="0"/>
					<Vertex X="954" Y="732" Z="0"/>
					<Vertex X="954" Y="737" Z="0"/>
					<Vertex X="949" Y="737" Z="0"/>
					<Vertex X="949" Y="741" Z="0"/>
					<Vertex X="949" Y="746" Z="0"/>
					<Vertex X="945" Y="746" Z="0"/>
					<Vertex X="908" Y="773" Z="0"/>
				</Vertices>
			</Region>
		</Regions>
		<Plots/>
	</Annotation>
</Annotations>
