<Annotations>
	<Annotation Id="1" Name="Anna" ReadOnly="0" NameReadOnly="0" LineColorReadOnly="0" Incremental="0" Type="4" LineColor="255" Visible="1" Selected="1" MarkupImagePath="" MacroName="">
		<Attributes/>
		<Regions>
			<RegionAttributeHeaders>
				<AttributeHeader Id="9999" Name="Region" ColumnWidth="-1"/>
				<AttributeHeader Id="9997" Name="Length" ColumnWidth="-1"/>
				<AttributeHeader Id="9996" Name="Area" ColumnWidth="-1"/>
				<AttributeHeader Id="9998" Name="Text" ColumnWidth="-1"/>
				<AttributeHeader Id="1" Name="Description" ColumnWidth="-1"/>
			</RegionAttributeHeaders>
			<Region Id="1" Type="0" Zoom="0.250000" Selected="1" ImageLocation="" ImageFocus="-1" Length="2738.1" Area="260657.5" Text="" NegativeROA="0" InputRegionId="0" Analyze="1" DisplayId="1">
				<Attributes/>
				<Vertices>
					<Vertex X="1949" Y="1162" Z="0"/>
					<Vertex X="1950" Y="1159" Z="0"/>
					<Vertex X="1952" Y="1157" Z="0"/>
					<Vertex X="1954" Y="1154" Z="0"/>
					<Vertex X="1955" Y="1151" Z="0"/>
					<Vertex X="1957" Y="1149" Z="0"/>
					<Vertex X="1958" Y="1146" Z="0"/>
					<Vertex X="1960" Y="1145" Z="0"/>
					<Vertex X="1961" Y="1143" Z="0"/>
					<Vertex X="1962" Y="1141" Z="0"/>
					<Vertex X="1964" Y="1139" Z="0"/>
					<Vertex X="1966" Y="1138" Z="0"/>
					<Vertex X="1967" Y="1135" Z="0"/>
					<Vertex X="1969" Y="1134" Z="0"/>
					<Vertex X="1970" Y="1133" Z="0"/>
					<Vertex X="1972" Y="1132" Z="0"/>
					<Vertex X="1973" Y="1128" Z="0"/>
					<Vertex X="1993" Y="1116" Z="0"/>
					<Vertex X="2004" Y="1113" Z="0"/>
					<Vertex X="2010" Y="1112" Z="0"/>
					<Vertex X="2014" Y="1112" Z="0"/>
					<Vertex X="2018" Y="1111" Z="0"/>
					<Vertex X="2023" Y="1110" Z="0"/>
					<Vertex X="2026" Y="1110" Z="0"/>
					<Vertex X="2031" Y="1110" Z="0"/>
					<Vertex X="2037" Y="1109" Z="0"/>
					<Vertex X="2043" Y="1109" Z="0"/>
					<Vertex X="2049" Y="1109" Z="0"/>
					<Vertex X="2054" Y="1108" Z="0"/>
					<Vertex X="2060" Y="1108" Z="0"/>
					<Vertex X="2067" Y="1106" Z="0"/>
					<Vertex X="2073" Y="1105" Z="0"/>
					<Vertex X="2079" Y="1104" Z="0"/>
					<Vertex X="2085" Y="1103" Z="0"/>
					<Vertex X="2094" Y="1101" Z="0"/>
					<Vertex X="2100" Y="1099" Z="0"/>
					<Vertex X="2107" Y="1098" Z="0"/>
					<Vertex X="2112" Y="1097" Z="0"/>
					<Vertex X="2118" Y="1096" Z="0"/>
					<Vertex X="2124" Y="1095" Z="0"/>
					<Vertex X="2129" Y="1095" Z="0"/>
					<Vertex X="2134" Y="1094" Z="0"/>
					<Vertex X="2139" Y="1093" Z="0"/>
					<Vertex X="2144" Y="1093" Z="0"/>
					<Vertex X="2149" Y="1092" Z="0"/>
					<Vertex X="2156" Y="1091" Z="0"/>
					<Vertex X="2160" Y="1089" Z="0"/>
					<Vertex X="2165" Y="1088" Z="0"/>
					<Vertex X="2170" Y="1087" Z="0"/>
					<Vertex X="2174" Y="1085" Z="0"/>
					<Vertex X="2179" Y="1084" Z="0"/>
					<Vertex X="2183" Y="1083" Z="0"/>
					<Vertex X="2187" Y="1082" Z="0"/>
					<Vertex X="2191" Y="1081" Z="0"/>
					<Vertex X="2195" Y="1079" Z="0"/>
					<Vertex X="2199" Y="1078" Z="0"/>
					<Vertex X="2204" Y="1077" Z="0"/>
					<Vertex X="2208" Y="1075" Z="0"/>
					<Vertex X="2213" Y="1074" Z="0"/>
					<Vertex X="2218" Y="1072" Z="0"/>
					<Vertex X="2223" Y="1070" Z="0"/>
					<Vertex X="2228" Y="1068" Z="0"/>
					<Vertex X="2234" Y="1066" Z="0"/>
					<Vertex X="2239" Y="1064" Z="0"/>
					<Vertex X="2245" Y="1062" Z="0"/>
					<Vertex X="2250" Y="1060" Z="0"/>
					<Vertex X="2256" Y="1058" Z="0"/>
					<Vertex X="2261" Y="1055" Z="0"/>
					<Vertex X="2267" Y="1054" Z="0"/>
					<Vertex X="2273" Y="1052" Z="0"/>
					<Vertex X="2278" Y="1050" Z="0"/>
					<Vertex X="2283" Y="1048" Z="0"/>
					<Vertex X="2288" Y="1046" Z="0"/>
					<Vertex X="2292" Y="1045" Z="0"/>
					<Vertex X="2297" Y="1043" Z="0"/>
					<Vertex X="2300" Y="1042" Z="0"/>
					<Vertex X="2305" Y="1040" Z="0"/>
					<Vertex X="2309" Y="1038" Z="0"/>
					<Vertex X="2313" Y="1036" Z="0"/>
					<Vertex X="2318" Y="1034" Z="0"/>
					<Vertex X="2324" Y="1031" Z="0"/>
					<Vertex X="2330" Y="1029" Z="0"/>
					<Vertex X="2335" Y="1027" Z="0"/>
					<Vertex X="2340" Y="1026" Z="0"/>
					<Vertex X="2346" Y="1024" Z="0"/>
					<Vertex X="2352" Y="1022" Z="0"/>
					<Vertex X="2358" Y="1021" Z="0"/>
					<Vertex X="2363" Y="1020" Z="0"/>
					<Vertex X="2368" Y="1019" Z="0"/>
					<Vertex X="2372" Y="1018" Z="0"/>
					<Vertex X="2377" Y="1017" Z="0"/>
					<Vertex X="2382" Y="1017" Z="0"/>
					<Vertex X="2386" Y="1016" Z="0"/>
					<Vertex X="2391" Y="1015" Z="0"/>
					<Vertex X="2395" Y="1014" Z="0"/>
					<Vertex X="2397" Y="1013" Z="0"/>
					<Vertex X="2418" Y="1005" Z="0"/>
					<Vertex X="2429" Y="1002" Z="0"/>
					<Vertex X="2434" Y="1001" Z="0"/>
					<Vertex X="2442" Y="998" Z="0"/>
					<Vertex X="2447" Y="996" Z="0"/>
					<Vertex X="2453" Y="994" Z="0"/>
					<Vertex X="2458" Y="992" Z="0"/>
					<Vertex X="2461" Y="991" Z="0"/>
					<Vertex X="2465" Y="990" Z="0"/>
					<Vertex X="2469" Y="988" Z="0"/>
					<Vertex X="2472" Y="988" Z="0"/>
					<Vertex X="2476" Y="986" Z="0"/>
					<Vertex X="2479" Y="985" Z="0"/>
					<Vertex X="2483" Y="983" Z="0"/>
					<Vertex X="2487" Y="980" Z="0"/>
					<Vertex X="2492" Y="977" Z="0"/>
					<Vertex X="2495" Y="975" Z="0"/>
					<Vertex X="2500" Y="972" Z="0"/>
					<Vertex X="2505" Y="969" Z="0"/>
					<Vertex X="2509" Y="967" Z="0"/>
					<Vertex X="2513" Y="964" Z="0"/>
					<Vertex X="2517" Y="962" Z="0"/>
					<Vertex X="2520" Y="959" Z="0"/>
					<Vertex X="2523" Y="957" Z="0"/>
					<Vertex X="2527" Y="955" Z="0"/>
					<Vertex X="2530" Y="952" Z="0"/>
					<Vertex X="2534" Y="950" Z="0"/>
					<Vertex X="2537" Y="947" Z="0"/>
					<Vertex X="2541" Y="943" Z="0"/>
					<Vertex X="2544" Y="940" Z="0"/>
					<Vertex X="2549" Y="936" Z="0"/>
					<Vertex X="2554" Y="933" Z="0"/>
					<Vertex X="2558" Y="929" Z="0"/>
					<Vertex X="2564" Y="926" Z="0"/>
					<Vertex X="2568" Y="923" Z="0"/>
					<Vertex X="2572" Y="920" Z="0"/>
					<Vertex X="2575" Y="917" Z="0"/>
					<Vertex X="2579" Y="914" Z="0"/>
					<Vertex X="2582" Y="912" Z="0"/>
					<Vertex X="2585" Y="910" Z="0"/>
					<Vertex X="2587" Y="908" Z="0"/>
					<Vertex X="2590" Y="907" Z="0"/>
					<Vertex X="2592" Y="906" Z="0"/>
					<Vertex X="2594" Y="905" Z="0"/>
					<Vertex X="2596" Y="904" Z="0"/>
					<Vertex X="2599" Y="903" Z="0"/>
					<Vertex X="2604" Y="901" Z="0"/>
					<Vertex X="2608" Y="899" Z="0"/>
					<Vertex X="2614" Y="897" Z="0"/>
					<Vertex X="2620" Y="894" Z="0"/>
					<Vertex X="2624" Y="893" Z="0"/>
					<Vertex X="2631" Y="890" Z="0"/>
					<Vertex X="2638" Y="888" Z="0"/>
					<Vertex X="2645" Y="886" Z="0"/>
					<Vertex X="2651" Y="884" Z="0"/>
					<Vertex X="2656" Y="882" Z="0"/>
					<Vertex X="2662" Y="880" Z="0"/>
					<Vertex X="2668" Y="879" Z="0"/>
					<Vertex X="2673" Y="877" Z="0"/>
					<Vertex X="2679" Y="875" Z="0"/>
					<Vertex X="2683" Y="874" Z="0"/>
					<Vertex X="2687" Y="872" Z="0"/>
					<Vertex X="2692" Y="871" Z="0"/>
					<Vertex X="2697" Y="870" Z="0"/>
					<Vertex X="2703" Y="868" Z="0"/>
					<Vertex X="2706" Y="866" Z="0"/>
					<Vertex X="2711" Y="865" Z="0"/>
					<Vertex X="2716" Y="863" Z="0"/>
					<Vertex X="2721" Y="862" Z="0"/>
					<Vertex X="2727" Y="861" Z="0"/>
					<Vertex X="2731" Y="860" Z="0"/>
					<Vertex X="2736" Y="860" Z="0"/>
					<Vertex X="2741" Y="859" Z="0"/>
					<Vertex X="2747" Y="859" Z="0"/>
					<Vertex X="2750" Y="858" Z="0"/>
					<Vertex X="2755" Y="858" Z="0"/>
					<Vertex X="2759" Y="858" Z="0"/>
					<Vertex X="2763" Y="858" Z="0"/>
					<Vertex X="2766" Y="858" Z="0"/>
					<Vertex X="2769" Y="858" Z="0"/>
					<Vertex X="2772" Y="858" Z="0"/>
					<Vertex X="2775" Y="859" Z="0"/>
					<Vertex X="2778" Y="859" Z="0"/>
					<Vertex X="2781" Y="860" Z="0"/>
					<Vertex X="2784" Y="860" Z="0"/>
					<Vertex X="2787" Y="861" Z="0"/>
					<Vertex X="2790" Y="861" Z="0"/>
					<Vertex X="2793" Y="862" Z="0"/>
					<Vertex X="2796" Y="863" Z="0"/>
					<Vertex X="2798" Y="865" Z="0"/>
					<Vertex X="2800" Y="867" Z="0"/>
					<Vertex X="2802" Y="868" Z="0"/>
					<Vertex X="2804" Y="870" Z="0"/>
					<Vertex X="2805" Y="872" Z="0"/>
					<Vertex X="2806" Y="875" Z="0"/>
					<Vertex X="2806" Y="877" Z="0"/>
					<Vertex X="2807" Y="879" Z="0"/>
					<Vertex X="2807" Y="881" Z="0"/>
					<Vertex X="2807" Y="884" Z="0"/>
					<Vertex X="2807" Y="886" Z="0"/>
					<Vertex X="2806" Y="888" Z="0"/>
					<Vertex X="2806" Y="891" Z="0"/>
					<Vertex X="2806" Y="894" Z="0"/>
					<Vertex X="2805" Y="897" Z="0"/>
					<Vertex X="2804" Y="900" Z="0"/>
					<Vertex X="2803" Y="903" Z="0"/>
					<Vertex X="2802" Y="907" Z="0"/>
					<Vertex X="2801" Y="910" Z="0"/>
					<Vertex X="2800" Y="915" Z="0"/>
					<Vertex X="2799" Y="919" Z="0"/>
					<Vertex X="2793" Y="935" Z="0"/>
					<Vertex X="2787" Y="945" Z="0"/>
					<Vertex X="2784" Y="950" Z="0"/>
					<Vertex X="2782" Y="955" Z="0"/>
					<Vertex X="2779" Y="963" Z="0"/>
					<Vertex X="2775" Y="972" Z="0"/>
					<Vertex X="2772" Y="980" Z="0"/>
					<Vertex X="2769" Y="989" Z="0"/>
					<Vertex X="2765" Y="999" Z="0"/>
					<Vertex X="2761" Y="1009" Z="0"/>
					<Vertex X="2756" Y="1020" Z="0"/>
					<Vertex X="2752" Y="1029" Z="0"/>
					<Vertex X="2748" Y="1039" Z="0"/>
					<Vertex X="2745" Y="1048" Z="0"/>
					<Vertex X="2741" Y="1058" Z="0"/>
					<Vertex X="2737" Y="1067" Z="0"/>
					<Vertex X="2732" Y="1077" Z="0"/>
					<Vertex X="2728" Y="1087" Z="0"/>
					<Vertex X="2723" Y="1097" Z="0"/>
					<Vertex X="2719" Y="1107" Z="0"/>
					<Vertex X="2715" Y="1116" Z="0"/>
					<Vertex X="2710" Y="1124" Z="0"/>
					<Vertex X="2706" Y="1132" Z="0"/>
					<Vertex X="2702" Y="1139" Z="0"/>
					<Vertex X="2697" Y="1145" Z="0"/>
					<Vertex X="2693" Y="1151" Z="0"/>
					<Vertex X="2689" Y="1156" Z="0"/>
					<Vertex X="2686" Y="1160" Z="0"/>
					<Vertex X="2682" Y="1164" Z="0"/>
					<Vertex X="2678" Y="1167" Z="0"/>
					<Vertex X="2674" Y="1171" Z="0"/>
					<Vertex X="2670" Y="1174" Z="0"/>
					<Vertex X="2666" Y="1177" Z="0"/>
					<Vertex X="2663" Y="1180" Z="0"/>
					<Vertex X="2658" Y="1184" Z="0"/>
					<Vertex X="2654" Y="1187" Z="0"/>
					<Vertex X="2650" Y="1190" Z="0"/>
					<Vertex X="2645" Y="1194" Z="0"/>
					<Vertex X="2640" Y="1198" Z="0"/>
					<Vertex X="2636" Y="1201" Z="0"/>
					<Vertex X="2632" Y="1205" Z="0"/>
					<Vertex X="2628" Y="1208" Z="0"/>
					<Vertex X="2624" Y="1211" Z="0"/>
					<Vertex X="2620" Y="1213" Z="0"/>
					<Vertex X="2616" Y="1216" Z="0"/>
					<Vertex X="2612" Y="1220" Z="0"/>
					<Vertex X="2608" Y="1223" Z="0"/>
					<Vertex X="2604" Y="1227" Z="0"/>
					<Vertex X="2600" Y="1230" Z="0"/>
					<Vertex X="2595" Y="1234" Z="0"/>
					<Vertex X="2590" Y="1239" Z="0"/>
					<Vertex X="2585" Y="1243" Z="0"/>
					<Vertex X="2581" Y="1247" Z="0"/>
					<Vertex X="2577" Y="1250" Z="0"/>
					<Vertex X="2573" Y="1253" Z="0"/>
					<Vertex X="2569" Y="1257" Z="0"/>
					<Vertex X="2565" Y="1260" Z="0"/>
					<Vertex X="2561" Y="1263" Z="0"/>
					<Vertex X="2557" Y="1267" Z="0"/>
					<Vertex X="2553" Y="1270" Z="0"/>
					<Vertex X="2549" Y="1273" Z="0"/>
					<Vertex X="2545" Y="1276" Z="0"/>
					<Vertex X="2540" Y="1279" Z="0"/>
					<Vertex X="2536" Y="1281" Z="0"/>
					<Vertex X="2532" Y="1283" Z="0"/>
					<Vertex X="2528" Y="1285" Z="0"/>
					<Vertex X="2524" Y="1286" Z="0"/>
					<Vertex X="2520" Y="1286" Z="0"/>
					<Vertex X="2517" Y="1287" Z="0"/>
					<Vertex X="2513" Y="1287" Z="0"/>
					<Vertex X="2510" Y="1287" Z="0"/>
					<Vertex X="2507" Y="1287" Z="0"/>
					<Vertex X="2504" Y="1287" Z="0"/>
					<Vertex X="2500" Y="1287" Z="0"/>
					<Vertex X="2497" Y="1286" Z="0"/>
					<Vertex X="2494" Y="1286" Z="0"/>
					<Vertex X="2491" Y="1285" Z="0"/>
					<Vertex X="2489" Y="1284" Z="0"/>
					<Vertex X="2486" Y="1283" Z="0"/>
					<Vertex X="2483" Y="1282" Z="0"/>
					<Vertex X="2480" Y="1281" Z="0"/>
					<Vertex X="2477" Y="1280" Z="0"/>
					<Vertex X="2475" Y="1279" Z="0"/>
					<Vertex X="2472" Y="1278" Z="0"/>
					<Vertex X="2470" Y="1277" Z="0"/>
					<Vertex X="2468" Y="1276" Z="0"/>
					<Vertex X="2466" Y="1276" Z="0"/>
					<Vertex X="2464" Y="1275" Z="0"/>
					<Vertex X="2462" Y="1274" Z="0"/>
					<Vertex X="2461" Y="1274" Z="0"/>
					<Vertex X="2459" Y="1273" Z="0"/>
					<Vertex X="2457" Y="1272" Z="0"/>
					<Vertex X="2455" Y="1272" Z="0"/>
					<Vertex X="2453" Y="1272" Z="0"/>
					<Vertex X="2451" Y="1272" Z="0"/>
					<Vertex X="2449" Y="1272" Z="0"/>
					<Vertex X="2447" Y="1272" Z="0"/>
					<Vertex X="2444" Y="1272" Z="0"/>
					<Vertex X="2442" Y="1273" Z="0"/>
					<Vertex X="2440" Y="1273" Z="0"/>
					<Vertex X="2438" Y="1274" Z="0"/>
					<Vertex X="2436" Y="1274" Z="0"/>
					<Vertex X="2434" Y="1275" Z="0"/>
					<Vertex X="2433" Y="1276" Z="0"/>
					<Vertex X="2431" Y="1276" Z="0"/>
					<Vertex X="2429" Y="1277" Z="0"/>
					<Vertex X="2427" Y="1278" Z="0"/>
					<Vertex X="2425" Y="1279" Z="0"/>
					<Vertex X="2423" Y="1280" Z="0"/>
					<Vertex X="2421" Y="1281" Z="0"/>
					<Vertex X="2419" Y="1283" Z="0"/>
					<Vertex X="2416" Y="1284" Z="0"/>
					<Vertex X="2414" Y="1286" Z="0"/>
					<Vertex X="2412" Y="1287" Z="0"/>
					<Vertex X="2410" Y="1289" Z="0"/>
					<Vertex X="2408" Y="1291" Z="0"/>
					<Vertex X="2406" Y="1292" Z="0"/>
					<Vertex X="2403" Y="1294" Z="0"/>
					<Vertex X="2401" Y="1297" Z="0"/>
					<Vertex X="2399" Y="1298" Z="0"/>
					<Vertex X="2397" Y="1301" Z="0"/>
					<Vertex X="2395" Y="1303" Z="0"/>
					<Vertex X="2393" Y="1306" Z="0"/>
					<Vertex X="2391" Y="1308" Z="0"/>
					<Vertex X="2389" Y="1310" Z="0"/>
					<Vertex X="2388" Y="1311" Z="0"/>
					<Vertex X="2387" Y="1314" Z="0"/>
					<Vertex X="2385" Y="1316" Z="0"/>
					<Vertex X="2384" Y="1317" Z="0"/>
					<Vertex X="2382" Y="1319" Z="0"/>
					<Vertex X="2381" Y="1321" Z="0"/>
					<Vertex X="2380" Y="1323" Z="0"/>
					<Vertex X="2379" Y="1324" Z="0"/>
					<Vertex X="2378" Y="1326" Z="0"/>
					<Vertex X="2376" Y="1328" Z="0"/>
					<Vertex X="2375" Y="1329" Z="0"/>
					<Vertex X="2373" Y="1331" Z="0"/>
					<Vertex X="2372" Y="1333" Z="0"/>
					<Vertex X="2370" Y="1334" Z="0"/>
					<Vertex X="2368" Y="1336" Z="0"/>
					<Vertex X="2367" Y="1337" Z="0"/>
					<Vertex X="2365" Y="1339" Z="0"/>
					<Vertex X="2363" Y="1340" Z="0"/>
					<Vertex X="2361" Y="1341" Z="0"/>
					<Vertex X="2359" Y="1342" Z="0"/>
					<Vertex X="2357" Y="1344" Z="0"/>
					<Vertex X="2355" Y="1345" Z="0"/>
					<Vertex X="2353" Y="1346" Z="0"/>
					<Vertex X="2352" Y="1347" Z="0"/>
					<Vertex X="2350" Y="1348" Z="0"/>
					<Vertex X="2348" Y="1349" Z="0"/>
					<Vertex X="2346" Y="1350" Z="0"/>
					<Vertex X="2344" Y="1351" Z="0"/>
					<Vertex X="2342" Y="1352" Z="0"/>
					<Vertex X="2340" Y="1353" Z="0"/>
					<Vertex X="2338" Y="1353" Z="0"/>
					<Vertex X="2335" Y="1354" Z="0"/>
					<Vertex X="2332" Y="1355" Z="0"/>
					<Vertex X="2329" Y="1355" Z="0"/>
					<Vertex X="2327" Y="1356" Z="0"/>
					<Vertex X="2324" Y="1356" Z="0"/>
					<Vertex X="2322" Y="1356" Z="0"/>
					<Vertex X="2320" Y="1357" Z="0"/>
					<Vertex X="2317" Y="1357" Z="0"/>
					<Vertex X="2315" Y="1357" Z="0"/>
					<Vertex X="2313" Y="1357" Z="0"/>
					<Vertex X="2310" Y="1357" Z="0"/>
					<Vertex X="2309" Y="1357" Z="0"/>
					<Vertex X="2307" Y="1357" Z="0"/>
					<Vertex X="2305" Y="1357" Z="0"/>
					<Vertex X="2303" Y="1357" Z="0"/>
					<Vertex X="2301" Y="1357" Z="0"/>
					<Vertex X="2300" Y="1357" Z="0"/>
					<Vertex X="2298" Y="1357" Z="0"/>
					<Vertex X="2296" Y="1357" Z="0"/>
					<Vertex X="2294" Y="1357" Z="0"/>
					<Vertex X="2292" Y="1357" Z="0"/>
					<Vertex X="2291" Y="1357" Z="0"/>
					<Vertex X="2289" Y="1357" Z="0"/>
					<Vertex X="2287" Y="1357" Z="0"/>
					<Vertex X="2285" Y="1357" Z="0"/>
					<Vertex X="2283" Y="1357" Z="0"/>
					<Vertex X="2281" Y="1357" Z="0"/>
					<Vertex X="2279" Y="1357" Z="0"/>
					<Vertex X="2277" Y="1356" Z="0"/>
					<Vertex X="2275" Y="1356" Z="0"/>
					<Vertex X="2272" Y="1356" Z="0"/>
					<Vertex X="2270" Y="1356" Z="0"/>
					<Vertex X="2267" Y="1355" Z="0"/>
					<Vertex X="2264" Y="1354" Z="0"/>
					<Vertex X="2261" Y="1353" Z="0"/>
					<Vertex X="2257" Y="1352" Z="0"/>
					<Vertex X="2254" Y="1351" Z="0"/>
					<Vertex X="2250" Y="1350" Z="0"/>
					<Vertex X="2247" Y="1349" Z="0"/>
					<Vertex X="2244" Y="1348" Z="0"/>
					<Vertex X="2242" Y="1346" Z="0"/>
					<Vertex X="2240" Y="1345" Z="0"/>
					<Vertex X="2238" Y="1343" Z="0"/>
					<Vertex X="2236" Y="1342" Z="0"/>
					<Vertex X="2235" Y="1340" Z="0"/>
					<Vertex X="2232" Y="1339" Z="0"/>
					<Vertex X="2231" Y="1337" Z="0"/>
					<Vertex X="2228" Y="1335" Z="0"/>
					<Vertex X="2225" Y="1333" Z="0"/>
					<Vertex X="2222" Y="1331" Z="0"/>
					<Vertex X="2220" Y="1329" Z="0"/>
					<Vertex X="2218" Y="1327" Z="0"/>
					<Vertex X="2215" Y="1326" Z="0"/>
					<Vertex X="2214" Y="1324" Z="0"/>
					<Vertex X="2212" Y="1323" Z="0"/>
					<Vertex X="2210" Y="1322" Z="0"/>
					<Vertex X="2209" Y="1321" Z="0"/>
					<Vertex X="2207" Y="1320" Z="0"/>
					<Vertex X="2206" Y="1319" Z="0"/>
					<Vertex X="2205" Y="1318" Z="0"/>
					<Vertex X="2203" Y="1317" Z="0"/>
					<Vertex X="2201" Y="1316" Z="0"/>
					<Vertex X="2199" Y="1315" Z="0"/>
					<Vertex X="2197" Y="1315" Z="0"/>
					<Vertex X="2195" Y="1314" Z="0"/>
					<Vertex X="2193" Y="1313" Z="0"/>
					<Vertex X="2191" Y="1313" Z="0"/>
					<Vertex X="2190" Y="1312" Z="0"/>
					<Vertex X="2188" Y="1312" Z="0"/>
					<Vertex X="2187" Y="1312" Z="0"/>
					<Vertex X="2186" Y="1311" Z="0"/>
					<Vertex X="2184" Y="1311" Z="0"/>
					<Vertex X="2183" Y="1311" Z="0"/>
					<Vertex X="2181" Y="1311" Z="0"/>
					<Vertex X="2180" Y="1311" Z="0"/>
					<Vertex X="2178" Y="1311" Z="0"/>
					<Vertex X="2177" Y="1312" Z="0"/>
					<Vertex X="2176" Y="1312" Z="0"/>
					<Vertex X="2175" Y="1312" Z="0"/>
					<Vertex X="2173" Y="1313" Z="0"/>
					<Vertex X="2172" Y="1314" Z="0"/>
					<Vertex X="2170" Y="1315" Z="0"/>
					<Vertex X="2168" Y="1315" Z="0"/>
					<Vertex X="2167" Y="1316" Z="0"/>
					<Vertex X="2165" Y="1317" Z="0"/>
					<Vertex X="2164" Y="1318" Z="0"/>
					<Vertex X="2162" Y="1318" Z="0"/>
					<Vertex X="2161" Y="1320" Z="0"/>
					<Vertex X="2159" Y="1321" Z="0"/>
					<Vertex X="2158" Y="1322" Z="0"/>
					<Vertex X="2157" Y="1323" Z="0"/>
					<Vertex X="2156" Y="1324" Z="0"/>
					<Vertex X="2155" Y="1324" Z="0"/>
					<Vertex X="2154" Y="1325" Z="0"/>
					<Vertex X="2153" Y="1326" Z="0"/>
					<Vertex X="2152" Y="1326" Z="0"/>
					<Vertex X="2152" Y="1327" Z="0"/>
					<Vertex X="2151" Y="1328" Z="0"/>
					<Vertex X="2151" Y="1329" Z="0"/>
					<Vertex X="2150" Y="1329" Z="0"/>
					<Vertex X="2150" Y="1330" Z="0"/>
					<Vertex X="2149" Y="1331" Z="0"/>
					<Vertex X="2149" Y="1330" Z="0"/>
					<Vertex X="2149" Y="1331" Z="0"/>
					<Vertex X="2149" Y="1332" Z="0"/>
					<Vertex X="2149" Y="1331" Z="0"/>
					<Vertex X="2147" Y="1333" Z="0"/>
					<Vertex X="2145" Y="1334" Z="0"/>
					<Vertex X="2143" Y="1336" Z="0"/>
					<Vertex X="2141" Y="1338" Z="0"/>
					<Vertex X="2139" Y="1340" Z="0"/>
					<Vertex X="2137" Y="1342" Z="0"/>
					<Vertex X="2135" Y="1344" Z="0"/>
					<Vertex X="2132" Y="1346" Z="0"/>
					<Vertex X="2130" Y="1347" Z="0"/>
					<Vertex X="2128" Y="1349" Z="0"/>
					<Vertex X="2126" Y="1350" Z="0"/>
					<Vertex X="2124" Y="1352" Z="0"/>
					<Vertex X="2122" Y="1353" Z="0"/>
					<Vertex X="2120" Y="1355" Z="0"/>
					<Vertex X="2119" Y="1356" Z="0"/>
					<Vertex X="2117" Y="1358" Z="0"/>
					<Vertex X="2115" Y="1360" Z="0"/>
					<Vertex X="2113" Y="1361" Z="0"/>
					<Vertex X="2112" Y="1363" Z="0"/>
					<Vertex X="2110" Y="1365" Z="0"/>
					<Vertex X="2109" Y="1367" Z="0"/>
					<Vertex X="2107" Y="1369" Z="0"/>
					<Vertex X="2106" Y="1371" Z="0"/>
					<Vertex X="2105" Y="1373" Z="0"/>
					<Vertex X="2103" Y="1375" Z="0"/>
					<Vertex X="2102" Y="1376" Z="0"/>
					<Vertex X="2100" Y="1378" Z="0"/>
					<Vertex X="2098" Y="1381" Z="0"/>
					<Vertex X="2096" Y="1383" Z="0"/>
					<Vertex X="2095" Y="1386" Z="0"/>
					<Vertex X="2093" Y="1388" Z="0"/>
					<Vertex X="2092" Y="1390" Z="0"/>
					<Vertex X="2091" Y="1392" Z="0"/>
					<Vertex X="2089" Y="1394" Z="0"/>
					<Vertex X="2088" Y="1396" Z="0"/>
					<Vertex X="2088" Y="1398" Z="0"/>
					<Vertex X="2087" Y="1400" Z="0"/>
					<Vertex X="2086" Y="1403" Z="0"/>
					<Vertex X="2085" Y="1406" Z="0"/>
					<Vertex X="2084" Y="1409" Z="0"/>
					<Vertex X="2083" Y="1412" Z="0"/>
					<Vertex X="2082" Y="1415" Z="0"/>
					<Vertex X="2081" Y="1417" Z="0"/>
					<Vertex X="2080" Y="1419" Z="0"/>
					<Vertex X="2080" Y="1421" Z="0"/>
					<Vertex X="2080" Y="1422" Z="0"/>
					<Vertex X="2080" Y="1423" Z="0"/>
					<Vertex X="2079" Y="1425" Z="0"/>
					<Vertex X="2079" Y="1426" Z="0"/>
					<Vertex X="2078" Y="1428" Z="0"/>
					<Vertex X="2077" Y="1431" Z="0"/>
					<Vertex X="2075" Y="1434" Z="0"/>
					<Vertex X="2073" Y="1437" Z="0"/>
					<Vertex X="2071" Y="1439" Z="0"/>
					<Vertex X="2069" Y="1443" Z="0"/>
					<Vertex X="2066" Y="1445" Z="0"/>
					<Vertex X="2063" Y="1447" Z="0"/>
					<Vertex X="2061" Y="1449" Z="0"/>
					<Vertex X="2058" Y="1451" Z="0"/>
					<Vertex X="2056" Y="1451" Z="0"/>
					<Vertex X="2053" Y="1453" Z="0"/>
					<Vertex X="2052" Y="1453" Z="0"/>
					<Vertex X="2049" Y="1453" Z="0"/>
					<Vertex X="2048" Y="1453" Z="0"/>
					<Vertex X="2046" Y="1454" Z="0"/>
					<Vertex X="2044" Y="1454" Z="0"/>
					<Vertex X="2043" Y="1453" Z="0"/>
					<Vertex X="2041" Y="1452" Z="0"/>
					<Vertex X="2039" Y="1451" Z="0"/>
					<Vertex X="2038" Y="1450" Z="0"/>
					<Vertex X="2037" Y="1450" Z="0"/>
					<Vertex X="2035" Y="1449" Z="0"/>
					<Vertex X="2034" Y="1449" Z="0"/>
					<Vertex X="2033" Y="1450" Z="0"/>
					<Vertex X="2031" Y="1450" Z="0"/>
					<Vertex X="2030" Y="1451" Z="0"/>
					<Vertex X="2029" Y="1451" Z="0"/>
					<Vertex X="2028" Y="1451" Z="0"/>
					<Vertex X="2027" Y="1452" Z="0"/>
					<Vertex X="2027" Y="1454" Z="0"/>
					<Vertex X="2027" Y="1455" Z="0"/>
					<Vertex X="2027" Y="1457" Z="0"/>
					<Vertex X="2027" Y="1459" Z="0"/>
					<Vertex X="2028" Y="1460" Z="0"/>
					<Vertex X="2029" Y="1461" Z="0"/>
					<Vertex X="2030" Y="1462" Z="0"/>
					<Vertex X="2031" Y="1463" Z="0"/>
					<Vertex X="2032" Y="1464" Z="0"/>
					<Vertex X="2034" Y="1465" Z="0"/>
					<Vertex X="2036" Y="1466" Z="0"/>
					<Vertex X="2038" Y="1468" Z="0"/>
					<Vertex X="2040" Y="1469" Z="0"/>
					<Vertex X="2042" Y="1470" Z="0"/>
					<Vertex X="2045" Y="1472" Z="0"/>
					<Vertex X="2047" Y="1472" Z="0"/>
					<Vertex X="2049" Y="1474" Z="0"/>
					<Vertex X="2050" Y="1475" Z="0"/>
					<Vertex X="2052" Y="1475" Z="0"/>
					<Vertex X="2053" Y="1476" Z="0"/>
					<Vertex X="2055" Y="1478" Z="0"/>
					<Vertex X="2056" Y="1479" Z="0"/>
					<Vertex X="2056" Y="1481" Z="0"/>
					<Vertex X="2057" Y="1482" Z="0"/>
					<Vertex X="2057" Y="1484" Z="0"/>
					<Vertex X="2057" Y="1486" Z="0"/>
					<Vertex X="2057" Y="1487" Z="0"/>
					<Vertex X="2057" Y="1489" Z="0"/>
					<Vertex X="2057" Y="1490" Z="0"/>
					<Vertex X="2056" Y="1492" Z="0"/>
					<Vertex X="2055" Y="1493" Z="0"/>
					<Vertex X="2054" Y="1494" Z="0"/>
					<Vertex X="2053" Y="1495" Z="0"/>
					<Vertex X="2051" Y="1496" Z="0"/>
					<Vertex X="2050" Y="1496" Z="0"/>
					<Vertex X="2048" Y="1496" Z="0"/>
					<Vertex X="2046" Y="1496" Z="0"/>
					<Vertex X="2044" Y="1496" Z="0"/>
					<Vertex X="2043" Y="1496" Z="0"/>
					<Vertex X="2042" Y="1496" Z="0"/>
					<Vertex X="2040" Y="1496" Z="0"/>
					<Vertex X="2039" Y="1496" Z="0"/>
					<Vertex X="2037" Y="1496" Z="0"/>
					<Vertex X="2036" Y="1496" Z="0"/>
					<Vertex X="2035" Y="1496" Z="0"/>
					<Vertex X="2034" Y="1496" Z="0"/>
					<Vertex X="2032" Y="1496" Z="0"/>
					<Vertex X="2030" Y="1496" Z="0"/>
					<Vertex X="2029" Y="1497" Z="0"/>
					<Vertex X="2027" Y="1497" Z="0"/>
					<Vertex X="2025" Y="1497" Z="0"/>
					<Vertex X="2024" Y="1497" Z="0"/>
					<Vertex X="2022" Y="1497" Z="0"/>
					<Vertex X="2020" Y="1497" Z="0"/>
					<Vertex X="2018" Y="1497" Z="0"/>
					<Vertex X="2017" Y="1497" Z="0"/>
					<Vertex X="2015" Y="1498" Z="0"/>
					<Vertex X="2014" Y="1498" Z="0"/>
					<Vertex X="2012" Y="1498" Z="0"/>
					<Vertex X="2011" Y="1498" Z="0"/>
					<Vertex X="2010" Y="1498" Z="0"/>
					<Vertex X="2009" Y="1497" Z="0"/>
					<Vertex X="2008" Y="1497" Z="0"/>
					<Vertex X="2007" Y="1497" Z="0"/>
					<Vertex X="2006" Y="1497" Z="0"/>
					<Vertex X="2005" Y="1497" Z="0"/>
					<Vertex X="2004" Y="1497" Z="0"/>
					<Vertex X="2003" Y="1496" Z="0"/>
					<Vertex X="2002" Y="1496" Z="0"/>
					<Vertex X="2001" Y="1496" Z="0"/>
					<Vertex X="2000" Y="1496" Z="0"/>
					<Vertex X="1999" Y="1496" Z="0"/>
					<Vertex X="1998" Y="1496" Z="0"/>
					<Vertex X="1997" Y="1496" Z="0"/>
					<Vertex X="1996" Y="1496" Z="0"/>
					<Vertex X="1995" Y="1496" Z="0"/>
					<Vertex X="1994" Y="1497" Z="0"/>
					<Vertex X="1992" Y="1498" Z="0"/>
					<Vertex X="1991" Y="1499" Z="0"/>
					<Vertex X="1989" Y="1501" Z="0"/>
					<Vertex X="1988" Y="1503" Z="0"/>
					<Vertex X="1987" Y="1505" Z="0"/>
					<Vertex X="1986" Y="1507" Z="0"/>
					<Vertex X="1985" Y="1507" Z="0"/>
					<Vertex X="1985" Y="1508" Z="0"/>
					<Vertex X="1985" Y="1509" Z="0"/>
					<Vertex X="1985" Y="1511" Z="0"/>
					<Vertex X="1985" Y="1512" Z="0"/>
					<Vertex X="1985" Y="1513" Z="0"/>
					<Vertex X="1985" Y="1514" Z="0"/>
					<Vertex X="1986" Y="1516" Z="0"/>
					<Vertex X="1986" Y="1518" Z="0"/>
					<Vertex X="1986" Y="1519" Z="0"/>
					<Vertex X="1986" Y="1521" Z="0"/>
					<Vertex X="1986" Y="1522" Z="0"/>
					<Vertex X="1987" Y="1525" Z="0"/>
					<Vertex X="1987" Y="1527" Z="0"/>
					<Vertex X="1988" Y="1528" Z="0"/>
					<Vertex X="1989" Y="1529" Z="0"/>
					<Vertex X="1990" Y="1531" Z="0"/>
					<Vertex X="1991" Y="1533" Z="0"/>
					<Vertex X="1992" Y="1534" Z="0"/>
					<Vertex X="1993" Y="1535" Z="0"/>
					<Vertex X="1994" Y="1536" Z="0"/>
					<Vertex X="1995" Y="1537" Z="0"/>
					<Vertex X="1995" Y="1539" Z="0"/>
					<Vertex X="1996" Y="1539" Z="0"/>
					<Vertex X="1996" Y="1541" Z="0"/>
					<Vertex X="1996" Y="1542" Z="0"/>
					<Vertex X="1996" Y="1543" Z="0"/>
					<Vertex X="1996" Y="1544" Z="0"/>
					<Vertex X="1996" Y="1545" Z="0"/>
					<Vertex X="1996" Y="1546" Z="0"/>
					<Vertex X="1996" Y="1547" Z="0"/>
					<Vertex X="1996" Y="1548" Z="0"/>
					<Vertex X="1996" Y="1549" Z="0"/>
					<Vertex X="1995" Y="1549" Z="0"/>
					<Vertex X="1995" Y="1550" Z="0"/>
					<Vertex X="1994" Y="1550" Z="0"/>
					<Vertex X="1993" Y="1551" Z="0"/>
					<Vertex X="1992" Y="1551" Z="0"/>
					<Vertex X="1991" Y="1552" Z="0"/>
					<Vertex X="1989" Y="1553" Z="0"/>
					<Vertex X="1988" Y="1554" Z="0"/>
					<Vertex X="1986" Y="1555" Z="0"/>
					<Vertex X="1984" Y="1556" Z="0"/>
					<Vertex X="1983" Y="1556" Z="0"/>
					<Vertex X="1982" Y="1557" Z="0"/>
					<Vertex X="1981" Y="1557" Z="0"/>
					<Vertex X="1980" Y="1557" Z="0"/>
					<Vertex X="1979" Y="1557" Z="0"/>
					<Vertex X="1977" Y="1557" Z="0"/>
					<Vertex X="1976" Y="1557" Z="0"/>
					<Vertex X="1975" Y="1557" Z="0"/>
					<Vertex X="1973" Y="1557" Z="0"/>
					<Vertex X="1972" Y="1557" Z="0"/>
					<Vertex X="1971" Y="1557" Z="0"/>
					<Vertex X="1969" Y="1556" Z="0"/>
					<Vertex X="1968" Y="1556" Z="0"/>
					<Vertex X="1967" Y="1556" Z="0"/>
					<Vertex X="1965" Y="1555" Z="0"/>
					<Vertex X="1963" Y="1555" Z="0"/>
					<Vertex X="1962" Y="1555" Z="0"/>
					<Vertex X="1961" Y="1555" Z="0"/>
					<Vertex X="1959" Y="1554" Z="0"/>
					<Vertex X="1958" Y="1553" Z="0"/>
					<Vertex X="1957" Y="1552" Z="0"/>
					<Vertex X="1956" Y="1552" Z="0"/>
					<Vertex X="1954" Y="1551" Z="0"/>
					<Vertex X="1953" Y="1551" Z="0"/>
					<Vertex X="1952" Y="1550" Z="0"/>
					<Vertex X="1951" Y="1549" Z="0"/>
					<Vertex X="1950" Y="1549" Z="0"/>
					<Vertex X="1949" Y="1548" Z="0"/>
					<Vertex X="1948" Y="1548" Z="0"/>
					<Vertex X="1947" Y="1547" Z="0"/>
					<Vertex X="1946" Y="1547" Z="0"/>
					<Vertex X="1945" Y="1546" Z="0"/>
					<Vertex X="1944" Y="1546" Z="0"/>
					<Vertex X="1943" Y="1545" Z="0"/>
					<Vertex X="1942" Y="1544" Z="0"/>
					<Vertex X="1941" Y="1543" Z="0"/>
					<Vertex X="1941" Y="1542" Z="0"/>
					<Vertex X="1940" Y="1541" Z="0"/>
					<Vertex X="1939" Y="1540" Z="0"/>
					<Vertex X="1939" Y="1539" Z="0"/>
					<Vertex X="1938" Y="1538" Z="0"/>
					<Vertex X="1938" Y="1537" Z="0"/>
					<Vertex X="1937" Y="1536" Z="0"/>
					<Vertex X="1936" Y="1534" Z="0"/>
					<Vertex X="1935" Y="1532" Z="0"/>
					<Vertex X="1935" Y="1531" Z="0"/>
					<Vertex X="1934" Y="1530" Z="0"/>
					<Vertex X="1933" Y="1528" Z="0"/>
					<Vertex X="1932" Y="1526" Z="0"/>
					<Vertex X="1931" Y="1525" Z="0"/>
					<Vertex X="1930" Y="1524" Z="0"/>
					<Vertex X="1930" Y="1522" Z="0"/>
					<Vertex X="1929" Y="1520" Z="0"/>
					<Vertex X="1928" Y="1519" Z="0"/>
					<Vertex X="1928" Y="1517" Z="0"/>
					<Vertex X="1927" Y="1516" Z="0"/>
					<Vertex X="1926" Y="1514" Z="0"/>
					<Vertex X="1926" Y="1512" Z="0"/>
					<Vertex X="1925" Y="1511" Z="0"/>
					<Vertex X="1924" Y="1508" Z="0"/>
					<Vertex X="1924" Y="1507" Z="0"/>
					<Vertex X="1923" Y="1505" Z="0"/>
					<Vertex X="1923" Y="1502" Z="0"/>
					<Vertex X="1922" Y="1500" Z="0"/>
					<Vertex X="1921" Y="1498" Z="0"/>
					<Vertex X="1920" Y="1495" Z="0"/>
					<Vertex X="1920" Y="1494" Z="0"/>
					<Vertex X="1919" Y="1492" Z="0"/>
					<Vertex X="1919" Y="1489" Z="0"/>
					<Vertex X="1918" Y="1487" Z="0"/>
					<Vertex X="1918" Y="1486" Z="0"/>
					<Vertex X="1917" Y="1484" Z="0"/>
					<Vertex X="1916" Y="1481" Z="0"/>
					<Vertex X="1916" Y="1479" Z="0"/>
					<Vertex X="1915" Y="1477" Z="0"/>
					<Vertex X="1914" Y="1475" Z="0"/>
					<Vertex X="1914" Y="1472" Z="0"/>
					<Vertex X="1913" Y="1470" Z="0"/>
					<Vertex X="1913" Y="1469" Z="0"/>
					<Vertex X="1912" Y="1466" Z="0"/>
					<Vertex X="1912" Y="1463" Z="0"/>
					<Vertex X="1911" Y="1461" Z="0"/>
					<Vertex X="1911" Y="1459" Z="0"/>
					<Vertex X="1910" Y="1456" Z="0"/>
					<Vertex X="1910" Y="1454" Z="0"/>
					<Vertex X="1910" Y="1452" Z="0"/>
					<Vertex X="1909" Y="1450" Z="0"/>
					<Vertex X="1909" Y="1448" Z="0"/>
					<Vertex X="1909" Y="1446" Z="0"/>
					<Vertex X="1908" Y="1444" Z="0"/>
					<Vertex X="1908" Y="1441" Z="0"/>
					<Vertex X="1908" Y="1439" Z="0"/>
					<Vertex X="1908" Y="1437" Z="0"/>
					<Vertex X="1908" Y="1434" Z="0"/>
					<Vertex X="1908" Y="1431" Z="0"/>
					<Vertex X="1908" Y="1428" Z="0"/>
					<Vertex X="1908" Y="1425" Z="0"/>
					<Vertex X="1908" Y="1422" Z="0"/>
					<Vertex X="1908" Y="1419" Z="0"/>
					<Vertex X="1908" Y="1417" Z="0"/>
					<Vertex X="1909" Y="1413" Z="0"/>
					<Vertex X="1909" Y="1410" Z="0"/>
					<Vertex X="1909" Y="1407" Z="0"/>
					<Vertex X="1909" Y="1404" Z="0"/>
					<Vertex X="1909" Y="1401" Z="0"/>
					<Vertex X="1910" Y="1397" Z="0"/>
					<Vertex X="1910" Y="1395" Z="0"/>
					<Vertex X="1910" Y="1391" Z="0"/>
					<Vertex X="1910" Y="1390" Z="0"/>
					<Vertex X="1910" Y="1387" Z="0"/>
					<Vertex X="1910" Y="1385" Z="0"/>
					<Vertex X="1911" Y="1383" Z="0"/>
					<Vertex X="1911" Y="1381" Z="0"/>
					<Vertex X="1911" Y="1377" Z="0"/>
					<Vertex X="1912" Y="1374" Z="0"/>
					<Vertex X="1912" Y="1371" Z="0"/>
					<Vertex X="1912" Y="1366" Z="0"/>
					<Vertex X="1913" Y="1364" Z="0"/>
					<Vertex X="1913" Y="1361" Z="0"/>
					<Vertex X="1914" Y="1359" Z="0"/>
					<Vertex X="1914" Y="1356" Z="0"/>
					<Vertex X="1914" Y="1354" Z="0"/>
					<Vertex X="1914" Y="1351" Z="0"/>
					<Vertex X="1915" Y="1349" Z="0"/>
					<Vertex X="1915" Y="1346" Z="0"/>
					<Vertex X="1915" Y="1344" Z="0"/>
					<Vertex X="1916" Y="1341" Z="0"/>
					<Vertex X="1916" Y="1339" Z="0"/>
					<Vertex X="1916" Y="1336" Z="0"/>
					<Vertex X="1917" Y="1333" Z="0"/>
					<Vertex X="1917" Y="1330" Z="0"/>
					<Vertex X="1917" Y="1327" Z="0"/>
					<Vertex X="1917" Y="1324" Z="0"/>
					<Vertex X="1917" Y="1321" Z="0"/>
					<Vertex X="1918" Y="1318" Z="0"/>
					<Vertex X="1918" Y="1315" Z="0"/>
					<Vertex X="1918" Y="1311" Z="0"/>
					<Vertex X="1919" Y="1308" Z="0"/>
					<Vertex X="1919" Y="1305" Z="0"/>
					<Vertex X="1919" Y="1302" Z="0"/>
					<Vertex X="1919" Y="1298" Z="0"/>
					<Vertex X="1920" Y="1295" Z="0"/>
					<Vertex X="1920" Y="1291" Z="0"/>
					<Vertex X="1920" Y="1289" Z="0"/>
					<Vertex X="1920" Y="1285" Z="0"/>
					<Vertex X="1921" Y="1281" Z="0"/>
					<Vertex X="1921" Y="1278" Z="0"/>
					<Vertex X="1922" Y="1275" Z="0"/>
					<Vertex X="1923" Y="1271" Z="0"/>
					<Vertex X="1923" Y="1268" Z="0"/>
					<Vertex X="1924" Y="1264" Z="0"/>
					<Vertex X="1925" Y="1260" Z="0"/>
					<Vertex X="1925" Y="1257" Z="0"/>
					<Vertex X="1926" Y="1254" Z="0"/>
					<Vertex X="1926" Y="1251" Z="0"/>
					<Vertex X="1927" Y="1248" Z="0"/>
					<Vertex X="1927" Y="1245" Z="0"/>
					<Vertex X="1927" Y="1242" Z="0"/>
					<Vertex X="1928" Y="1239" Z="0"/>
					<Vertex X="1928" Y="1236" Z="0"/>
					<Vertex X="1928" Y="1233" Z="0"/>
					<Vertex X="1928" Y="1231" Z="0"/>
					<Vertex X="1928" Y="1228" Z="0"/>
					<Vertex X="1929" Y="1225" Z="0"/>
					<Vertex X="1929" Y="1222" Z="0"/>
					<Vertex X="1929" Y="1220" Z="0"/>
					<Vertex X="1930" Y="1218" Z="0"/>
					<Vertex X="1930" Y="1215" Z="0"/>
					<Vertex X="1931" Y="1213" Z="0"/>
					<Vertex X="1931" Y="1211" Z="0"/>
					<Vertex X="1932" Y="1208" Z="0"/>
					<Vertex X="1932" Y="1206" Z="0"/>
					<Vertex X="1933" Y="1204" Z="0"/>
					<Vertex X="1934" Y="1200" Z="0"/>
					<Vertex X="1935" Y="1198" Z="0"/>
					<Vertex X="1936" Y="1195" Z="0"/>
					<Vertex X="1937" Y="1193" Z="0"/>
					<Vertex X="1937" Y="1191" Z="0"/>
					<Vertex X="1938" Y="1189" Z="0"/>
					<Vertex X="1938" Y="1187" Z="0"/>
					<Vertex X="1939" Y="1185" Z="0"/>
					<Vertex X="1939" Y="1183" Z="0"/>
					<Vertex X="1940" Y="1182" Z="0"/>
					<Vertex X="1941" Y="1180" Z="0"/>
					<Vertex X="1942" Y="1178" Z="0"/>
					<Vertex X="1942" Y="1176" Z="0"/>
					<Vertex X="1943" Y="1174" Z="0"/>
					<Vertex X="1944" Y="1172" Z="0"/>
					<Vertex X="1945" Y="1170" Z="0"/>
					<Vertex X="1946" Y="1168" Z="0"/>
					<Vertex X="1948" Y="1165" Z="0"/>
					<Vertex X="1949" Y="1162" Z="0"/>
				</Vertices>
			</Region>
		</Regions>
		<Plots/>
	</Annotation>
</Annotations>
